Workbook

Sheet Dashboard
B2: HR Analytics Dashboard
B3: Workforce · Attrition · Performance · Engagement · Compliance · Attendance · Recruitment | All KPIs are live formulas over the data sheets.
B5: TOTAL EMPLOYEES | E5: ACTIVE EMPLOYEES | H5: TOTAL EXITS | K5: OVERALL ATTRITION | N5: % FEMALE | Q5: AVG CTC (ACTIVE)
B6: =COUNTA(Employees!$A$2:$A$1501) -> 1500 | E6: =COUNTIF(Employees!$U$2:$U$1501,"Active") -> 1237 | H6: =COUNTA(Attrition!$A$2:$A$264) -> 263 | K6: =COUNTA(Attrition!$A$2:$A$264)/COUNTA(Employees!$A$2:$A$1501) -> 0.17533333 | N6: =COUNTIF(Employees!$D$2:$D$1501,"Female")/COUNTA(Employees!$A$2:$A$1501) -> 0.44733333 | Q6: =AVERAGEIFS(Employees!$P$2:$P$1501,Employees!$U$2:$U$1501,"Active") -> 1962206.1
B8: AVG PERF RATING (1-5) | E8: eNPS (2026) | H8: TRAINING COMPLETION | K8: ATTENDANCE RATE | N8: AVG TIME-TO-HIRE (DAYS) | Q8: AVG COST PER HIRE
B9: =AVERAGE(Performance!$C$2:$C$3701) -> 2.7616216 | E9: =(COUNTIFS(Engagement!$B$2:$B$2375,2026,Engagement!$H$2:$H$2375,">=9")-COUNTIFS(Engagement!$B$2:$B$2375,2026,Engagement!$H$2:$H$2375,"<=6"))/COUNTIF(Engagement!$B$2:$B$2375,2026)*100 -> -1.6556291 | H9: =COUNTIF(Compliance_Trainings!$E$2:$E$7423,"Completed")/COUNTA(Compliance_Trainings!$A$2:$A$7423) -> 0.75249259 | K9: =SUM(Attendance!$D$2:$D$13892)/SUM(Attendance!$C$2:$C$13892) -> 0.92955216 | N9: =AVERAGE(Recruitment!$N$2:$N$1501) -> 53.783333 | Q9: =AVERAGE(Recruitment!$K$2:$K$1501) -> 36392.794
B68: Key Insights
B69: • Attrition: 17.5% overall (263 of 1500 employees); 82% of exits are voluntary. 'Better Compensation' is the #1 reason (62 exits, 24%).
B70: • Exits are accelerating: 91 exits in 2026 vs 53 in 2025 (+72%). Sales has the highest departmental attrition (25%).
B71: • One in three exits (33%) is a regrettable loss; only 19% received a counter-offer. Compensation is the weakest exit-interview dimension.
B72: • Performance: average rating 2.76/5; only 6.2% of reviews led to promotion. Exited employees show lower average ratings than active employees.
B73: • Engagement: 2026 eNPS is negative (-1.7); recognition and work-life balance are the lowest-rated dimensions — consistent with 'Better Compensation' and 'Work-Life Balance' as top exit reasons.
B74: • Recruitment: average time-to-hire 54 days at ₹36,393 per hire. Campus is the cheapest source (₹35,131/hire); LinkedIn is the fastest (51 days).
B75: • Compliance: 75% of mandatory trainings completed; 731 records overdue — Information Security has the largest overdue backlog.
B77: Data Notes & Caveats
B78: – 48 exits (all involuntary) have no resignation date / new-employer record — expected for terminations.
B79: – 345 requisitions show an offer date earlier than the requisition open date; time-to-offer figures should be read with caution.
B80: – 2026 performance reviews and 2026 engagement survey are partial-year; attendance covers Oct 2025 – Sep 2026 only.
... B84: Sheet Index
B85: Dashboard | E85: KPIs, charts, insights
B86: EDA_Workforce | E86: Headcount, diversity, CTC, levels, age bands, hiring trend
B87: EDA_Attrition | E87: Exits by year/reason/department/tenure, exit-interview ratings
B88: EDA_Performance | E88: Ratings, goals, promotions, hikes by year & department
B89: EDA_Engagement | E89: Satisfaction dimensions & eNPS by year & department
B90: EDA_Compliance | E90: Training status, statutory record checks, grievances
B91: EDA_Attendance | E91: Monthly presence, leave, late logins, overtime
B92: EDA_Recruitment | E92: Funnel, source effectiveness, cost & speed
B93: Departments / Employees / Attrition / Exit_Reviews / Performance / Engagement / Compliance_Trainings / Compliance_Records / Attendance / Recruitment | E93: Raw data (with helper columns)

Sheet EDA_Workforce
B2: Workforce Structure — EDA
B3: Headcount, diversity, compensation and profile breakdowns. All figures are live formulas over the Employees / Departments data sheets.
B5: 1. Headcount by Department
B6: Department | C6: Total HC | D6: Active | E6: Exited | F6: Attrition % | G6: Avg CTC (Active) | H6: Avg Age | I6: % Female | J6: HC Target | K6: Gap (Act.-Tgt.)
B7: Engineering | C7: =COUNTIF(Employees!$I$2:$I$1501,B7) -> 455 | D7: =COUNTIFS(Employees!$I$2:$I$1501,B7,Employees!$U$2:$U$1501,"Active") -> 387 | E7: =COUNTIFS(Employees!$I$2:$I$1501,B7,Employees!$U$2:$U$1501,"Exited") -> 68 | F7: =E7/C7 -> 0.14945055 | G7: =AVERAGEIFS(Employees!$P$2:$P$1501,Employees!$I$2:$I$1501,B7,Employees!$U$2:$U$1501,"Active") -> 1752082.7 | H7: =AVERAGEIF(Employees!$I$2:$I$1501,B7,Employees!$E$2:$E$1501) -> 32.041758 | I7: =COUNTIFS(Employees!$I$2:$I$1501,B7,Employees!$D$2:$D$1501,"Female")/C7 -> 0.45714286 | J7: =VLOOKUP(B7,Departments!$B$2:$E$10,4,FALSE()) -> 472 | K7: =D7-J7 -> -85
B8: Data & AI | C8: =COUNTIF(Employees!$I$2:$I$1501,B8) -> 139 | D8: =COUNTIFS(Employees!$I$2:$I$1501,B8,Employees!$U$2:$U$1501,"Active") -> 117 | E8: =COUNTIFS(Employees!$I$2:$I$1501,B8,Employees!$U$2:$U$1501,"Exited") -> 22 | F8: =E8/C8 -> 0.15827338 | G8: =AVERAGEIFS(Employees!$P$2:$P$1501,Employees!$I$2:$I$1501,B8,Employees!$U$2:$U$1501,"Active") -> 1819153.8 | H8: =AVERAGEIF(Employees!$I$2:$I$1501,B8,Employees!$E$2:$E$1501) -> 31.661871 | I8: =COUNTIFS(Employees!$I$2:$I$1501,B8,Employees!$D$2:$D$1501,"Female")/C8 -> 0.48201439 | J8: =VLOOKUP(B8,Departments!$B$2:$E$10,4,FALSE()) -> 157 | K8: =D8-J8 -> -40
B9: Sales | C9: =COUNTIF(Employees!$I$2:$I$1501,B9) -> 207 | D9: =COUNTIFS(Employees!$I$2:$I$1501,B9,Employees!$U$2:$U$1501,"Active") -> 155 | E9: =COUNTIFS(Employees!$I$2:$I$1501,B9,Employees!$U$2:$U$1501,"Exited") -> 52 | F9: =E9/C9 -> 0.25120773 | G9: =AVERAGEIFS(Employees!$P$2:$P$1501,Employees!$I$2:$I$1501,B9,Employees!$U$2:$U$1501,"Active") -> 3015941.9 | H9: =AVERAGEIF(Employees!$I$2:$I$1501,B9,Employees!$E$2:$E$1501) -> 36.15942 | I9: =COUNTIFS(Employees!$I$2:$I$1501,B9,Employees!$D$2:$D$1501,"Female")/C9 -> 0.43478261 | J9: =VLOOKUP(B9,Departments!$B$2:$E$10,4,FALSE()) -> 220 | K9: =D9-J9 -> -65
B10: Customer Support | C10: =COUNTIF(Employees!$I$2:$I$1501,B10) -> 207 | D10: =COUNTIFS(Employees!$I$2:$I$1501,B10,Employees!$U$2:$U$1501,"Active") -> 170 | E10: =COUNTIFS(Employees!$I$2:$I$1501,B10,Employees!$U$2:$U$1501,"Exited") -> 37 | F10: =E10/C10 -> 0.17874396 | G10: =AVERAGEIFS(Employees!$P$2:$P$1501,Employees!$I$2:$I$1501,B10,Employees!$U$2:$U$1501,"Active") -> 2111611.8 | H10: =AVERAGEIF(Employees!$I$2:$I$1501,B10,Employees!$E$2:$E$1501) -> 32.94686 | I10: =COUNTIFS(Employees!$I$2:$I$1501,B10,Employees!$D$2:$D$1501,"Female")/C10 -> 0.4057971 | J10: =VLOOKUP(B10,Departments!$B$2:$E$10,4,FALSE()) -> 220 | K10: =D10-J10 -> -50
B11: Operations | C11: =COUNTIF(Employees!$I$2:$I$1501,B11) -> 145 | D11: =COUNTIFS(Employees!$I$2:$I$1501,B11,Employees!$U$2:$U$1501,"Active") -> 118 | E11: =COUNTIFS(Employees!$I$2:$I$1501,B11,Employees!$U$2:$U$1501,"Exited") -> 27 | F11: =E11/C11 -> 0.1862069 | G11: =AVERAGEIFS(Employees!$P$2:$P$1501,Employees!$I$2:$I$1501,B11,Employees!$U$2:$U$1501,"Active") -> 1641432.2 | H11: =AVERAGEIF(Employees!$I$2:$I$1501,B11,Employees!$E$2:$E$1501) -> 31.041379 | I11: =COUNTIFS(Employees!$I$2:$I$1501,B11,Employees!$D$2:$D$1501,"Female")/C11 -> 0.40689655 | J11: =VLOOKUP(B11,Departments!$B$2:$E$10,4,FALSE()) -> 157 | K11: =D11-J11 -> -39
B12: Finance | C12: =COUNTIF(Employees!$I$2:$I$1501,B12) -> 97 | D12: =COUNTIFS(Employees!$I$2:$I$1501,B12,Employees!$U$2:$U$1501,"Active") -> 82 | E12: =COUNTIFS(Employees!$I$2:$I$1501,B12,Employees!$U$2:$U$1501,"Exited") -> 15 | F12: =E12/C12 -> 0.15463918 | G12: =AVERAGEIFS(Employees!$P$2:$P$1501,Employees!$I$2:$I$1501,B12,Employees!$U$2:$U$1501,"Active") -> 1906682.9 | H12: =AVERAGEIF(Employees!$I$2:$I$1501,B12,Employees!$E$2:$E$1501) -> 32.113402 | I12: =COUNTIFS(Employees!$I$2:$I$1501,B12,Employees!$D$2:$D$1501,"Female")/C12 -> 0.44329897 | J12: =VLOOKUP(B12,Departments!$B$2:$E$10,4,FALSE()) -> 94 | K12: =D12-J12 -> -12
B13: Human Resources | C13: =COUNTIF(Employees!$I$2:$I$1501,B13) -> 82 | D13: =COUNTIFS(Employees!$I$2:$I$1501,B13,Employees!$U$2:$U$1501,"Active") -> 68 | E13: =COUNTIFS(Employees!$I$2:$I$1501,B13,Employees!$U$2:$U$1501,"Exited") -> 14 | F13: =E13/C13 -> 0.17073171 | G13: =AVERAGEIFS(Employees!$P$2:$P$1501,Employees!$I$2:$I$1501,B13,Employees!$U$2:$U$1501,"Active") -> 1563235.3 | H13: =AVERAGEIF(Employees!$I$2:$I$1501,B13,Employees!$E$2:$E$1501) -> 30.231707 | I13: =COUNTIFS(Employees!$I$2:$I$1501,B13,Employees!$D$2:$D$1501,"Female")/C13 -> 0.45121951 | J13: =VLOOKUP(B13,Departments!$B$2:$E$10,4,FALSE()) -> 78 | K13: =D13-J13 -> -10
B14: Marketing | C14: =COUNTIF(Employees!$I$2:$I$1501,B14) -> 100 | D14: =COUNTIFS(Employees!$I$2:$I$1501,B14,Employees!$U$2:$U$1501,"Active") -> 82 | E14: =COUNTIFS(Employees!$I$2:$I$1501,B14,Employees!$U$2:$U$1501,"Exited") -> 18 | F14: =E14/C14 -> 0.18 | G14: =AVERAGEIFS(Employees!$P$2:$P$1501,Employees!$I$2:$I$1501,B14,Employees!$U$2:$U$1501,"Active") -> 1657634.1 | H14: =AVERAGEIF(Employees!$I$2:$I$1501,B14,Employees!$E$2:$E$1501) -> 30.32 | I14: =COUNTIFS(Employees!$I$2:$I$1501,B14,Employees!$D$2:$D$1501,"Female")/C14 -> 0.46 | J14: =VLOOKUP(B14,Departments!$B$2:$E$10,4,FALSE()) -> 94 | K14: =D14-J14 -> -12
B15: Legal & Compliance | C15: =COUNTIF(Employees!$I$2:$I$1501,B15) -> 68 | D15: =COUNTIFS(Employees!$I$2:$I$1501,B15,Employees!$U$2:$U$1501,"Active") -> 58 | E15: =COUNTIFS(Employees!$I$2:$I$1501,B15,Employees!$U$2:$U$1501,"Exited") -> 10 | F15: =E15/C15 -> 0.14705882 | G15: =AVERAGEIFS(Employees!$P$2:$P$1501,Employees!$I$2:$I$1501,B15,Employees!$U$2:$U$1501,"Active") -> 2028344.8 | H15: =AVERAGEIF(Employees!$I$2:$I$1501,B15,Employees!$E$2:$E$1501) -> 33.220588 | I15: =COUNTIFS(Employees!$I$2:$I$1501,B15,Employees!$D$2:$D$1501,"Female")/C15 -> 0.54411765 | J15: =VLOOKUP(B15,Departments!$B$2:$E$10,4,FALSE()) -> 78 | K15: =D15-J15 -> -20
B16: Total | C16: =SUM(C7:C15) -> 1500 | D16: =SUM(D7:D15) -> 1237 | E16: =SUM(E7:E15) -> 263 | F16: =E16/C16 -> 0.17533333 | G16: =AVERAGEIFS(Employees!$P$2:$P$1501,Employees!$U$2:$U$1501,"Active") -> 1962206.1 | H16: =AVERAGE(Employees!$E$2:$E$1501) -> 32.447333 | I16: =COUNTIF(Employees!$D$2:$D$1501,"Female")/C16 -> 0.44733333 | J16: =SUM(J7:J15) -> 1570 | K16: =D16-J16 -> -333
B18: 2. Job Level Mix
B19: Job Level | C19: Headcount | D19: % of Total | E19: Avg CTC | F19: Avg Age
B20: L1 | C20: =COUNTIF(Employees!$K$2:$K$1501,B20) -> 199 | D20: =C20/COUNTA(Employees!$A$2:$A$1501) -> 0.13266667 | E20: =AVERAGEIF(Employees!$K$2:$K$1501,B20,Employees!$P$2:$P$1501) -> 412909.55 | F20: =AVERAGEIF(Employees!$K$2:$K$1501,B20,Employees!$E$2:$E$1501) -> 25.231156
B21: L2 | C21: =COUNTIF(Employees!$K$2:$K$1501,B21) -> 546 | D21: =C21/COUNTA(Employees!$A$2:$A$1501) -> 0.364 | E21: =AVERAGEIF(Employees!$K$2:$K$1501,B21,Employees!$P$2:$P$1501) -> 999736.26 | F21: =AVERAGEIF(Employees!$K$2:$K$1501,B21,Employees!$E$2:$E$1501) -> 28.584249
B22: L3 | C22: =COUNTIF(Employees!$K$2:$K$1501,B22) -> 292 | D22: =C22/COUNTA(Employees!$A$2:$A$1501) -> 0.19466667 | E22: =AVERAGEIF(Employees!$K$2:$K$1501,B22,Employees!$P$2:$P$1501) -> 2015976 | F22: =AVERAGEIF(Employees!$K$2:$K$1501,B22,Employees!$E$2:$E$1501) -> 33.195205
B23: L4 | C23: =COUNTIF(Employees!$K$2:$K$1501,B23) -> 463 | D23: =C23/COUNTA(Employees!$A$2:$A$1501) -> 0.30866667 | E23: =AVERAGEIF(Employees!$K$2:$K$1501,B23,Employees!$P$2:$P$1501) -> 3651062.6 | F23: =AVERAGEIF(Employees!$K$2:$K$1501,B23,Employees!$E$2:$E$1501) -> 39.632829
B25: 3. Diversity & Profile
B26: Gender | C26: Count | D26: % of Total
B27: Female | C27: =COUNTIF(Employees!$D$2:$D$1501,B27) -> 671 | D27: =C27/COUNTA(Employees!$A$2:$A$1501) -> 0.44733333
B28: Male | C28: =COUNTIF(Employees!$D$2:$D$1501,B28) -> 824 | D28: =C28/COUNTA(Employees!$A$2:$A$1501) -> 0.54933333
B29: Other | C29: =COUNTIF(Employees!$D$2:$D$1501,B29) -> 5 | D29: =C29/COUNTA(Employees!$A$2:$A$1501) -> 0.0033333333
B32: Work Mode | C32: Count | D32: % of Total
B33: Hybrid | C33: =COUNTIF(Employees!$M$2:$M$1501,B33) -> 603 | D33: =C33/COUNTA(Employees!$A$2:$A$1501) -> 0.402
B34: Onsite | C34: =COUNTIF(Employees!$M$2:$M$1501,B34) -> 673 | D34: =C34/COUNTA(Employees!$A$2:$A$1501) -> 0.44866667
B35: Remote | C35: =COUNTIF(Employees!$M$2:$M$1501,B35) -> 224 | D35: =C35/COUNTA(Employees!$A$2:$A$1501) -> 0.14933333
B38: Employment Type | C38: Count | D38: % of Total
B39: Full-time | C39: =COUNTIF(Employees!$N$2:$N$1501,B39) -> 1324 | D39: =C39/COUNTA(Employees!$A$2:$A$1501) -> 0.88266667
B40: Contract | C40: =COUNTIF(Employees!$N$2:$N$1501,B40) -> 122 | D40: =C40/COUNTA(Employees!$A$2:$A$1501) -> 0.081333333
B41: Intern | C41: =COUNTIF(Employees!$N$2:$N$1501,B41) -> 54 | D41: =C41/COUNTA(Employees!$A$2:$A$1501) -> 0.036
B44: Education | C44: Count | D44: % of Total
B45: Bachelor's | C45: =COUNTIF(Employees!$G$2:$G$1501,B45) -> 767 | D45: =C45/COUNTA(Employees!$A$2:$A$1501) -> 0.51133333
B46: Master's | C46: =COUNTIF(Employees!$G$2:$G$1501,B46) -> 399 | D46: =C46/COUNTA(Employees!$A$2:$A$1501) -> 0.266
B47: MBA | C47: =COUNTIF(Employees!$G$2:$G$1501,B47) -> 197 | D47: =C47/COUNTA(Employees!$A$2:$A$1501) -> 0.13133333
B48: Diploma | C48: =COUNTIF(Employees!$G$2:$G$1501,B48) -> 112 | D48: =C48/COUNTA(Employees!$A$2:$A$1501) -> 0.074666667
B49: PhD | C49: =COUNTIF(Employees!$G$2:$G$1501,B49) -> 25 | D49: =C49/COUNTA(Employees!$A$2:$A$1501) -> 0.016666667
B52: Marital Status | C52: Count | D52: % of Total
B53: Married | C53: =COUNTIF(Employees!$F$2:$F$1501,B53) -> 763 | D53: =C53/COUNTA(Employees!$A$2:$A$1501) -> 0.50866667
B54: Single | C54: =COUNTIF(Employees!$F$2:$F$1501,B54) -> 658 | D54: =C54/COUNTA(Employees!$A$2:$A$1501) -> 0.43866667
B55: Divorced | C55: =COUNTIF(Employees!$F$2:$F$1501,B55) -> 79 | D55: =C55/COUNTA(Employees!$A$2:$A$1501) -> 0.052666667
B58: Work Location | C58: Count | D58: % of Total
B59: Bengaluru | C59: =COUNTIF(Employees!$L$2:$L$1501,B59) -> 309 | D59: =C59/COUNTA(Employees!$A$2:$A$1501) -> 0.206
B60: Chennai | C60: =COUNTIF(Employees!$L$2:$L$1501,B60) -> 381 | D60: =C60/COUNTA(Employees!$A$2:$A$1501) -> 0.254
B61: Coimbatore | C61: =COUNTIF(Employees!$L$2:$L$1501,B61) -> 451 | D61: =C61/COUNTA(Employees!$A$2:$A$1501) -> 0.30066667
B62: Hyderabad | C62: =COUNTIF(Employees!$L$2:$L$1501,B62) -> 133 | D62: =C62/COUNTA(Employees!$A$2:$A$1501) -> 0.088666667
B63: Mumbai | C63: =COUNTIF(Employees!$L$2:$L$1501,B63) -> 149 | D63: =C63/COUNTA(Employees!$A$2:$A$1501) -> 0.099333333
B64: Pune | C64: =COUNTIF(Employees!$L$2:$L$1501,B64) -> 77 | D64: =C64/COUNTA(Employees!$A$2:$A$1501) -> 0.051333333
B67: Hiring Source | C67: Count | D67: % of Total
B68: Job Portal | C68: =COUNTIF(Employees!$S$2:$S$1501,B68) -> 430 | D68: =C68/COUNTA(Employees!$A$2:$A$1501) -> 0.28666667
B69: Referral | C69: =COUNTIF(Employees!$S$2:$S$1501,B69) -> 400 | D69: =C69/COUNTA(Employees!$A$2:$A$1501) -> 0.26666667
B70: LinkedIn | C70: =COUNTIF(Employees!$S$2:$S$1501,B70) -> 293 | D70: =C70/COUNTA(Employees!$A$2:$A$1501) -> 0.19533333
B71: Campus | C71: =COUNTIF(Employees!$S$2:$S$1501,B71) -> 235 | D71: =C71/COUNTA(Employees!$A$2:$A$1501) -> 0.15666667
B72: Consultant | C72: =COUNTIF(Employees!$S$2:$S$1501,B72) -> 142 | D72: =C72/COUNTA(Employees!$A$2:$A$1501) -> 0.094666667
B74: 4. Age Bands & Hiring Trend
B75: Age Band | C75: Headcount | D75: % of Total | E75: Attrition % (band)
B76: 21-24 | C76: =COUNTIF(Employees!$W$2:$W$1501,B76) -> 179 | D76: =C76/COUNTA(Employees!$A$2:$A$1501) -> 0.11933333 | E76: =COUNTIFS(Employees!$W$2:$W$1501,B76,Employees!$U$2:$U$1501,"Exited")/C76 -> 0.24581006
B77: 25-29 | C77: =COUNTIF(Employees!$W$2:$W$1501,B77) -> 359 | D77: =C77/COUNTA(Employees!$A$2:$A$1501) -> 0.23933333 | E77: =COUNTIFS(Employees!$W$2:$W$1501,B77,Employees!$U$2:$U$1501,"Exited")/C77 -> 0.16713092
B78: 30-34 | C78: =COUNTIF(Employees!$W$2:$W$1501,B78) -> 407 | D78: =C78/COUNTA(Employees!$A$2:$A$1501) -> 0.27133333 | E78: =COUNTIFS(Employees!$W$2:$W$1501,B78,Employees!$U$2:$U$1501,"Exited")/C78 -> 0.15724816
B79: 35-39 | C79: =COUNTIF(Employees!$W$2:$W$1501,B79) -> 302 | D79: =C79/COUNTA(Employees!$A$2:$A$1501) -> 0.20133333 | E79: =COUNTIFS(Employees!$W$2:$W$1501,B79,Employees!$U$2:$U$1501,"Exited")/C79 -> 0.17218543
B80: 40-44 | C80: =COUNTIF(Employees!$W$2:$W$1501,B80) -> 206 | D80: =C80/COUNTA(Employees!$A$2:$A$1501) -> 0.13733333 | E80: =COUNTIFS(Employees!$W$2:$W$1501,B80,Employees!$U$2:$U$1501,"Exited")/C80 -> 0.18446602
B81: 45+ | C81: =COUNTIF(Employees!$W$2:$W$1501,B81) -> 47 | D81: =C81/COUNTA(Employees!$A$2:$A$1501) -> 0.031333333 | E81: =COUNTIFS(Employees!$W$2:$W$1501,B81,Employees!$U$2:$U$1501,"Exited")/C81 -> 0.10638298
B84: Hire Year | C84: Hired | D84: Still Active
B85: 2014 | C85: =COUNTIF(Employees!$V$2:$V$1501,B85) -> 24 | D85: =COUNTIFS(Employees!$V$2:$V$1501,B85,Employees!$U$2:$U$1501,"Active") -> 17
B86: 2015 | C86: =COUNTIF(Employees!$V$2:$V$1501,B86) -> 68 | D86: =COUNTIFS(Employees!$V$2:$V$1501,B86,Employees!$U$2:$U$1501,"Active") -> 62
B87: 2016 | C87: =COUNTIF(Employees!$V$2:$V$1501,B87) -> 59 | D87: =COUNTIFS(Employees!$V$2:$V$1501,B87,Employees!$U$2:$U$1501,"Active") -> 51
B88: 2017 | C88: =COUNTIF(Employees!$V$2:$V$1501,B88) -> 70 | D88: =COUNTIFS(Employees!$V$2:$V$1501,B88,Employees!$U$2:$U$1501,"Active") -> 63
B89: 2018 | C89: =COUNTIF(Employees!$V$2:$V$1501,B89) -> 93 | D89: =COUNTIFS(Employees!$V$2:$V$1501,B89,Employees!$U$2:$U$1501,"Active") -> 77
B90: 2019 | C90: =COUNTIF(Employees!$V$2:$V$1501,B90) -> 88 | D90: =COUNTIFS(Employees!$V$2:$V$1501,B90,Employees!$U$2:$U$1501,"Active") -> 73
B91: 2020 | C91: =COUNTIF(Employees!$V$2:$V$1501,B91) -> 115 | D91: =COUNTIFS(Employees!$V$2:$V$1501,B91,Employees!$U$2:$U$1501,"Active") -> 92
B92: 2021 | C92: =COUNTIF(Employees!$V$2:$V$1501,B92) -> 116 | D92: =COUNTIFS(Employees!$V$2:$V$1501,B92,Employees!$U$2:$U$1501,"Active") -> 91
B93: 2022 | C93: =COUNTIF(Employees!$V$2:$V$1501,B93) -> 145 | D93: =COUNTIFS(Employees!$V$2:$V$1501,B93,Employees!$U$2:$U$1501,"Active") -> 117
B94: 2023 | C94: =COUNTIF(Employees!$V$2:$V$1501,B94) -> 159 | D94: =COUNTIFS(Employees!$V$2:$V$1501,B94,Employees!$U$2:$U$1501,"Active") -> 134
B95: 2024 | C95: =COUNTIF(Employees!$V$2:$V$1501,B95) -> 158 | D95: =COUNTIFS(Employees!$V$2:$V$1501,B95,Employees!$U$2:$U$1501,"Active") -> 130
B96: 2025 | C96: =COUNTIF(Employees!$V$2:$V$1501,B96) -> 202 | D96: =COUNTIFS(Employees!$V$2:$V$1501,B96,Employees!$U$2:$U$1501,"Active") -> 168
B97: 2026 | C97: =COUNTIF(Employees!$V$2:$V$1501,B97) -> 203 | D97: =COUNTIFS(Employees!$V$2:$V$1501,B97,Employees!$U$2:$U$1501,"Active") -> 162

Sheet EDA_Attrition
B2: Attrition & Exits — EDA
B3: Exit volumes, reasons, tenure profile and exit-interview signals. Live formulas over the Attrition and Exit_Reviews data sheets.
B5: 1. Exits by Year
B6: Year | C6: Total Exits | D6: Voluntary | E6: Involuntary | F6: % of Workforce
B7: 2016 | C7: =COUNTIF(Attrition!$O$2:$O$264,B7) -> 3 | D7: =COUNTIFS(Attrition!$O$2:$O$264,B7,Attrition!$D$2:$D$264,"Voluntary") -> 3 | E7: =COUNTIFS(Attrition!$O$2:$O$264,B7,Attrition!$D$2:$D$264,"Involuntary") -> 0 | F7: =C7/COUNTA(Employees!$A$2:$A$1501) -> 0.002
B8: 2017 | C8: =COUNTIF(Attrition!$O$2:$O$264,B8) -> 3 | D8: =COUNTIFS(Attrition!$O$2:$O$264,B8,Attrition!$D$2:$D$264,"Voluntary") -> 3 | E8: =COUNTIFS(Attrition!$O$2:$O$264,B8,Attrition!$D$2:$D$264,"Involuntary") -> 0 | F8: =C8/COUNTA(Employees!$A$2:$A$1501) -> 0.002
B9: 2018 | C9: =COUNTIF(Attrition!$O$2:$O$264,B9) -> 2 | D9: =COUNTIFS(Attrition!$O$2:$O$264,B9,Attrition!$D$2:$D$264,"Voluntary") -> 2 | E9: =COUNTIFS(Attrition!$O$2:$O$264,B9,Attrition!$D$2:$D$264,"Involuntary") -> 0 | F9: =C9/COUNTA(Employees!$A$2:$A$1501) -> 0.0013333333
B10: 2019 | C10: =COUNTIF(Attrition!$O$2:$O$264,B10) -> 3 | D10: =COUNTIFS(Attrition!$O$2:$O$264,B10,Attrition!$D$2:$D$264,"Voluntary") -> 2 | E10: =COUNTIFS(Attrition!$O$2:$O$264,B10,Attrition!$D$2:$D$264,"Involuntary") -> 1 | F10: =C10/COUNTA(Employees!$A$2:$A$1501) -> 0.002
B11: 2020 | C11: =COUNTIF(Attrition!$O$2:$O$264,B11) -> 5 | D11: =COUNTIFS(Attrition!$O$2:$O$264,B11,Attrition!$D$2:$D$264,"Voluntary") -> 5 | E11: =COUNTIFS(Attrition!$O$2:$O$264,B11,Attrition!$D$2:$D$264,"Involuntary") -> 0 | F11: =C11/COUNTA(Employees!$A$2:$A$1501) -> 0.0033333333
B12: 2021 | C12: =COUNTIF(Attrition!$O$2:$O$264,B12) -> 17 | D12: =COUNTIFS(Attrition!$O$2:$O$264,B12,Attrition!$D$2:$D$264,"Voluntary") -> 16 | E12: =COUNTIFS(Attrition!$O$2:$O$264,B12,Attrition!$D$2:$D$264,"Involuntary") -> 1 | F12: =C12/COUNTA(Employees!$A$2:$A$1501) -> 0.011333333
B13: 2022 | C13: =COUNTIF(Attrition!$O$2:$O$264,B13) -> 21 | D13: =COUNTIFS(Attrition!$O$2:$O$264,B13,Attrition!$D$2:$D$264,"Voluntary") -> 14 | E13: =COUNTIFS(Attrition!$O$2:$O$264,B13,Attrition!$D$2:$D$264,"Involuntary") -> 7 | F13: =C13/COUNTA(Employees!$A$2:$A$1501) -> 0.014
B14: 2023 | C14: =COUNTIF(Attrition!$O$2:$O$264,B14) -> 34 | D14: =COUNTIFS(Attrition!$O$2:$O$264,B14,Attrition!$D$2:$D$264,"Voluntary") -> 26 | E14: =COUNTIFS(Attrition!$O$2:$O$264,B14,Attrition!$D$2:$D$264,"Involuntary") -> 8 | F14: =C14/COUNTA(Employees!$A$2:$A$1501) -> 0.022666667
B15: 2024 | C15: =COUNTIF(Attrition!$O$2:$O$264,B15) -> 31 | D15: =COUNTIFS(Attrition!$O$2:$O$264,B15,Attrition!$D$2:$D$264,"Voluntary") -> 23 | E15: =COUNTIFS(Attrition!$O$2:$O$264,B15,Attrition!$D$2:$D$264,"Involuntary") -> 8 | F15: =C15/COUNTA(Employees!$A$2:$A$1501) -> 0.020666667
B16: 2025 | C16: =COUNTIF(Attrition!$O$2:$O$264,B16) -> 53 | D16: =COUNTIFS(Attrition!$O$2:$O$264,B16,Attrition!$D$2:$D$264,"Voluntary") -> 46 | E16: =COUNTIFS(Attrition!$O$2:$O$264,B16,Attrition!$D$2:$D$264,"Involuntary") -> 7 | F16: =C16/COUNTA(Employees!$A$2:$A$1501) -> 0.035333333
B17: 2026 | C17: =COUNTIF(Attrition!$O$2:$O$264,B17) -> 91 | D17: =COUNTIFS(Attrition!$O$2:$O$264,B17,Attrition!$D$2:$D$264,"Voluntary") -> 75 | E17: =COUNTIFS(Attrition!$O$2:$O$264,B17,Attrition!$D$2:$D$264,"Involuntary") -> 16 | F17: =C17/COUNTA(Employees!$A$2:$A$1501) -> 0.060666667
B19: 2. Exit Reasons (Primary)
B20: Primary Reason | C20: Exits | D20: % of Exits | E20: Avg Tenure (months) | F20: % Regrettable | G20: Avg FnF Days
B21: Better Compensation | C21: =COUNTIF(Attrition!$E$2:$E$264,B21) -> 62 | D21: =C21/COUNTA(Attrition!$A$2:$A$264) -> 0.23574144 | E21: =AVERAGEIF(Attrition!$E$2:$E$264,B21,Attrition!$H$2:$H$264) -> 29.714516 | F21: =COUNTIFS(Attrition!$E$2:$E$264,B21,Attrition!$I$2:$I$264,"Yes")/C21 -> 0.35483871 | G21: =AVERAGEIF(Attrition!$E$2:$E$264,B21,Attrition!$M$2:$M$264) -> 34.612903
B22: Career Growth | C22: =COUNTIF(Attrition!$E$2:$E$264,B22) -> 42 | D22: =C22/COUNTA(Attrition!$A$2:$A$264) -> 0.15969582 | E22: =AVERAGEIF(Attrition!$E$2:$E$264,B22,Attrition!$H$2:$H$264) -> 29.633333 | F22: =COUNTIFS(Attrition!$E$2:$E$264,B22,Attrition!$I$2:$I$264,"Yes")/C22 -> 0.42857143 | G22: =AVERAGEIF(Attrition!$E$2:$E$264,B22,Attrition!$M$2:$M$264) -> 34.904762
B23: Manager Issues | C23: =COUNTIF(Attrition!$E$2:$E$264,B23) -> 22 | D23: =C23/COUNTA(Attrition!$A$2:$A$264) -> 0.08365019 | E23: =AVERAGEIF(Attrition!$E$2:$E$264,B23,Attrition!$H$2:$H$264) -> 11.131818 | F23: =COUNTIFS(Attrition!$E$2:$E$264,B23,Attrition!$I$2:$I$264,"Yes")/C23 -> 0.36363636 | G23: =AVERAGEIF(Attrition!$E$2:$E$264,B23,Attrition!$M$2:$M$264) -> 31.681818
B24: Work-Life Balance | C24: =COUNTIF(Attrition!$E$2:$E$264,B24) -> 19 | D24: =C24/COUNTA(Attrition!$A$2:$A$264) -> 0.072243346 | E24: =AVERAGEIF(Attrition!$E$2:$E$264,B24,Attrition!$H$2:$H$264) -> 27.468421 | F24: =COUNTIFS(Attrition!$E$2:$E$264,B24,Attrition!$I$2:$I$264,"Yes")/C24 -> 0.47368421 | G24: =AVERAGEIF(Attrition!$E$2:$E$264,B24,Attrition!$M$2:$M$264) -> 35.052632
B25: Toxic Culture | C25: =COUNTIF(Attrition!$E$2:$E$264,B25) -> 19 | D25: =C25/COUNTA(Attrition!$A$2:$A$264) -> 0.072243346 | E25: =AVERAGEIF(Attrition!$E$2:$E$264,B25,Attrition!$H$2:$H$264) -> 39.021053 | F25: =COUNTIFS(Attrition!$E$2:$E$264,B25,Attrition!$I$2:$I$264,"Yes")/C25 -> 0.52631579 | G25: =AVERAGEIF(Attrition!$E$2:$E$264,B25,Attrition!$M$2:$M$264) -> 28.157895
B26: Higher Studies | C26: =COUNTIF(Attrition!$E$2:$E$264,B26) -> 17 | D26: =C26/COUNTA(Attrition!$A$2:$A$264) -> 0.064638783 | E26: =AVERAGEIF(Attrition!$E$2:$E$264,B26,Attrition!$H$2:$H$264) -> 33.182353 | F26: =COUNTIFS(Attrition!$E$2:$E$264,B26,Attrition!$I$2:$I$264,"Yes")/C26 -> 0.41176471 | G26: =AVERAGEIF(Attrition!$E$2:$E$264,B26,Attrition!$M$2:$M$264) -> 38.588235
B27: Relocation | C27: =COUNTIF(Attrition!$E$2:$E$264,B27) -> 15 | D27: =C27/COUNTA(Attrition!$A$2:$A$264) -> 0.057034221 | E27: =AVERAGEIF(Attrition!$E$2:$E$264,B27,Attrition!$H$2:$H$264) -> 13.146667 | F27: =COUNTIFS(Attrition!$E$2:$E$264,B27,Attrition!$I$2:$I$264,"Yes")/C27 -> 0.33333333 | G27: =AVERAGEIF(Attrition!$E$2:$E$264,B27,Attrition!$M$2:$M$264) -> 40.066667
B28: Performance | C28: =COUNTIF(Attrition!$E$2:$E$264,B28) -> 13 | D28: =C28/COUNTA(Attrition!$A$2:$A$264) -> 0.049429658 | E28: =AVERAGEIF(Attrition!$E$2:$E$264,B28,Attrition!$H$2:$H$264) -> 22.246154 | F28: =COUNTIFS(Attrition!$E$2:$E$264,B28,Attrition!$I$2:$I$264,"Yes")/C28 -> 0 | G28: =AVERAGEIF(Attrition!$E$2:$E$264,B28,Attrition!$M$2:$M$264) -> 33.153846
B29: Job Role Mismatch | C29: =COUNTIF(Attrition!$E$2:$E$264,B29) -> 12 | D29: =C29/COUNTA(Attrition!$A$2:$A$264) -> 0.045627376 | E29: =AVERAGEIF(Attrition!$E$2:$E$264,B29,Attrition!$H$2:$H$264) -> 19.266667 | F29: =COUNTIFS(Attrition!$E$2:$E$264,B29,Attrition!$I$2:$I$264,"Yes")/C29 -> 0.58333333 | G29: =AVERAGEIF(Attrition!$E$2:$E$264,B29,Attrition!$M$2:$M$264) -> 37
B30: Restructuring / Layoff | C30: =COUNTIF(Attrition!$E$2:$E$264,B30) -> 12 | D30: =C30/COUNTA(Attrition!$A$2:$A$264) -> 0.045627376 | E30: =AVERAGEIF(Attrition!$E$2:$E$264,B30,Attrition!$H$2:$H$264) -> 28.675 | F30: =COUNTIFS(Attrition!$E$2:$E$264,B30,Attrition!$I$2:$I$264,"Yes")/C30 -> 0 | G30: =AVERAGEIF(Attrition!$E$2:$E$264,B30,Attrition!$M$2:$M$264) -> 45
B31: Contract End | C31: =COUNTIF(Attrition!$E$2:$E$264,B31) -> 10 | D31: =C31/COUNTA(Attrition!$A$2:$A$264) -> 0.038022814 | E31: =AVERAGEIF(Attrition!$E$2:$E$264,B31,Attrition!$H$2:$H$264) -> 14.5 | F31: =COUNTIFS(Attrition!$E$2:$E$264,B31,Attrition!$I$2:$I$264,"Yes")/C31 -> 0 | G31: =AVERAGEIF(Attrition!$E$2:$E$264,B31,Attrition!$M$2:$M$264) -> 37.5
B32: Misconduct / Policy Violation | C32: =COUNTIF(Attrition!$E$2:$E$264,B32) -> 9 | D32: =C32/COUNTA(Attrition!$A$2:$A$264) -> 0.034220532 | E32: =AVERAGEIF(Attrition!$E$2:$E$264,B32,Attrition!$H$2:$H$264) -> 14.9 | F32: =COUNTIFS(Attrition!$E$2:$E$264,B32,Attrition!$I$2:$I$264,"Yes")/C32 -> 0 | G32: =AVERAGEIF(Attrition!$E$2:$E$264,B32,Attrition!$M$2:$M$264) -> 46.666667
... B34: Absconding | C34: =COUNTIF(Attrition!$E$2:$E$264,B34) -> 4 | D34: =C34/COUNTA(Attrition!$A$2:$A$264) -> 0.015209125 | E34: =AVERAGEIF(Attrition!$E$2:$E$264,B34,Attrition!$H$2:$H$264) -> 22.325 | F34: =COUNTIFS(Attrition!$E$2:$E$264,B34,Attrition!$I$2:$I$264,"Yes")/C34 -> 0 | G34: =AVERAGEIF(Attrition!$E$2:$E$264,B34,Attrition!$M$2:$M$264) -> 34.75
B36: 3. Exits by Department
B37: Department | C37: Exits | D37: Attrition % (of dept HC) | E37: % Regrettable | F37: Avg Tenure at Exit (months)
B38: Engineering | C38: =COUNTIF(Attrition!$P$2:$P$264,B38) -> 68 | D38: =C38/COUNTIF(Employees!$I$2:$I$1501,B38) -> 0.14945055 | E38: =COUNTIFS(Attrition!$P$2:$P$264,B38,Attrition!$I$2:$I$264,"Yes")/C38 -> 0.29411765 | F38: =AVERAGEIF(Attrition!$P$2:$P$264,B38,Attrition!$H$2:$H$264) -> 28.141176
B39: Data & AI | C39: =COUNTIF(Attrition!$P$2:$P$264,B39) -> 22 | D39: =C39/COUNTIF(Employees!$I$2:$I$1501,B39) -> 0.15827338 | E39: =COUNTIFS(Attrition!$P$2:$P$264,B39,Attrition!$I$2:$I$264,"Yes")/C39 -> 0.40909091 | F39: =AVERAGEIF(Attrition!$P$2:$P$264,B39,Attrition!$H$2:$H$264) -> 21.386364
B40: Sales | C40: =COUNTIF(Attrition!$P$2:$P$264,B40) -> 52 | D40: =C40/COUNTIF(Employees!$I$2:$I$1501,B40) -> 0.25120773 | E40: =COUNTIFS(Attrition!$P$2:$P$264,B40,Attrition!$I$2:$I$264,"Yes")/C40 -> 0.30769231 | F40: =AVERAGEIF(Attrition!$P$2:$P$264,B40,Attrition!$H$2:$H$264) -> 29.559615
B41: Customer Support | C41: =COUNTIF(Attrition!$P$2:$P$264,B41) -> 37 | D41: =C41/COUNTIF(Employees!$I$2:$I$1501,B41) -> 0.17874396 | E41: =COUNTIFS(Attrition!$P$2:$P$264,B41,Attrition!$I$2:$I$264,"Yes")/C41 -> 0.35135135 | F41: =AVERAGEIF(Attrition!$P$2:$P$264,B41,Attrition!$H$2:$H$264) -> 37.191892
B42: Operations | C42: =COUNTIF(Attrition!$P$2:$P$264,B42) -> 27 | D42: =C42/COUNTIF(Employees!$I$2:$I$1501,B42) -> 0.1862069 | E42: =COUNTIFS(Attrition!$P$2:$P$264,B42,Attrition!$I$2:$I$264,"Yes")/C42 -> 0.37037037 | F42: =AVERAGEIF(Attrition!$P$2:$P$264,B42,Attrition!$H$2:$H$264) -> 20.748148
B43: Finance | C43: =COUNTIF(Attrition!$P$2:$P$264,B43) -> 15 | D43: =C43/COUNTIF(Employees!$I$2:$I$1501,B43) -> 0.15463918 | E43: =COUNTIFS(Attrition!$P$2:$P$264,B43,Attrition!$I$2:$I$264,"Yes")/C43 -> 0.2 | F43: =AVERAGEIF(Attrition!$P$2:$P$264,B43,Attrition!$H$2:$H$264) -> 20.66
B44: Human Resources | C44: =COUNTIF(Attrition!$P$2:$P$264,B44) -> 14 | D44: =C44/COUNTIF(Employees!$I$2:$I$1501,B44) -> 0.17073171 | E44: =COUNTIFS(Attrition!$P$2:$P$264,B44,Attrition!$I$2:$I$264,"Yes")/C44 -> 0.5 | F44: =AVERAGEIF(Attrition!$P$2:$P$264,B44,Attrition!$H$2:$H$264) -> 18.607143
B45: Marketing | C45: =COUNTIF(Attrition!$P$2:$P$264,B45) -> 18 | D45: =C45/COUNTIF(Employees!$I$2:$I$1501,B45) -> 0.18 | E45: =COUNTIFS(Attrition!$P$2:$P$264,B45,Attrition!$I$2:$I$264,"Yes")/C45 -> 0.33333333 | F45: =AVERAGEIF(Attrition!$P$2:$P$264,B45,Attrition!$H$2:$H$264) -> 13.061111
B46: Legal & Compliance | C46: =COUNTIF(Attrition!$P$2:$P$264,B46) -> 10 | D46: =C46/COUNTIF(Employees!$I$2:$I$1501,B46) -> 0.14705882 | E46: =COUNTIFS(Attrition!$P$2:$P$264,B46,Attrition!$I$2:$I$264,"Yes")/C46 -> 0.4 | F46: =AVERAGEIF(Attrition!$P$2:$P$264,B46,Attrition!$H$2:$H$264) -> 26.72
B48: 4. Tenure at Exit
B49: Tenure Band | C49: Exits | D49: % of Exits
B50: <1 yr | C50: =COUNTIF(Attrition!$Q$2:$Q$264,B50) -> 119 | D50: =C50/COUNTA(Attrition!$A$2:$A$264) -> 0.45247148
B51: 1-3 yrs | C51: =COUNTIF(Attrition!$Q$2:$Q$264,B51) -> 75 | D51: =C51/COUNTA(Attrition!$A$2:$A$264) -> 0.2851711
B52: 3-5 yrs | C52: =COUNTIF(Attrition!$Q$2:$Q$264,B52) -> 33 | D52: =C52/COUNTA(Attrition!$A$2:$A$264) -> 0.12547529
B53: 5+ yrs | C53: =COUNTIF(Attrition!$Q$2:$Q$264,B53) -> 36 | D53: =C53/COUNTA(Attrition!$A$2:$A$264) -> 0.13688213
B55: 5. Exit Process KPIs
B56: KPI | C56: Value
B57: Regrettable loss rate | C57: =COUNTIF(Attrition!$I$2:$I$264,"Yes")/COUNTA(Attrition!$A$2:$A$264) -> 0.33460076
B58: Rehire-eligible share | C58: =COUNTIF(Attrition!$J$2:$J$264,"Yes")/COUNTA(Attrition!$A$2:$A$264) -> 0.79467681
B59: Counter-offer rate | C59: =COUNTIF(Attrition!$K$2:$K$264,"Yes")/COUNTA(Attrition!$A$2:$A$264) -> 0.19011407
B60: Exit-interview completion | C60: =COUNTIF(Attrition!$L$2:$L$264,"Yes")/COUNTA(Attrition!$A$2:$A$264) -> 0.70342205
B61: Avg notice served (days) | C61: =AVERAGE(Attrition!$G$2:$G$264) -> 32.931559
B62: Avg notice compliance (served/period) | C62: =SUM(Attrition!$G$2:$G$264)/SUM(Attrition!$F$2:$F$264) -> 0.52778793
B63: Avg FnF settlement (days) | C63: =AVERAGE(Attrition!$M$2:$M$264) -> 36.034221
B65: 6. Exit-Interview Ratings (1–5) & Sentiment
B66: Rating Dimension | C66: Avg Score (exited employees)
B67: Manager | C67: =AVERAGE(Exit_Reviews!$H$2:$H$186) -> 3.0162162
B68: Culture | C68: =AVERAGE(Exit_Reviews!$I$2:$I$186) -> 3.1837838
B69: Compensation | C69: =AVERAGE(Exit_Reviews!$J$2:$J$186) -> 3.0486486
B70: Career Growth | C70: =AVERAGE(Exit_Reviews!$K$2:$K$186) -> 2.827027
B71: Work-Life Balance | C71: =AVERAGE(Exit_Reviews!$L$2:$L$186) -> 2.9945946
B74: Response | C74: Would Recommend | D74: Would Return
B75: Yes | C75: =COUNTIF(Exit_Reviews!$M$2:$M$186,B75) -> 61 | D75: =COUNTIF(Exit_Reviews!$N$2:$N$186,B75) -> 65
B76: Maybe | C76: =COUNTIF(Exit_Reviews!$M$2:$M$186,B76) -> 58 | D76: =COUNTIF(Exit_Reviews!$N$2:$N$186,B76) -> 49
B77: No | C77: =COUNTIF(Exit_Reviews!$M$2:$M$186,B77) -> 66 | D77: =COUNTIF(Exit_Reviews!$N$2:$N$186,B77) -> 71

Sheet EDA_Performance
B2: Performance — EDA
B3: Ratings, goal attainment, promotions and increments by review year. Live formulas over the Performance data sheet.
B5: 1. Yearly Summary
B6: Review Year | C6: Reviews | D6: Avg Rating | E6: Avg Goals % | F6: Promotions | G6: Promotion % | H6: Avg Hike % | I6: Avg Training Hrs
B7: 2021 | C7: =COUNTIF(Performance!$B$2:$B$3701,B7) -> 501 | D7: =AVERAGEIF(Performance!$B$2:$B$3701,B7,Performance!$C$2:$C$3701) -> 2.762475 | E7: =AVERAGEIF(Performance!$B$2:$B$3701,B7,Performance!$D$2:$D$3701) -> 81.083832 | F7: =COUNTIFS(Performance!$B$2:$B$3701,B7,Performance!$E$2:$E$3701,"Yes") -> 38 | G7: =F7/C7 -> 0.075848303 | H7: =AVERAGEIF(Performance!$B$2:$B$3701,B7,Performance!$F$2:$F$3701) -> 6.0902196 | I7: =AVERAGEIF(Performance!$B$2:$B$3701,B7,Performance!$G$2:$G$3701) -> 23.668663
B8: 2022 | C8: =COUNTIF(Performance!$B$2:$B$3701,B8) -> 600 | D8: =AVERAGEIF(Performance!$B$2:$B$3701,B8,Performance!$C$2:$C$3701) -> 2.705 | E8: =AVERAGEIF(Performance!$B$2:$B$3701,B8,Performance!$D$2:$D$3701) -> 81.86 | F8: =COUNTIFS(Performance!$B$2:$B$3701,B8,Performance!$E$2:$E$3701,"Yes") -> 25 | G8: =F8/C8 -> 0.041666667 | H8: =AVERAGEIF(Performance!$B$2:$B$3701,B8,Performance!$F$2:$F$3701) -> 5.9345 | I8: =AVERAGEIF(Performance!$B$2:$B$3701,B8,Performance!$G$2:$G$3701) -> 22.161667
B9: 2023 | C9: =COUNTIF(Performance!$B$2:$B$3701,B9) -> 724 | D9: =AVERAGEIF(Performance!$B$2:$B$3701,B9,Performance!$C$2:$C$3701) -> 2.7859116 | E9: =AVERAGEIF(Performance!$B$2:$B$3701,B9,Performance!$D$2:$D$3701) -> 81.918508 | F9: =COUNTIFS(Performance!$B$2:$B$3701,B9,Performance!$E$2:$E$3701,"Yes") -> 48 | G9: =F9/C9 -> 0.066298343 | H9: =AVERAGEIF(Performance!$B$2:$B$3701,B9,Performance!$F$2:$F$3701) -> 6.0799724 | I9: =AVERAGEIF(Performance!$B$2:$B$3701,B9,Performance!$G$2:$G$3701) -> 23.523481
B10: 2024 | C10: =COUNTIF(Performance!$B$2:$B$3701,B10) -> 849 | D10: =AVERAGEIF(Performance!$B$2:$B$3701,B10,Performance!$C$2:$C$3701) -> 2.7644287 | E10: =AVERAGEIF(Performance!$B$2:$B$3701,B10,Performance!$D$2:$D$3701) -> 80.941107 | F10: =COUNTIFS(Performance!$B$2:$B$3701,B10,Performance!$E$2:$E$3701,"Yes") -> 49 | G10: =F10/C10 -> 0.057714959 | H10: =AVERAGEIF(Performance!$B$2:$B$3701,B10,Performance!$F$2:$F$3701) -> 6.1744405 | I10: =AVERAGEIF(Performance!$B$2:$B$3701,B10,Performance!$G$2:$G$3701) -> 23.720848
B11: 2025 | C11: =COUNTIF(Performance!$B$2:$B$3701,B11) -> 976 | D11: =AVERAGEIF(Performance!$B$2:$B$3701,B11,Performance!$C$2:$C$3701) -> 2.8053279 | E11: =AVERAGEIF(Performance!$B$2:$B$3701,B11,Performance!$D$2:$D$3701) -> 82.145492 | F11: =COUNTIFS(Performance!$B$2:$B$3701,B11,Performance!$E$2:$E$3701,"Yes") -> 68 | G11: =F11/C11 -> 0.069672131 | H11: =AVERAGEIF(Performance!$B$2:$B$3701,B11,Performance!$F$2:$F$3701) -> 6.1010246 | I11: =AVERAGEIF(Performance!$B$2:$B$3701,B11,Performance!$G$2:$G$3701) -> 23.92623
B12: 2026 | C12: =COUNTIF(Performance!$B$2:$B$3701,B12) -> 50 | D12: =AVERAGEIF(Performance!$B$2:$B$3701,B12,Performance!$C$2:$C$3701) -> 2.18 | E12: =AVERAGEIF(Performance!$B$2:$B$3701,B12,Performance!$D$2:$D$3701) -> 78.1 | F12: =COUNTIFS(Performance!$B$2:$B$3701,B12,Performance!$E$2:$E$3701,"Yes") -> 2 | G12: =F12/C12 -> 0.04 | H12: =AVERAGEIF(Performance!$B$2:$B$3701,B12,Performance!$F$2:$F$3701) -> 4.934 | I12: =AVERAGEIF(Performance!$B$2:$B$3701,B12,Performance!$G$2:$G$3701) -> 21.74
B14: 2. Rating Distribution by Year
B15: Review Year | C15: Rating 1 | D15: Rating 2 | E15: Rating 3 | F15: Rating 4 | G15: Rating 5 | H15: Total
B16: 2021 | C16: =COUNTIFS(Performance!$B$2:$B$3701,B16,Performance!$C$2:$C$3701,1) -> 50 | D16: =COUNTIFS(Performance!$B$2:$B$3701,B16,Performance!$C$2:$C$3701,2) -> 142 | E16: =COUNTIFS(Performance!$B$2:$B$3701,B16,Performance!$C$2:$C$3701,3) -> 200 | F16: =COUNTIFS(Performance!$B$2:$B$3701,B16,Performance!$C$2:$C$3701,4) -> 95 | G16: =COUNTIFS(Performance!$B$2:$B$3701,B16,Performance!$C$2:$C$3701,5) -> 14 | H16: =SUM(C16:G16) -> 501
B17: 2022 | C17: =COUNTIFS(Performance!$B$2:$B$3701,B17,Performance!$C$2:$C$3701,1) -> 44 | D17: =COUNTIFS(Performance!$B$2:$B$3701,B17,Performance!$C$2:$C$3701,2) -> 208 | E17: =COUNTIFS(Performance!$B$2:$B$3701,B17,Performance!$C$2:$C$3701,3) -> 240 | F17: =COUNTIFS(Performance!$B$2:$B$3701,B17,Performance!$C$2:$C$3701,4) -> 97 | G17: =COUNTIFS(Performance!$B$2:$B$3701,B17,Performance!$C$2:$C$3701,5) -> 11 | H17: =SUM(C17:G17) -> 600
B18: 2023 | C18: =COUNTIFS(Performance!$B$2:$B$3701,B18,Performance!$C$2:$C$3701,1) -> 64 | D18: =COUNTIFS(Performance!$B$2:$B$3701,B18,Performance!$C$2:$C$3701,2) -> 194 | E18: =COUNTIFS(Performance!$B$2:$B$3701,B18,Performance!$C$2:$C$3701,3) -> 315 | F18: =COUNTIFS(Performance!$B$2:$B$3701,B18,Performance!$C$2:$C$3701,4) -> 135 | G18: =COUNTIFS(Performance!$B$2:$B$3701,B18,Performance!$C$2:$C$3701,5) -> 16 | H18: =SUM(C18:G18) -> 724
B19: 2024 | C19: =COUNTIFS(Performance!$B$2:$B$3701,B19,Performance!$C$2:$C$3701,1) -> 69 | D19: =COUNTIFS(Performance!$B$2:$B$3701,B19,Performance!$C$2:$C$3701,2) -> 252 | E19: =COUNTIFS(Performance!$B$2:$B$3701,B19,Performance!$C$2:$C$3701,3) -> 355 | F19: =COUNTIFS(Performance!$B$2:$B$3701,B19,Performance!$C$2:$C$3701,4) -> 156 | G19: =COUNTIFS(Performance!$B$2:$B$3701,B19,Performance!$C$2:$C$3701,5) -> 17 | H19: =SUM(C19:G19) -> 849
B20: 2025 | C20: =COUNTIFS(Performance!$B$2:$B$3701,B20,Performance!$C$2:$C$3701,1) -> 90 | D20: =COUNTIFS(Performance!$B$2:$B$3701,B20,Performance!$C$2:$C$3701,2) -> 270 | E20: =COUNTIFS(Performance!$B$2:$B$3701,B20,Performance!$C$2:$C$3701,3) -> 391 | F20: =COUNTIFS(Performance!$B$2:$B$3701,B20,Performance!$C$2:$C$3701,4) -> 190 | G20: =COUNTIFS(Performance!$B$2:$B$3701,B20,Performance!$C$2:$C$3701,5) -> 35 | H20: =SUM(C20:G20) -> 976
B21: 2026 | C21: =COUNTIFS(Performance!$B$2:$B$3701,B21,Performance!$C$2:$C$3701,1) -> 11 | D21: =COUNTIFS(Performance!$B$2:$B$3701,B21,Performance!$C$2:$C$3701,2) -> 23 | E21: =COUNTIFS(Performance!$B$2:$B$3701,B21,Performance!$C$2:$C$3701,3) -> 13 | F21: =COUNTIFS(Performance!$B$2:$B$3701,B21,Performance!$C$2:$C$3701,4) -> 2 | G21: =COUNTIFS(Performance!$B$2:$B$3701,B21,Performance!$C$2:$C$3701,5) -> 1 | H21: =SUM(C21:G21) -> 50
B23: 3. Rating by Department
B24: Department | C24: Reviews | D24: Avg Rating | E24: Promotion % | F24: Avg Hike %
B25: Engineering | C25: =COUNTIF(Performance!$H$2:$H$3701,B25) -> 1163 | D25: =AVERAGEIF(Performance!$H$2:$H$3701,B25,Performance!$C$2:$C$3701) -> 2.7815993 | E25: =COUNTIFS(Performance!$H$2:$H$3701,B25,Performance!$E$2:$E$3701,"Yes")/C25 -> 0.066208083 | F25: =AVERAGEIF(Performance!$H$2:$H$3701,B25,Performance!$F$2:$F$3701) -> 6.1067928
B26: Data & AI | C26: =COUNTIF(Performance!$H$2:$H$3701,B26) -> 312 | D26: =AVERAGEIF(Performance!$H$2:$H$3701,B26,Performance!$C$2:$C$3701) -> 2.7339744 | E26: =COUNTIFS(Performance!$H$2:$H$3701,B26,Performance!$E$2:$E$3701,"Yes")/C26 -> 0.064102564 | F26: =AVERAGEIF(Performance!$H$2:$H$3701,B26,Performance!$F$2:$F$3701) -> 5.8650641
B27: Sales | C27: =COUNTIF(Performance!$H$2:$H$3701,B27) -> 584 | D27: =AVERAGEIF(Performance!$H$2:$H$3701,B27,Performance!$C$2:$C$3701) -> 2.7089041 | E27: =COUNTIFS(Performance!$H$2:$H$3701,B27,Performance!$E$2:$E$3701,"Yes")/C27 -> 0.051369863 | F27: =AVERAGEIF(Performance!$H$2:$H$3701,B27,Performance!$F$2:$F$3701) -> 5.9717466
B28: Customer Support | C28: =COUNTIF(Performance!$H$2:$H$3701,B28) -> 517 | D28: =AVERAGEIF(Performance!$H$2:$H$3701,B28,Performance!$C$2:$C$3701) -> 2.7794971 | E28: =COUNTIFS(Performance!$H$2:$H$3701,B28,Performance!$E$2:$E$3701,"Yes")/C28 -> 0.065764023 | F28: =AVERAGEIF(Performance!$H$2:$H$3701,B28,Performance!$F$2:$F$3701) -> 6.1116054
B29: Operations | C29: =COUNTIF(Performance!$H$2:$H$3701,B29) -> 343 | D29: =AVERAGEIF(Performance!$H$2:$H$3701,B29,Performance!$C$2:$C$3701) -> 2.7609329 | E29: =COUNTIFS(Performance!$H$2:$H$3701,B29,Performance!$E$2:$E$3701,"Yes")/C29 -> 0.06122449 | F29: =AVERAGEIF(Performance!$H$2:$H$3701,B29,Performance!$F$2:$F$3701) -> 6.0451895
B30: Finance | C30: =COUNTIF(Performance!$H$2:$H$3701,B30) -> 248 | D30: =AVERAGEIF(Performance!$H$2:$H$3701,B30,Performance!$C$2:$C$3701) -> 2.8064516 | E30: =COUNTIFS(Performance!$H$2:$H$3701,B30,Performance!$E$2:$E$3701,"Yes")/C30 -> 0.064516129 | F30: =AVERAGEIF(Performance!$H$2:$H$3701,B30,Performance!$F$2:$F$3701) -> 6.1762097
B31: Human Resources | C31: =COUNTIF(Performance!$H$2:$H$3701,B31) -> 195 | D31: =AVERAGEIF(Performance!$H$2:$H$3701,B31,Performance!$C$2:$C$3701) -> 2.7487179 | E31: =COUNTIFS(Performance!$H$2:$H$3701,B31,Performance!$E$2:$E$3701,"Yes")/C31 -> 0.056410256 | F31: =AVERAGEIF(Performance!$H$2:$H$3701,B31,Performance!$F$2:$F$3701) -> 6.0061538
B32: Marketing | C32: =COUNTIF(Performance!$H$2:$H$3701,B32) -> 188 | D32: =AVERAGEIF(Performance!$H$2:$H$3701,B32,Performance!$C$2:$C$3701) -> 2.7659574 | E32: =COUNTIFS(Performance!$H$2:$H$3701,B32,Performance!$E$2:$E$3701,"Yes")/C32 -> 0.079787234 | F32: =AVERAGEIF(Performance!$H$2:$H$3701,B32,Performance!$F$2:$F$3701) -> 6.2781915
B33: Legal & Compliance | C33: =COUNTIF(Performance!$H$2:$H$3701,B33) -> 150 | D33: =AVERAGEIF(Performance!$H$2:$H$3701,B33,Performance!$C$2:$C$3701) -> 2.7466667 | E33: =COUNTIFS(Performance!$H$2:$H$3701,B33,Performance!$E$2:$E$3701,"Yes")/C33 -> 0.04 | F33: =AVERAGEIF(Performance!$H$2:$H$3701,B33,Performance!$F$2:$F$3701) -> 6.1413333
B35: 4. Active vs Exited Employees
B36: Status | C36: Reviews | D36: Avg Rating | E36: Avg Goals % | F36: Promotion %
B37: Active | C37: =COUNTIF(Performance!$I$2:$I$3701,B37) -> 3288 | D37: =AVERAGEIF(Performance!$I$2:$I$3701,B37,Performance!$C$2:$C$3701) -> 2.8062652 | E37: =AVERAGEIF(Performance!$I$2:$I$3701,B37,Performance!$D$2:$D$3701) -> 82.019161 | F37: =COUNTIFS(Performance!$I$2:$I$3701,B37,Performance!$E$2:$E$3701,"Yes")/C37 -> 0.064476886
B38: Exited | C38: =COUNTIF(Performance!$I$2:$I$3701,B38) -> 412 | D38: =AVERAGEIF(Performance!$I$2:$I$3701,B38,Performance!$C$2:$C$3701) -> 2.4053398 | E38: =AVERAGEIF(Performance!$I$2:$I$3701,B38,Performance!$D$2:$D$3701) -> 78.075243 | F38: =COUNTIFS(Performance!$I$2:$I$3701,B38,Performance!$E$2:$E$3701,"Yes")/C38 -> 0.04368932

Sheet EDA_Engagement
B2: Engagement Survey — EDA
B3: Satisfaction dimensions and eNPS by survey year and department. Live formulas over the Engagement data sheet.
B5: 1. Engagement by Survey Year
B6: Year | C6: Responses | D6: Job Sat. | E6: Environment | F6: Mgr Relation | G6: Work-Life | H6: Recognition | I6: Avg eNPS Score (0-10) | J6: % Promoters | K6: % Detractors | L6: eNPS
B7: 2024 | C7: =COUNTIF(Engagement!$B$2:$B$2375,B7) -> 679 | D7: =AVERAGEIF(Engagement!$B$2:$B$2375,B7,Engagement!$C$2:$C$2375) -> 3.4447717 | E7: =AVERAGEIF(Engagement!$B$2:$B$2375,B7,Engagement!$D$2:$D$2375) -> 3.4698085 | F7: =AVERAGEIF(Engagement!$B$2:$B$2375,B7,Engagement!$E$2:$E$2375) -> 3.4580265 | G7: =AVERAGEIF(Engagement!$B$2:$B$2375,B7,Engagement!$F$2:$F$2375) -> 3.4344624 | H7: =AVERAGEIF(Engagement!$B$2:$B$2375,B7,Engagement!$G$2:$G$2375) -> 3.4270987 | I7: =AVERAGEIF(Engagement!$B$2:$B$2375,B7,Engagement!$H$2:$H$2375) -> 7.2061856 | J7: =COUNTIFS(Engagement!$B$2:$B$2375,B7,Engagement!$H$2:$H$2375,">=9")/C7 -> 0.30486009 | K7: =COUNTIFS(Engagement!$B$2:$B$2375,B7,Engagement!$H$2:$H$2375,"<=6")/C7 -> 0.35640648 | L7: =(J7-K7)*100 -> -5.1546392
B8: 2025 | C8: =COUNTIF(Engagement!$B$2:$B$2375,B8) -> 789 | D8: =AVERAGEIF(Engagement!$B$2:$B$2375,B8,Engagement!$C$2:$C$2375) -> 3.4588086 | E8: =AVERAGEIF(Engagement!$B$2:$B$2375,B8,Engagement!$D$2:$D$2375) -> 3.4512041 | F8: =AVERAGEIF(Engagement!$B$2:$B$2375,B8,Engagement!$E$2:$E$2375) -> 3.4296578 | G8: =AVERAGEIF(Engagement!$B$2:$B$2375,B8,Engagement!$F$2:$F$2375) -> 3.4841572 | H8: =AVERAGEIF(Engagement!$B$2:$B$2375,B8,Engagement!$G$2:$G$2375) -> 3.4499366 | I8: =AVERAGEIF(Engagement!$B$2:$B$2375,B8,Engagement!$H$2:$H$2375) -> 7.2446134 | J8: =COUNTIFS(Engagement!$B$2:$B$2375,B8,Engagement!$H$2:$H$2375,">=9")/C8 -> 0.31432193 | K8: =COUNTIFS(Engagement!$B$2:$B$2375,B8,Engagement!$H$2:$H$2375,"<=6")/C8 -> 0.3409379 | L8: =(J8-K8)*100 -> -2.661597
B9: 2026 | C9: =COUNTIF(Engagement!$B$2:$B$2375,B9) -> 906 | D9: =AVERAGEIF(Engagement!$B$2:$B$2375,B9,Engagement!$C$2:$C$2375) -> 3.4569536 | E9: =AVERAGEIF(Engagement!$B$2:$B$2375,B9,Engagement!$D$2:$D$2375) -> 3.5154525 | F9: =AVERAGEIF(Engagement!$B$2:$B$2375,B9,Engagement!$E$2:$E$2375) -> 3.4238411 | G9: =AVERAGEIF(Engagement!$B$2:$B$2375,B9,Engagement!$F$2:$F$2375) -> 3.4271523 | H9: =AVERAGEIF(Engagement!$B$2:$B$2375,B9,Engagement!$G$2:$G$2375) -> 3.5110375 | I9: =AVERAGEIF(Engagement!$B$2:$B$2375,B9,Engagement!$H$2:$H$2375) -> 7.3233996 | J9: =COUNTIFS(Engagement!$B$2:$B$2375,B9,Engagement!$H$2:$H$2375,">=9")/C9 -> 0.33112583 | K9: =COUNTIFS(Engagement!$B$2:$B$2375,B9,Engagement!$H$2:$H$2375,"<=6")/C9 -> 0.34768212 | L9: =(J9-K9)*100 -> -1.6556291
B11: 2. Engagement by Department (all years)
B12: Department | C12: Responses | D12: Avg Job Sat. | E12: Avg Work-Life | F12: Avg eNPS Score | G12: eNPS
B13: Engineering | C13: =COUNTIF(Engagement!$I$2:$I$2375,B13) -> 775 | D13: =AVERAGEIF(Engagement!$I$2:$I$2375,B13,Engagement!$C$2:$C$2375) -> 3.4593548 | E13: =AVERAGEIF(Engagement!$I$2:$I$2375,B13,Engagement!$F$2:$F$2375) -> 3.4012903 | F13: =AVERAGEIF(Engagement!$I$2:$I$2375,B13,Engagement!$H$2:$H$2375) -> 7.3509677 | G13: =(COUNTIFS(Engagement!$I$2:$I$2375,B13,Engagement!$H$2:$H$2375,">=9")-COUNTIFS(Engagement!$I$2:$I$2375,B13,Engagement!$H$2:$H$2375,"<=6"))/C13*100 -> -0.77419355
B14: Data & AI | C14: =COUNTIF(Engagement!$I$2:$I$2375,B14) -> 217 | D14: =AVERAGEIF(Engagement!$I$2:$I$2375,B14,Engagement!$C$2:$C$2375) -> 3.4884793 | E14: =AVERAGEIF(Engagement!$I$2:$I$2375,B14,Engagement!$F$2:$F$2375) -> 3.4976959 | F14: =AVERAGEIF(Engagement!$I$2:$I$2375,B14,Engagement!$H$2:$H$2375) -> 6.9861751 | G14: =(COUNTIFS(Engagement!$I$2:$I$2375,B14,Engagement!$H$2:$H$2375,">=9")-COUNTIFS(Engagement!$I$2:$I$2375,B14,Engagement!$H$2:$H$2375,"<=6"))/C14*100 -> -16.589862
B15: Sales | C15: =COUNTIF(Engagement!$I$2:$I$2375,B15) -> 318 | D15: =AVERAGEIF(Engagement!$I$2:$I$2375,B15,Engagement!$C$2:$C$2375) -> 3.4402516 | E15: =AVERAGEIF(Engagement!$I$2:$I$2375,B15,Engagement!$F$2:$F$2375) -> 3.4308176 | F15: =AVERAGEIF(Engagement!$I$2:$I$2375,B15,Engagement!$H$2:$H$2375) -> 7.3867925 | G15: =(COUNTIFS(Engagement!$I$2:$I$2375,B15,Engagement!$H$2:$H$2375,">=9")-COUNTIFS(Engagement!$I$2:$I$2375,B15,Engagement!$H$2:$H$2375,"<=6"))/C15*100 -> 1.8867925
B16: Customer Support | C16: =COUNTIF(Engagement!$I$2:$I$2375,B16) -> 314 | D16: =AVERAGEIF(Engagement!$I$2:$I$2375,B16,Engagement!$C$2:$C$2375) -> 3.4522293 | E16: =AVERAGEIF(Engagement!$I$2:$I$2375,B16,Engagement!$F$2:$F$2375) -> 3.4968153 | F16: =AVERAGEIF(Engagement!$I$2:$I$2375,B16,Engagement!$H$2:$H$2375) -> 7.3025478 | G16: =(COUNTIFS(Engagement!$I$2:$I$2375,B16,Engagement!$H$2:$H$2375,">=9")-COUNTIFS(Engagement!$I$2:$I$2375,B16,Engagement!$H$2:$H$2375,"<=6"))/C16*100 -> 0.31847134
B17: Operations | C17: =COUNTIF(Engagement!$I$2:$I$2375,B17) -> 213 | D17: =AVERAGEIF(Engagement!$I$2:$I$2375,B17,Engagement!$C$2:$C$2375) -> 3.4647887 | E17: =AVERAGEIF(Engagement!$I$2:$I$2375,B17,Engagement!$F$2:$F$2375) -> 3.4553991 | F17: =AVERAGEIF(Engagement!$I$2:$I$2375,B17,Engagement!$H$2:$H$2375) -> 7.2629108 | G17: =(COUNTIFS(Engagement!$I$2:$I$2375,B17,Engagement!$H$2:$H$2375,">=9")-COUNTIFS(Engagement!$I$2:$I$2375,B17,Engagement!$H$2:$H$2375,"<=6"))/C17*100 -> -0.46948357
B18: Finance | C18: =COUNTIF(Engagement!$I$2:$I$2375,B18) -> 166 | D18: =AVERAGEIF(Engagement!$I$2:$I$2375,B18,Engagement!$C$2:$C$2375) -> 3.3855422 | E18: =AVERAGEIF(Engagement!$I$2:$I$2375,B18,Engagement!$F$2:$F$2375) -> 3.5180723 | F18: =AVERAGEIF(Engagement!$I$2:$I$2375,B18,Engagement!$H$2:$H$2375) -> 7.060241 | G18: =(COUNTIFS(Engagement!$I$2:$I$2375,B18,Engagement!$H$2:$H$2375,">=9")-COUNTIFS(Engagement!$I$2:$I$2375,B18,Engagement!$H$2:$H$2375,"<=6"))/C18*100 -> -7.8313253
B19: Human Resources | C19: =COUNTIF(Engagement!$I$2:$I$2375,B19) -> 125 | D19: =AVERAGEIF(Engagement!$I$2:$I$2375,B19,Engagement!$C$2:$C$2375) -> 3.504 | E19: =AVERAGEIF(Engagement!$I$2:$I$2375,B19,Engagement!$F$2:$F$2375) -> 3.336 | F19: =AVERAGEIF(Engagement!$I$2:$I$2375,B19,Engagement!$H$2:$H$2375) -> 7.016 | G19: =(COUNTIFS(Engagement!$I$2:$I$2375,B19,Engagement!$H$2:$H$2375,">=9")-COUNTIFS(Engagement!$I$2:$I$2375,B19,Engagement!$H$2:$H$2375,"<=6"))/C19*100 -> -15.2
B20: Marketing | C20: =COUNTIF(Engagement!$I$2:$I$2375,B20) -> 142 | D20: =AVERAGEIF(Engagement!$I$2:$I$2375,B20,Engagement!$C$2:$C$2375) -> 3.4225352 | E20: =AVERAGEIF(Engagement!$I$2:$I$2375,B20,Engagement!$F$2:$F$2375) -> 3.5 | F20: =AVERAGEIF(Engagement!$I$2:$I$2375,B20,Engagement!$H$2:$H$2375) -> 7.3661972 | G20: =(COUNTIFS(Engagement!$I$2:$I$2375,B20,Engagement!$H$2:$H$2375,">=9")-COUNTIFS(Engagement!$I$2:$I$2375,B20,Engagement!$H$2:$H$2375,"<=6"))/C20*100 -> 0.70422535
B21: Legal & Compliance | C21: =COUNTIF(Engagement!$I$2:$I$2375,B21) -> 104 | D21: =AVERAGEIF(Engagement!$I$2:$I$2375,B21,Engagement!$C$2:$C$2375) -> 3.4615385 | E21: =AVERAGEIF(Engagement!$I$2:$I$2375,B21,Engagement!$F$2:$F$2375) -> 3.5384615 | F21: =AVERAGEIF(Engagement!$I$2:$I$2375,B21,Engagement!$H$2:$H$2375) -> 7.1826923 | G21: =(COUNTIFS(Engagement!$I$2:$I$2375,B21,Engagement!$H$2:$H$2375,">=9")-COUNTIFS(Engagement!$I$2:$I$2375,B21,Engagement!$H$2:$H$2375,"<=6"))/C21*100 -> -3.8461538

Sheet EDA_Compliance
B2: Compliance — EDA
B3: Mandatory training status and employee statutory record checks. Live formulas over the Compliance_Trainings and Compliance_Records sheets.
B5: 1. Training Status by Course
B6: Course | C6: Completed | D6: In Progress | E6: Not Started | F6: Overdue | G6: Total | H6: Completion % | I6: Avg Score %
B7: POSH Awareness | C7: =COUNTIFS(Compliance_Trainings!$B$2:$B$7423,B7,Compliance_Trainings!$E$2:$E$7423,"Completed") -> 941 | D7: =COUNTIFS(Compliance_Trainings!$B$2:$B$7423,B7,Compliance_Trainings!$E$2:$E$7423,"In Progress") -> 100 | E7: =COUNTIFS(Compliance_Trainings!$B$2:$B$7423,B7,Compliance_Trainings!$E$2:$E$7423,"Not Started") -> 74 | F7: =COUNTIFS(Compliance_Trainings!$B$2:$B$7423,B7,Compliance_Trainings!$E$2:$E$7423,"Overdue") -> 122 | G7: =SUM(C7:F7) -> 1237 | H7: =C7/G7 -> 0.7607114 | I7: =AVERAGEIF(Compliance_Trainings!$B$2:$B$7423,B7,Compliance_Trainings!$G$2:$G$7423) -> 79.5983
B8: Code of Conduct | C8: =COUNTIFS(Compliance_Trainings!$B$2:$B$7423,B8,Compliance_Trainings!$E$2:$E$7423,"Completed") -> 928 | D8: =COUNTIFS(Compliance_Trainings!$B$2:$B$7423,B8,Compliance_Trainings!$E$2:$E$7423,"In Progress") -> 102 | E8: =COUNTIFS(Compliance_Trainings!$B$2:$B$7423,B8,Compliance_Trainings!$E$2:$E$7423,"Not Started") -> 93 | F8: =COUNTIFS(Compliance_Trainings!$B$2:$B$7423,B8,Compliance_Trainings!$E$2:$E$7423,"Overdue") -> 114 | G8: =SUM(C8:F8) -> 1237 | H8: =C8/G8 -> 0.7502021 | I8: =AVERAGEIF(Compliance_Trainings!$B$2:$B$7423,B8,Compliance_Trainings!$G$2:$G$7423) -> 79.532328
B9: Data Privacy & DPDP Act | C9: =COUNTIFS(Compliance_Trainings!$B$2:$B$7423,B9,Compliance_Trainings!$E$2:$E$7423,"Completed") -> 936 | D9: =COUNTIFS(Compliance_Trainings!$B$2:$B$7423,B9,Compliance_Trainings!$E$2:$E$7423,"In Progress") -> 95 | E9: =COUNTIFS(Compliance_Trainings!$B$2:$B$7423,B9,Compliance_Trainings!$E$2:$E$7423,"Not Started") -> 77 | F9: =COUNTIFS(Compliance_Trainings!$B$2:$B$7423,B9,Compliance_Trainings!$E$2:$E$7423,"Overdue") -> 129 | G9: =SUM(C9:F9) -> 1237 | H9: =C9/G9 -> 0.75666936 | I9: =AVERAGEIF(Compliance_Trainings!$B$2:$B$7423,B9,Compliance_Trainings!$G$2:$G$7423) -> 79.646368
B10: Information Security | C10: =COUNTIFS(Compliance_Trainings!$B$2:$B$7423,B10,Compliance_Trainings!$E$2:$E$7423,"Completed") -> 922 | D10: =COUNTIFS(Compliance_Trainings!$B$2:$B$7423,B10,Compliance_Trainings!$E$2:$E$7423,"In Progress") -> 100 | E10: =COUNTIFS(Compliance_Trainings!$B$2:$B$7423,B10,Compliance_Trainings!$E$2:$E$7423,"Not Started") -> 91 | F10: =COUNTIFS(Compliance_Trainings!$B$2:$B$7423,B10,Compliance_Trainings!$E$2:$E$7423,"Overdue") -> 124 | G10: =SUM(C10:F10) -> 1237 | H10: =C10/G10 -> 0.74535166 | I10: =AVERAGEIF(Compliance_Trainings!$B$2:$B$7423,B10,Compliance_Trainings!$G$2:$G$7423) -> 79.229935
B11: Anti-Bribery | C11: =COUNTIFS(Compliance_Trainings!$B$2:$B$7423,B11,Compliance_Trainings!$E$2:$E$7423,"Completed") -> 909 | D11: =COUNTIFS(Compliance_Trainings!$B$2:$B$7423,B11,Compliance_Trainings!$E$2:$E$7423,"In Progress") -> 98 | E11: =COUNTIFS(Compliance_Trainings!$B$2:$B$7423,B11,Compliance_Trainings!$E$2:$E$7423,"Not Started") -> 96 | F11: =COUNTIFS(Compliance_Trainings!$B$2:$B$7423,B11,Compliance_Trainings!$E$2:$E$7423,"Overdue") -> 134 | G11: =SUM(C11:F11) -> 1237 | H11: =C11/G11 -> 0.73484236 | I11: =AVERAGEIF(Compliance_Trainings!$B$2:$B$7423,B11,Compliance_Trainings!$G$2:$G$7423) -> 79.574257
B12: Fire & Safety | C12: =COUNTIFS(Compliance_Trainings!$B$2:$B$7423,B12,Compliance_Trainings!$E$2:$E$7423,"Completed") -> 949 | D12: =COUNTIFS(Compliance_Trainings!$B$2:$B$7423,B12,Compliance_Trainings!$E$2:$E$7423,"In Progress") -> 95 | E12: =COUNTIFS(Compliance_Trainings!$B$2:$B$7423,B12,Compliance_Trainings!$E$2:$E$7423,"Not Started") -> 85 | F12: =COUNTIFS(Compliance_Trainings!$B$2:$B$7423,B12,Compliance_Trainings!$E$2:$E$7423,"Overdue") -> 108 | G12: =SUM(C12:F12) -> 1237 | H12: =C12/G12 -> 0.76717866 | I12: =AVERAGEIF(Compliance_Trainings!$B$2:$B$7423,B12,Compliance_Trainings!$G$2:$G$7423) -> 80.134879
B13: Total | C13: =SUM(C7:C12) -> 5585 | D13: =SUM(D7:D12) -> 590 | E13: =SUM(E7:E12) -> 516 | F13: =SUM(F7:F12) -> 731 | G13: =SUM(G7:G12) -> 7422 | H13: =C13/G13 -> 0.75249259 | I13: =AVERAGE(Compliance_Trainings!$G$2:$G$7423) -> 79.621844
B15: 2. Statutory & Policy Record Checks (1,500 employees)
B16: Check | C16: Employees | D16: % of Workforce
B17: Background verification cleared | C17: =COUNTIF(Compliance_Records!$B$2:$B$1501,"Cleared") -> 1356 | D17: =C17/COUNTA(Compliance_Records!$A$2:$A$1501) -> 0.904
B18: PF UAN linked | C18: =COUNTIF(Compliance_Records!$C$2:$C$1501,"Yes") -> 1420 | D18: =C18/COUNTA(Compliance_Records!$A$2:$A$1501) -> 0.94666667
B19: ESI applicable | C19: =COUNTIF(Compliance_Records!$D$2:$D$1501,"Yes") -> 0 | D19: =C19/COUNTA(Compliance_Records!$A$2:$A$1501) -> 0
B20: NDA signed | C20: =COUNTIF(Compliance_Records!$E$2:$E$1501,"Yes") -> 1443 | D20: =C20/COUNTA(Compliance_Records!$A$2:$A$1501) -> 0.962
B21: Policy acknowledged | C21: =COUNTIF(Compliance_Records!$F$2:$F$1501,"Yes") -> 1374 | D21: =C21/COUNTA(Compliance_Records!$A$2:$A$1501) -> 0.916
B23: 3. Grievances & Disciplinary
B24: Metric | C24: Count
B25: Total grievances raised | C25: =SUM(Compliance_Records!$G$2:$G$1501) -> 220
B26: Employees with >=1 grievance | C26: =COUNTIF(Compliance_Records!$G$2:$G$1501,">=1") -> 208
B27: Total POSH complaints | C27: =SUM(Compliance_Records!$H$2:$H$1501) -> 18
B28: Total disciplinary actions | C28: =SUM(Compliance_Records!$I$2:$I$1501) -> 72
B29: Employees with >=1 disciplinary action | C29: =COUNTIF(Compliance_Records!$I$2:$I$1501,">=1") -> 72

Sheet EDA_Attendance
B2: Attendance & Leave — EDA
B3: Monthly presence, leave usage, late logins and overtime (Oct 2025 – Sep 2026). Live formulas over the Attendance data sheet.
B5: 1. Monthly Summary
B6: Month | C6: Emp-Months | D6: Working Days | E6: Days Present | F6: Attendance % | G6: Sick Leave | H6: Casual Leave | I6: Unplanned Abs. | J6: Late Logins | K6: Overtime Hrs | L6: OT per Emp-Month
B7: 2025-10 | C7: =COUNTIF(Attendance!$B$2:$B$13892,B7) -> 1081 | D7: =SUMIF(Attendance!$B$2:$B$13892,B7,Attendance!$C$2:$C$13892) -> 23782 | E7: =SUMIF(Attendance!$B$2:$B$13892,B7,Attendance!$D$2:$D$13892) -> 22087 | F7: =E7/D7 -> 0.92872761 | G7: =SUMIF(Attendance!$B$2:$B$13892,B7,Attendance!$E$2:$E$13892) -> 655 | H7: =SUMIF(Attendance!$B$2:$B$13892,B7,Attendance!$F$2:$F$13892) -> 742 | I7: =SUMIF(Attendance!$B$2:$B$13892,B7,Attendance!$G$2:$G$13892) -> 363 | J7: =SUMIF(Attendance!$B$2:$B$13892,B7,Attendance!$H$2:$H$13892) -> 1634 | K7: =SUMIF(Attendance!$B$2:$B$13892,B7,Attendance!$I$2:$I$13892) -> 4513 | L7: =K7/C7 -> 4.1748381
B8: 2025-11 | C8: =COUNTIF(Attendance!$B$2:$B$13892,B8) -> 1096 | D8: =SUMIF(Attendance!$B$2:$B$13892,B8,Attendance!$C$2:$C$13892) -> 24112 | E8: =SUMIF(Attendance!$B$2:$B$13892,B8,Attendance!$D$2:$D$13892) -> 22469 | F8: =E8/D8 -> 0.93185965 | G8: =SUMIF(Attendance!$B$2:$B$13892,B8,Attendance!$E$2:$E$13892) -> 696 | H8: =SUMIF(Attendance!$B$2:$B$13892,B8,Attendance!$F$2:$F$13892) -> 755 | I8: =SUMIF(Attendance!$B$2:$B$13892,B8,Attendance!$G$2:$G$13892) -> 353 | J8: =SUMIF(Attendance!$B$2:$B$13892,B8,Attendance!$H$2:$H$13892) -> 1660 | K8: =SUMIF(Attendance!$B$2:$B$13892,B8,Attendance!$I$2:$I$13892) -> 4542 | L8: =K8/C8 -> 4.1441606
B9: 2025-12 | C9: =COUNTIF(Attendance!$B$2:$B$13892,B9) -> 1106 | D9: =SUMIF(Attendance!$B$2:$B$13892,B9,Attendance!$C$2:$C$13892) -> 24332 | E9: =SUMIF(Attendance!$B$2:$B$13892,B9,Attendance!$D$2:$D$13892) -> 22610 | F9: =E9/D9 -> 0.929229 | G9: =SUMIF(Attendance!$B$2:$B$13892,B9,Attendance!$E$2:$E$13892) -> 722 | H9: =SUMIF(Attendance!$B$2:$B$13892,B9,Attendance!$F$2:$F$13892) -> 741 | I9: =SUMIF(Attendance!$B$2:$B$13892,B9,Attendance!$G$2:$G$13892) -> 349 | J9: =SUMIF(Attendance!$B$2:$B$13892,B9,Attendance!$H$2:$H$13892) -> 1654 | K9: =SUMIF(Attendance!$B$2:$B$13892,B9,Attendance!$I$2:$I$13892) -> 4864 | L9: =K9/C9 -> 4.39783
B10: 2026-01 | C10: =COUNTIF(Attendance!$B$2:$B$13892,B10) -> 1125 | D10: =SUMIF(Attendance!$B$2:$B$13892,B10,Attendance!$C$2:$C$13892) -> 24750 | E10: =SUMIF(Attendance!$B$2:$B$13892,B10,Attendance!$D$2:$D$13892) -> 23031 | F10: =E10/D10 -> 0.93054545 | G10: =SUMIF(Attendance!$B$2:$B$13892,B10,Attendance!$E$2:$E$13892) -> 703 | H10: =SUMIF(Attendance!$B$2:$B$13892,B10,Attendance!$F$2:$F$13892) -> 762 | I10: =SUMIF(Attendance!$B$2:$B$13892,B10,Attendance!$G$2:$G$13892) -> 357 | J10: =SUMIF(Attendance!$B$2:$B$13892,B10,Attendance!$H$2:$H$13892) -> 1644 | K10: =SUMIF(Attendance!$B$2:$B$13892,B10,Attendance!$I$2:$I$13892) -> 4715 | L10: =K10/C10 -> 4.1911111
B11: 2026-02 | C11: =COUNTIF(Attendance!$B$2:$B$13892,B11) -> 1142 | D11: =SUMIF(Attendance!$B$2:$B$13892,B11,Attendance!$C$2:$C$13892) -> 25124 | E11: =SUMIF(Attendance!$B$2:$B$13892,B11,Attendance!$D$2:$D$13892) -> 23290 | F11: =E11/D11 -> 0.92700207 | G11: =SUMIF(Attendance!$B$2:$B$13892,B11,Attendance!$E$2:$E$13892) -> 690 | H11: =SUMIF(Attendance!$B$2:$B$13892,B11,Attendance!$F$2:$F$13892) -> 801 | I11: =SUMIF(Attendance!$B$2:$B$13892,B11,Attendance!$G$2:$G$13892) -> 380 | J11: =SUMIF(Attendance!$B$2:$B$13892,B11,Attendance!$H$2:$H$13892) -> 1722 | K11: =SUMIF(Attendance!$B$2:$B$13892,B11,Attendance!$I$2:$I$13892) -> 5205 | L11: =K11/C11 -> 4.5577933
B12: 2026-03 | C12: =COUNTIF(Attendance!$B$2:$B$13892,B12) -> 1158 | D12: =SUMIF(Attendance!$B$2:$B$13892,B12,Attendance!$C$2:$C$13892) -> 25476 | E12: =SUMIF(Attendance!$B$2:$B$13892,B12,Attendance!$D$2:$D$13892) -> 23691 | F12: =E12/D12 -> 0.92993406 | G12: =SUMIF(Attendance!$B$2:$B$13892,B12,Attendance!$E$2:$E$13892) -> 698 | H12: =SUMIF(Attendance!$B$2:$B$13892,B12,Attendance!$F$2:$F$13892) -> 821 | I12: =SUMIF(Attendance!$B$2:$B$13892,B12,Attendance!$G$2:$G$13892) -> 385 | J12: =SUMIF(Attendance!$B$2:$B$13892,B12,Attendance!$H$2:$H$13892) -> 1716 | K12: =SUMIF(Attendance!$B$2:$B$13892,B12,Attendance!$I$2:$I$13892) -> 4752 | L12: =K12/C12 -> 4.1036269
B13: 2026-04 | C13: =COUNTIF(Attendance!$B$2:$B$13892,B13) -> 1165 | D13: =SUMIF(Attendance!$B$2:$B$13892,B13,Attendance!$C$2:$C$13892) -> 25630 | E13: =SUMIF(Attendance!$B$2:$B$13892,B13,Attendance!$D$2:$D$13892) -> 23832 | F13: =E13/D13 -> 0.92984783 | G13: =SUMIF(Attendance!$B$2:$B$13892,B13,Attendance!$E$2:$E$13892) -> 720 | H13: =SUMIF(Attendance!$B$2:$B$13892,B13,Attendance!$F$2:$F$13892) -> 891 | I13: =SUMIF(Attendance!$B$2:$B$13892,B13,Attendance!$G$2:$G$13892) -> 421 | J13: =SUMIF(Attendance!$B$2:$B$13892,B13,Attendance!$H$2:$H$13892) -> 1749 | K13: =SUMIF(Attendance!$B$2:$B$13892,B13,Attendance!$I$2:$I$13892) -> 5251 | L13: =K13/C13 -> 4.5072961
B14: 2026-05 | C14: =COUNTIF(Attendance!$B$2:$B$13892,B14) -> 1178 | D14: =SUMIF(Attendance!$B$2:$B$13892,B14,Attendance!$C$2:$C$13892) -> 25916 | E14: =SUMIF(Attendance!$B$2:$B$13892,B14,Attendance!$D$2:$D$13892) -> 23992 | F14: =E14/D14 -> 0.92576015 | G14: =SUMIF(Attendance!$B$2:$B$13892,B14,Attendance!$E$2:$E$13892) -> 740 | H14: =SUMIF(Attendance!$B$2:$B$13892,B14,Attendance!$F$2:$F$13892) -> 878 | I14: =SUMIF(Attendance!$B$2:$B$13892,B14,Attendance!$G$2:$G$13892) -> 349 | J14: =SUMIF(Attendance!$B$2:$B$13892,B14,Attendance!$H$2:$H$13892) -> 1863 | K14: =SUMIF(Attendance!$B$2:$B$13892,B14,Attendance!$I$2:$I$13892) -> 5099 | L14: =K14/C14 -> 4.3285229
B15: 2026-06 | C15: =COUNTIF(Attendance!$B$2:$B$13892,B15) -> 1184 | D15: =SUMIF(Attendance!$B$2:$B$13892,B15,Attendance!$C$2:$C$13892) -> 26048 | E15: =SUMIF(Attendance!$B$2:$B$13892,B15,Attendance!$D$2:$D$13892) -> 24214 | F15: =E15/D15 -> 0.92959152 | G15: =SUMIF(Attendance!$B$2:$B$13892,B15,Attendance!$E$2:$E$13892) -> 733 | H15: =SUMIF(Attendance!$B$2:$B$13892,B15,Attendance!$F$2:$F$13892) -> 818 | I15: =SUMIF(Attendance!$B$2:$B$13892,B15,Attendance!$G$2:$G$13892) -> 367 | J15: =SUMIF(Attendance!$B$2:$B$13892,B15,Attendance!$H$2:$H$13892) -> 1761 | K15: =SUMIF(Attendance!$B$2:$B$13892,B15,Attendance!$I$2:$I$13892) -> 5312 | L15: =K15/C15 -> 4.4864865
B16: 2026-07 | C16: =COUNTIF(Attendance!$B$2:$B$13892,B16) -> 1189 | D16: =SUMIF(Attendance!$B$2:$B$13892,B16,Attendance!$C$2:$C$13892) -> 26158 | E16: =SUMIF(Attendance!$B$2:$B$13892,B16,Attendance!$D$2:$D$13892) -> 24303 | F16: =E16/D16 -> 0.92908479 | G16: =SUMIF(Attendance!$B$2:$B$13892,B16,Attendance!$E$2:$E$13892) -> 704 | H16: =SUMIF(Attendance!$B$2:$B$13892,B16,Attendance!$F$2:$F$13892) -> 889 | I16: =SUMIF(Attendance!$B$2:$B$13892,B16,Attendance!$G$2:$G$13892) -> 395 | J16: =SUMIF(Attendance!$B$2:$B$13892,B16,Attendance!$H$2:$H$13892) -> 1761 | K16: =SUMIF(Attendance!$B$2:$B$13892,B16,Attendance!$I$2:$I$13892) -> 4964 | L16: =K16/C16 -> 4.1749369
B17: 2026-08 | C17: =COUNTIF(Attendance!$B$2:$B$13892,B17) -> 1197 | D17: =SUMIF(Attendance!$B$2:$B$13892,B17,Attendance!$C$2:$C$13892) -> 26334 | E17: =SUMIF(Attendance!$B$2:$B$13892,B17,Attendance!$D$2:$D$13892) -> 24543 | F17: =E17/D17 -> 0.93198906 | G17: =SUMIF(Attendance!$B$2:$B$13892,B17,Attendance!$E$2:$E$13892) -> 776 | H17: =SUMIF(Attendance!$B$2:$B$13892,B17,Attendance!$F$2:$F$13892) -> 810 | I17: =SUMIF(Attendance!$B$2:$B$13892,B17,Attendance!$G$2:$G$13892) -> 378 | J17: =SUMIF(Attendance!$B$2:$B$13892,B17,Attendance!$H$2:$H$13892) -> 1701 | K17: =SUMIF(Attendance!$B$2:$B$13892,B17,Attendance!$I$2:$I$13892) -> 5197 | L17: =K17/C17 -> 4.3416876
B18: 2026-09 | C18: =COUNTIF(Attendance!$B$2:$B$13892,B18) -> 1270 | D18: =SUMIF(Attendance!$B$2:$B$13892,B18,Attendance!$C$2:$C$13892) -> 27940 | E18: =SUMIF(Attendance!$B$2:$B$13892,B18,Attendance!$D$2:$D$13892) -> 26011 | F18: =E18/D18 -> 0.9309592 | G18: =SUMIF(Attendance!$B$2:$B$13892,B18,Attendance!$E$2:$E$13892) -> 751 | H18: =SUMIF(Attendance!$B$2:$B$13892,B18,Attendance!$F$2:$F$13892) -> 864 | I18: =SUMIF(Attendance!$B$2:$B$13892,B18,Attendance!$G$2:$G$13892) -> 409 | J18: =SUMIF(Attendance!$B$2:$B$13892,B18,Attendance!$H$2:$H$13892) -> 1904 | K18: =SUMIF(Attendance!$B$2:$B$13892,B18,Attendance!$I$2:$I$13892) -> 5532 | L18: =K18/C18 -> 4.3559055
B19: Total | C19: =SUM(C7:C18) -> 13891 | D19: =SUM(D7:D18) -> 305602 | E19: =SUM(E7:E18) -> 284073 | F19: =E19/D19 -> 0.92955216 | G19: =SUM(G7:G18) -> 8588 | H19: =SUM(H7:H18) -> 9772 | I19: =SUM(I7:I18) -> 4506 | J19: =SUM(J7:J18) -> 20769 | K19: =SUM(K7:K18) -> 59946 | L19: =K19/C19 -> 4.3154561
B21: 2. Key Indicators (12-month window)
B22: Indicator | C22: Value
B23: Overall attendance rate | C23: =SUM(Attendance!$D$2:$D$13892)/SUM(Attendance!$C$2:$C$13892) -> 0.92955216
B24: Total sick leave days | C24: =SUM(Attendance!$E$2:$E$13892) -> 8588
B25: Total casual leave days | C25: =SUM(Attendance!$F$2:$F$13892) -> 9772
B26: Total unplanned absences | C26: =SUM(Attendance!$G$2:$G$13892) -> 4506
B27: Total late logins | C27: =SUM(Attendance!$H$2:$H$13892) -> 20769
B28: Avg late logins per emp-month | C28: =SUM(Attendance!$H$2:$H$13892)/COUNTA(Attendance!$A$2:$A$13892) -> 1.4951407
B29: Total overtime hours | C29: =SUM(Attendance!$I$2:$I$13892) -> 59946
B30: Avg overtime hrs per emp-month | C30: =SUM(Attendance!$I$2:$I$13892)/COUNTA(Attendance!$A$2:$A$13892) -> 4.3154561

Sheet EDA_Recruitment
B2: Recruitment — EDA
B3: Hiring funnel, source effectiveness, cost and speed. Live formulas over the Recruitment data sheet.
B5: 1. Overall Funnel
B6: Funnel Stage | C6: Volume | D6: Step Conversion
B7: Applicants | C7: =SUM(Recruitment!$H$2:$H$1501) -> 112455
B8: Interviews | C8: =SUM(Recruitment!$I$2:$I$1501) -> 12756 | D8: =C8/C7 -> 0.11343204
B9: Offers Made | C9: =SUM(Recruitment!$J$2:$J$1501) -> 2422 | D9: =C9/C8 -> 0.18987143
B10: Hires (requisitions closed) | C10: =COUNTA(Recruitment!$A$2:$A$1501) -> 1500 | D10: =C10/C9 -> 0.61932287
B12: 2. Source Effectiveness
B13: Source | C13: Hires | D13: Applicants | E13: Interviews | F13: Offers | G13: Offers per Hire | H13: Applicants per Hire | I13: Avg Cost/Hire | J13: Avg Time-to-Offer (d) | K13: Avg Time-to-Hire (d) | L13: Total Spend
B14: Job Portal | C14: =COUNTIF(Recruitment!$L$2:$L$1501,B14) -> 430 | D14: =SUMIF(Recruitment!$L$2:$L$1501,B14,Recruitment!$H$2:$H$1501) -> 32431 | E14: =SUMIF(Recruitment!$L$2:$L$1501,B14,Recruitment!$I$2:$I$1501) -> 3650 | F14: =SUMIF(Recruitment!$L$2:$L$1501,B14,Recruitment!$J$2:$J$1501) -> 687 | G14: =F14/C14 -> 1.5976744 | H14: =D14/C14 -> 75.42093 | I14: =AVERAGEIF(Recruitment!$L$2:$L$1501,B14,Recruitment!$K$2:$K$1501) -> 37145.986 | J14: =AVERAGEIF(Recruitment!$L$2:$L$1501,B14,Recruitment!$M$2:$M$1501) -> 18.295349 | K14: =AVERAGEIF(Recruitment!$L$2:$L$1501,B14,Recruitment!$N$2:$N$1501) -> 55.260465 | L14: =SUMIF(Recruitment!$L$2:$L$1501,B14,Recruitment!$K$2:$K$1501) -> 15972774
B15: Referral | C15: =COUNTIF(Recruitment!$L$2:$L$1501,B15) -> 400 | D15: =SUMIF(Recruitment!$L$2:$L$1501,B15,Recruitment!$H$2:$H$1501) -> 30247 | E15: =SUMIF(Recruitment!$L$2:$L$1501,B15,Recruitment!$I$2:$I$1501) -> 3409 | F15: =SUMIF(Recruitment!$L$2:$L$1501,B15,Recruitment!$J$2:$J$1501) -> 654 | G15: =F15/C15 -> 1.635 | H15: =D15/C15 -> 75.6175 | I15: =AVERAGEIF(Recruitment!$L$2:$L$1501,B15,Recruitment!$K$2:$K$1501) -> 35703.518 | J15: =AVERAGEIF(Recruitment!$L$2:$L$1501,B15,Recruitment!$M$2:$M$1501) -> 16.825 | K15: =AVERAGEIF(Recruitment!$L$2:$L$1501,B15,Recruitment!$N$2:$N$1501) -> 54.125 | L15: =SUMIF(Recruitment!$L$2:$L$1501,B15,Recruitment!$K$2:$K$1501) -> 14281407
B16: LinkedIn | C16: =COUNTIF(Recruitment!$L$2:$L$1501,B16) -> 293 | D16: =SUMIF(Recruitment!$L$2:$L$1501,B16,Recruitment!$H$2:$H$1501) -> 21030 | E16: =SUMIF(Recruitment!$L$2:$L$1501,B16,Recruitment!$I$2:$I$1501) -> 2571 | F16: =SUMIF(Recruitment!$L$2:$L$1501,B16,Recruitment!$J$2:$J$1501) -> 472 | G16: =F16/C16 -> 1.6109215 | H16: =D16/C16 -> 71.774744 | I16: =AVERAGEIF(Recruitment!$L$2:$L$1501,B16,Recruitment!$K$2:$K$1501) -> 37297.553 | J16: =AVERAGEIF(Recruitment!$L$2:$L$1501,B16,Recruitment!$M$2:$M$1501) -> 15.300341 | K16: =AVERAGEIF(Recruitment!$L$2:$L$1501,B16,Recruitment!$N$2:$N$1501) -> 51.488055 | L16: =SUMIF(Recruitment!$L$2:$L$1501,B16,Recruitment!$K$2:$K$1501) -> 10928183
B17: Campus | C17: =COUNTIF(Recruitment!$L$2:$L$1501,B17) -> 235 | D17: =SUMIF(Recruitment!$L$2:$L$1501,B17,Recruitment!$H$2:$H$1501) -> 18287 | E17: =SUMIF(Recruitment!$L$2:$L$1501,B17,Recruitment!$I$2:$I$1501) -> 1936 | F17: =SUMIF(Recruitment!$L$2:$L$1501,B17,Recruitment!$J$2:$J$1501) -> 384 | G17: =F17/C17 -> 1.6340426 | H17: =D17/C17 -> 77.817021 | I17: =AVERAGEIF(Recruitment!$L$2:$L$1501,B17,Recruitment!$K$2:$K$1501) -> 35130.613 | J17: =AVERAGEIF(Recruitment!$L$2:$L$1501,B17,Recruitment!$M$2:$M$1501) -> 14.595745 | K17: =AVERAGEIF(Recruitment!$L$2:$L$1501,B17,Recruitment!$N$2:$N$1501) -> 52.438298 | L17: =SUMIF(Recruitment!$L$2:$L$1501,B17,Recruitment!$K$2:$K$1501) -> 8255694
B18: Consultant | C18: =COUNTIF(Recruitment!$L$2:$L$1501,B18) -> 142 | D18: =SUMIF(Recruitment!$L$2:$L$1501,B18,Recruitment!$H$2:$H$1501) -> 10460 | E18: =SUMIF(Recruitment!$L$2:$L$1501,B18,Recruitment!$I$2:$I$1501) -> 1190 | F18: =SUMIF(Recruitment!$L$2:$L$1501,B18,Recruitment!$J$2:$J$1501) -> 225 | G18: =F18/C18 -> 1.584507 | H18: =D18/C18 -> 73.661972 | I18: =AVERAGEIF(Recruitment!$L$2:$L$1501,B18,Recruitment!$K$2:$K$1501) -> 36275.585 | J18: =AVERAGEIF(Recruitment!$L$2:$L$1501,B18,Recruitment!$M$2:$M$1501) -> 18.119718 | K18: =AVERAGEIF(Recruitment!$L$2:$L$1501,B18,Recruitment!$N$2:$N$1501) -> 55.309859 | L18: =SUMIF(Recruitment!$L$2:$L$1501,B18,Recruitment!$K$2:$K$1501) -> 5151133
B20: 3. Hiring by Department
B21: Department | C21: Hires | D21: Avg Cost/Hire | E21: Avg Time-to-Hire (d) | F21: Total Spend
B22: Engineering | C22: =COUNTIF(Recruitment!$C$2:$C$1501,B22) -> 455 | D22: =AVERAGEIF(Recruitment!$C$2:$C$1501,B22,Recruitment!$K$2:$K$1501) -> 34237.963 | E22: =AVERAGEIF(Recruitment!$C$2:$C$1501,B22,Recruitment!$N$2:$N$1501) -> 53.413187 | F22: =SUMIF(Recruitment!$C$2:$C$1501,B22,Recruitment!$K$2:$K$1501) -> 15578273
B23: Data & AI | C23: =COUNTIF(Recruitment!$C$2:$C$1501,B23) -> 139 | D23: =AVERAGEIF(Recruitment!$C$2:$C$1501,B23,Recruitment!$K$2:$K$1501) -> 37789.77 | E23: =AVERAGEIF(Recruitment!$C$2:$C$1501,B23,Recruitment!$N$2:$N$1501) -> 51.618705 | F23: =SUMIF(Recruitment!$C$2:$C$1501,B23,Recruitment!$K$2:$K$1501) -> 5252778
B24: Sales | C24: =COUNTIF(Recruitment!$C$2:$C$1501,B24) -> 207 | D24: =AVERAGEIF(Recruitment!$C$2:$C$1501,B24,Recruitment!$K$2:$K$1501) -> 37597.556 | E24: =AVERAGEIF(Recruitment!$C$2:$C$1501,B24,Recruitment!$N$2:$N$1501) -> 53.830918 | F24: =SUMIF(Recruitment!$C$2:$C$1501,B24,Recruitment!$K$2:$K$1501) -> 7782694
B25: Customer Support | C25: =COUNTIF(Recruitment!$C$2:$C$1501,B25) -> 207 | D25: =AVERAGEIF(Recruitment!$C$2:$C$1501,B25,Recruitment!$K$2:$K$1501) -> 36322.348 | E25: =AVERAGEIF(Recruitment!$C$2:$C$1501,B25,Recruitment!$N$2:$N$1501) -> 53.671498 | F25: =SUMIF(Recruitment!$C$2:$C$1501,B25,Recruitment!$K$2:$K$1501) -> 7518726
B26: Operations | C26: =COUNTIF(Recruitment!$C$2:$C$1501,B26) -> 145 | D26: =AVERAGEIF(Recruitment!$C$2:$C$1501,B26,Recruitment!$K$2:$K$1501) -> 36189.441 | E26: =AVERAGEIF(Recruitment!$C$2:$C$1501,B26,Recruitment!$N$2:$N$1501) -> 56.696552 | F26: =SUMIF(Recruitment!$C$2:$C$1501,B26,Recruitment!$K$2:$K$1501) -> 5247469
B27: Finance | C27: =COUNTIF(Recruitment!$C$2:$C$1501,B27) -> 97 | D27: =AVERAGEIF(Recruitment!$C$2:$C$1501,B27,Recruitment!$K$2:$K$1501) -> 34839.557 | E27: =AVERAGEIF(Recruitment!$C$2:$C$1501,B27,Recruitment!$N$2:$N$1501) -> 52.773196 | F27: =SUMIF(Recruitment!$C$2:$C$1501,B27,Recruitment!$K$2:$K$1501) -> 3379437
B28: Human Resources | C28: =COUNTIF(Recruitment!$C$2:$C$1501,B28) -> 82 | D28: =AVERAGEIF(Recruitment!$C$2:$C$1501,B28,Recruitment!$K$2:$K$1501) -> 37565.146 | E28: =AVERAGEIF(Recruitment!$C$2:$C$1501,B28,Recruitment!$N$2:$N$1501) -> 52.146341 | F28: =SUMIF(Recruitment!$C$2:$C$1501,B28,Recruitment!$K$2:$K$1501) -> 3080342
B29: Marketing | C29: =COUNTIF(Recruitment!$C$2:$C$1501,B29) -> 100 | D29: =AVERAGEIF(Recruitment!$C$2:$C$1501,B29,Recruitment!$K$2:$K$1501) -> 38135.04 | E29: =AVERAGEIF(Recruitment!$C$2:$C$1501,B29,Recruitment!$N$2:$N$1501) -> 56.33 | F29: =SUMIF(Recruitment!$C$2:$C$1501,B29,Recruitment!$K$2:$K$1501) -> 3813504
B30: Legal & Compliance | C30: =COUNTIF(Recruitment!$C$2:$C$1501,B30) -> 68 | D30: =AVERAGEIF(Recruitment!$C$2:$C$1501,B30,Recruitment!$K$2:$K$1501) -> 43176 | E30: =AVERAGEIF(Recruitment!$C$2:$C$1501,B30,Recruitment!$N$2:$N$1501) -> 54.338235 | F30: =SUMIF(Recruitment!$C$2:$C$1501,B30,Recruitment!$K$2:$K$1501) -> 2935968

Sheet Departments
A1: dept_id | B1: dept_name | C1: hq_location | D1: annual_budget_inr_cr | E1: head_count_target
A2: D01 | B2: Engineering | C2: Chennai | D2: 31.41 | E2: 472
A3: D02 | B3: Data & AI | C3: Bengaluru | D3: 18.68 | E3: 157
A4: D03 | B4: Sales | C4: Mumbai | D4: 34.63 | E4: 220
A5: D04 | B5: Customer Support | C5: Coimbatore | D5: 28.5 | E5: 220
A6: D05 | B6: Operations | C6: Coimbatore | D6: 5.58 | E6: 157
A7: D06 | B7: Finance | C7: Chennai | D7: 39.07 | E7: 94
A8: D07 | B8: Human Resources | C8: Coimbatore | D8: 30.92 | E8: 78
A9: D08 | B9: Marketing | C9: Bengaluru | D9: 31.87 | E9: 94
A10: D09 | B10: Legal & Compliance | C10: Mumbai | D10: 6.87 | E10: 78

Sheet Employees
A1: employee_id | B1: first_name | C1: last_name | D1: gender | E1: age | F1: marital_status | G1: education | H1: dept_id | I1: department | J1: job_role | K1: job_level | L1: work_location | M1: work_mode | N1: employment_type | O1: hire_date | P1: annual_ctc_inr | Q1: distance_from_home_km | R1: overtime | S1: hiring_source | T1: manager_id | U1: employment_status | V1: hire_year | W1: age_band
A2: E10001 | B2: Priya | C2: Rao | D2: Female | E2: 28 | F2: Single | G2: Bachelor's | H2: D03 | I2: Sales | J2: Sales Executive | K2: L1 | L2: Bengaluru | M2: Onsite | N2: Full-time | O2: 43925 | P2: 461000 | Q2: 9 | R2: No | S2: Consultant | T2: E10776 | U2: Active | V2: =IF(O2="","",YEAR(O2)) -> 2020 | W2: =IF(E2<25,"21-24",IF(E2<30,"25-29",IF(E2<35,"30-34",IF(E2<40,"35-39",IF(E2<45,"40-44","45+"))))) -> 25-29
A3: E10002 | B3: Manoj | C3: Nair | D3: Male | E3: 23 | F3: Single | G3: Master's | H3: D08 | I3: Marketing | J3: Marketing Executive | K3: L1 | L3: Bengaluru | M3: Remote | N3: Full-time | O3: 46129 | P3: 417000 | Q3: 4 | R3: Yes | S3: Referral | T3: E11057 | U3: Active | V3: =IF(O3="","",YEAR(O3)) -> 2026 | W3: =IF(E3<25,"21-24",IF(E3<30,"25-29",IF(E3<35,"30-34",IF(E3<40,"35-39",IF(E3<45,"40-44","45+"))))) -> 21-24
A4: E10003 | B4: Siddharth | C4: Iyer | D4: Female | E4: 21 | F4: Married | G4: Bachelor's | H4: D03 | I4: Sales | J4: Sales Executive | K4: L1 | L4: Mumbai | M4: Hybrid | N4: Full-time | O4: 46245 | P4: 409000 | Q4: 11 | R4: Yes | S4: Referral | T4: E10242 | U4: Active | V4: =IF(O4="","",YEAR(O4)) -> 2026 | W4: =IF(E4<25,"21-24",IF(E4<30,"25-29",IF(E4<35,"30-34",IF(E4<40,"35-39",IF(E4<45,"40-44","45+"))))) -> 21-24
A5: E10004 | B5: Mary | C5: Sharma | D5: Female | E5: 30 | F5: Married | G5: Bachelor's | H5: D01 | I5: Engineering | J5: QA Engineer | K5: L2 | L5: Coimbatore | M5: Onsite | N5: Full-time | O5: 44101 | P5: 1164000 | Q5: 19 | R5: No | S5: Campus | T5: E11358 | U5: Active | V5: =IF(O5="","",YEAR(O5)) -> 2020 | W5: =IF(E5<25,"21-24",IF(E5<30,"25-29",IF(E5<35,"30-34",IF(E5<40,"35-39",IF(E5<45,"40-44","45+"))))) -> 30-34
A6: E10005 | B6: Sneha | C6: Menon | D6: Male | E6: 27 | F6: Single | G6: Bachelor's | H6: D04 | I6: Customer Support | J6: Support Associate | K6: L1 | L6: Hyderabad | M6: Onsite | N6: Full-time | O6: 45609 | P6: 308000 | Q6: 14 | R6: No | S6: Campus | T6: E10781 | U6: Active | V6: =IF(O6="","",YEAR(O6)) -> 2024 | W6: =IF(E6<25,"21-24",IF(E6<30,"25-29",IF(E6<35,"30-34",IF(E6<40,"35-39",IF(E6<45,"40-44","45+"))))) -> 25-29
A7: E10006 | B7: Rohit | C7: Verma | D7: Male | E7: 31 | F7: Single | G7: Bachelor's | H7: D06 | I7: Finance | J7: Accountant | K7: L2 | L7: Bengaluru | M7: Hybrid | N7: Full-time | O7: 44794 | P7: 1251000 | Q7: 10 | R7: No | S7: Job Portal | T7: E11361 | U7: Active | V7: =IF(O7="","",YEAR(O7)) -> 2022 | W7: =IF(E7<25,"21-24",IF(E7<30,"25-29",IF(E7<35,"30-34",IF(E7<40,"35-39",IF(E7<45,"40-44","45+"))))) -> 30-34
A8: E10007 | B8: Janani | C8: Menon | D8: Male | E8: 27 | F8: Single | G8: MBA | H8: D02 | I8: Data & AI | J8: Data Analyst | K8: L2 | L8: Hyderabad | M8: Hybrid | N8: Full-time | O8: 44904 | P8: 889000 | Q8: 23 | R8: No | S8: Job Portal | T8: E10019 | U8: Exited | V8: =IF(O8="","",YEAR(O8)) -> 2022 | W8: =IF(E8<25,"21-24",IF(E8<30,"25-29",IF(E8<35,"30-34",IF(E8<40,"35-39",IF(E8<45,"40-44","45+"))))) -> 25-29
A9: E10008 | B9: Siddharth | C9: Shetty | D9: Male | E9: 25 | F9: Single | G9: Bachelor's | H9: D01 | I9: Engineering | J9: DevOps Engineer | K9: L2 | L9: Coimbatore | M9: Remote | N9: Full-time | O9: 44975 | P9: 965000 | Q9: 6 | R9: No | S9: Campus | T9: E11358 | U9: Exited | V9: =IF(O9="","",YEAR(O9)) -> 2023 | W9: =IF(E9<25,"21-24",IF(E9<30,"25-29",IF(E9<35,"30-34",IF(E9<40,"35-39",IF(E9<45,"40-44","45+"))))) -> 25-29
A10: E10009 | B10: Aditya | C10: Subramanian | D10: Male | E10: 29 | F10: Single | G10: Bachelor's | H10: D04 | I10: Customer Support | J10: Senior Support Associate | K10: L3 | L10: Coimbatore | M10: Hybrid | N10: Full-time | O10: 45064 | P10: 1450000 | Q10: 4 | R10: No | S10: Campus | T10: E11344 | U10: Active | V10: =IF(O10="","",YEAR(O10)) -> 2023 | W10: =IF(E10<25,"21-24",IF(E10<30,"25-29",IF(E10<35,"30-34",IF(E10<40,"35-39",IF(E10<45,"40-44","45+"))))) -> 25-29
A11: E10010 | B11: Arun | C11: Patel | D11: Male | E11: 28 | F11: Married | G11: Bachelor's | H11: D01 | I11: Engineering | J11: Tech Lead | K11: L3 | L11: Hyderabad | M11: Hybrid | N11: Full-time | O11: 45048 | P11: 2339000 | Q11: 12 | R11: No | S11: Job Portal | T11: E10916 | U11: Active | V11: =IF(O11="","",YEAR(O11)) -> 2023 | W11: =IF(E11<25,"21-24",IF(E11<30,"25-29",IF(E11<35,"30-34",IF(E11<40,"35-39",IF(E11<45,"40-44","45+"))))) -> 25-29
A12: E10011 | B12: Mary | C12: Das | D12: Male | E12: 33 | F12: Single | G12: Master's | H12: D01 | I12: Engineering | J12: DevOps Engineer | K12: L2 | L12: Coimbatore | M12: Hybrid | N12: Full-time | O12: 42367 | P12: 712000 | Q12: 11 | R12: No | S12: Referral | T12: E10786 | U12: Exited | V12: =IF(O12="","",YEAR(O12)) -> 2015 | W12: =IF(E12<25,"21-24",IF(E12<30,"25-29",IF(E12<35,"30-34",IF(E12<40,"35-39",IF(E12<45,"40-44","45+"))))) -> 30-34
A13: E10012 | B13: Meena | C13: Menon | D13: Female | E13: 31 | F13: Single | G13: MBA | H13: D01 | I13: Engineering | J13: Tech Lead | K13: L3 | L13: Coimbatore | M13: Hybrid | N13: Full-time | O13: 44923 | P13: 2396000 | Q13: 5 | R13: Yes | S13: Job Portal | T13: E11103 | U13: Active | V13: =IF(O13="","",YEAR(O13)) -> 2022 | W13: =IF(E13<25,"21-24",IF(E13<30,"25-29",IF(E13<35,"30-34",IF(E13<40,"35-39",IF(E13<45,"40-44","45+"))))) -> 30-34
... A176: E10175 | B176: Bhavya | C176: Iyer | D176: Female | E176: 41 | F176: Single | G176: Bachelor's | H176: D01 | I176: Engineering | J176: Engineering Manager | K176: L4 | L176: Coimbatore | M176: Hybrid | N176: Full-time | O176: 43971 | P176: 4495000 | Q176: 24 | R176: No | S176: Job Portal | T176: E10585 | U176: Exited | V176: =IF(O176="","",YEAR(O176)) -> 2020 | W176: =IF(E176<25,"21-24",IF(E176<30,"25-29",IF(E176<35,"30-34",IF(E176<40,"35-39",IF(E176<45,"40-44","45+"))))) -> 40-44
A177: E10176 | B177: John | C177: Subramanian | D177: Male | E177: 32 | F177: Single | G177: Bachelor's | H177: D07 | I177: Human Resources | J177: HR Manager | K177: L4 | L177: Chennai | M177: Remote | N177: Full-time | O177: 44194 | P177: 3284000 | Q177: 31 | R177: No | S177: LinkedIn | U177: Active | V177: =IF(O177="","",YEAR(O177)) -> 2020 | W177: =IF(E177<25,"21-24",IF(E177<30,"25-29",IF(E177<35,"30-34",IF(E177<40,"35-39",IF(E177<45,"40-44","45+"))))) -> 30-34
A178: E10177 | B178: Imran | C178: Raman | D178: Female | E178: 28 | F178: Divorced | G178: Bachelor's | H178: D02 | I178: Data & AI | J178: Data Scientist | K178: L2 | L178: Coimbatore | M178: Remote | N178: Contract | O178: 44239 | P178: 689000 | Q178: 15 | R178: Yes | S178: LinkedIn | T178: E10316 | U178: Active | V178: =IF(O178="","",YEAR(O178)) -> 2021 | W178: =IF(E178<25,"21-24",IF(E178<30,"25-29",IF(E178<35,"30-34",IF(E178<40,"35-39",IF(E178<45,"40-44","45+"))))) -> 25-29
A179: E10178 | B179: Deepa | C179: Nair | D179: Female | E179: 38 | F179: Single | G179: Diploma | H179: D03 | I179: Sales | J179: Regional Sales Manager | K179: L4 | L179: Hyderabad | M179: Remote | N179: Full-time | O179: 43294 | P179: 4681000 | Q179: 10 | R179: No | S179: Referral | T179: E10839 | U179: Active | V179: =IF(O179="","",YEAR(O179)) -> 2018 | W179: =IF(E179<25,"21-24",IF(E179<30,"25-29",IF(E179<35,"30-34",IF(E179<40,"35-39",IF(E179<45,"40-44","45+"))))) -> 35-39
A180: E10179 | B180: Arun | C180: Reddy | D180: Male | E180: 23 | F180: Married | G180: Bachelor's | H180: D01 | I180: Engineering | J180: DevOps Engineer | K180: L2 | L180: Coimbatore | M180: Hybrid | N180: Full-time | O180: 45680 | P180: 717000 | Q180: 10 | R180: Yes | S180: Consultant | T180: E10432 | U180: Active | V180: =IF(O180="","",YEAR(O180)) -> 2025 | W180: =IF(E180<25,"21-24",IF(E180<30,"25-29",IF(E180<35,"30-34",IF(E180<40,"35-39",IF(E180<45,"40-44","45+"))))) -> 21-24
A181: E10180 | B181: Manoj | C181: Patel | D181: Female | E181: 25 | F181: Married | G181: Diploma | H181: D08 | I181: Marketing | J181: Content Strategist | K181: L2 | L181: Pune | M181: Hybrid | N181: Full-time | O181: 45363 | P181: 1096000 | Q181: 9 | R181: No | S181: Job Portal | T181: E11234 | U181: Active | V181: =IF(O181="","",YEAR(O181)) -> 2024 | W181: =IF(E181<25,"21-24",IF(E181<30,"25-29",IF(E181<35,"30-34",IF(E181<40,"35-39",IF(E181<45,"40-44","45+"))))) -> 25-29
A182: E10181 | B182: Divya | C182: Fernandes | D182: Male | E182: 45 | F182: Divorced | G182: Bachelor's | H182: D03 | I182: Sales | J182: Regional Sales Manager | K182: L4 | L182: Chennai | M182: Onsite | N182: Full-time | O182: 45179 | P182: 3666000 | Q182: 38 | R182: No | S182: Job Portal | T182: E11029 | U182: Active | V182: =IF(O182="","",YEAR(O182)) -> 2023 | W182: =IF(E182<25,"21-24",IF(E182<30,"25-29",IF(E182<35,"30-34",IF(E182<40,"35-39",IF(E182<45,"40-44","45+"))))) -> 45+
A183: E10182 | B183: Anjali | C183: Gupta | D183: Male | E183: 27 | F183: Married | G183: Master's | H183: D05 | I183: Operations | J183: Operations Executive | K183: L1 | L183: Bengaluru | M183: Hybrid | N183: Full-time | O183: 45699 | P183: 416000 | Q183: 7 | R183: Yes | S183: Campus | T183: E10560 | U183: Active | V183: =IF(O183="","",YEAR(O183)) -> 2025 | W183: =IF(E183<25,"21-24",IF(E183<30,"25-29",IF(E183<35,"30-34",IF(E183<40,"35-39",IF(E183<45,"40-44","45+"))))) -> 25-29
A184: E10183 | B184: Shalini | C184: Khan | D184: Female | E184: 29 | F184: Married | G184: Master's | H184: D09 | I184: Legal & Compliance | J184: Compliance Officer | K184: L2 | L184: Bengaluru | M184: Remote | N184: Full-time | O184: 44654 | P184: 1201000 | Q184: 14 | R184: No | S184: Referral | T184: E11109 | U184: Active | V184: =IF(O184="","",YEAR(O184)) -> 2022 | W184: =IF(E184<25,"21-24",IF(E184<30,"25-29",IF(E184<35,"30-34",IF(E184<40,"35-39",IF(E184<45,"40-44","45+"))))) -> 25-29
A185: E10184 | B185: Varun | C185: Das | D185: Male | E185: 28 | F185: Married | G185: Bachelor's | H185: D01 | I185: Engineering | J185: QA Engineer | K185: L2 | L185: Mumbai | M185: Remote | N185: Full-time | O185: 45141 | P185: 867000 | Q185: 20 | R185: Yes | S185: Job Portal | T185: E11200 | U185: Active | V185: =IF(O185="","",YEAR(O185)) -> 2023 | W185: =IF(E185<25,"21-24",IF(E185<30,"25-29",IF(E185<35,"30-34",IF(E185<40,"35-39",IF(E185<45,"40-44","45+"))))) -> 25-29
A186: E10185 | B186: Bhavya | C186: Khan | D186: Male | E186: 30 | F186: Married | G186: Diploma | H186: D08 | I186: Marketing | J186: Content Strategist | K186: L2 | L186: Coimbatore | M186: Hybrid | N186: Full-time | O186: 44927 | P186: 1134000 | Q186: 14 | R186: No | S186: LinkedIn | T186: E11349 | U186: Active | V186: =IF(O186="","",YEAR(O186)) -> 2023 | W186: =IF(E186<25,"21-24",IF(E186<30,"25-29",IF(E186<35,"30-34",IF(E186<40,"35-39",IF(E186<45,"40-44","45+"))))) -> 30-34
A187: E10186 | B187: Janani | C187: Gupta | D187: Male | E187: 41 | F187: Married | G187: Master's | H187: D03 | I187: Sales | J187: Regional Sales Manager | K187: L4 | L187: Hyderabad | M187: Remote | N187: Contract | O187: 45086 | P187: 3586000 | Q187: 29 | R187: No | S187: Job Portal | T187: E10233 | U187: Active | V187: =IF(O187="","",YEAR(O187)) -> 2023 | W187: =IF(E187<25,"21-24",IF(E187<30,"25-29",IF(E187<35,"30-34",IF(E187<40,"35-39",IF(E187<45,"40-44","45+"))))) -> 40-44
A188: E10187 | B188: Naveen | C188: Gupta | D188: Male | E188: 26 | F188: Married | G188: MBA | H188: D04 | I188: Customer Support | J188: Senior Support Associate | K188: L3 | L188: Bengaluru | M188: Hybrid | N188: Full-time | O188: 45748 | P188: 1690000 | Q188: 4 | R188: No | S188: Referral | T188: E10493 | U188: Active | V188: =IF(O188="","",YEAR(O188)) -> 2025 | W188: =IF(E188<25,"21-24",IF(E188<30,"25-29",IF(E188<35,"30-34",IF(E188<40,"35-39",IF(E188<45,"40-44","45+"))))) -> 25-29
A189: E10188 | B189: Deepa | C189: Rao | D189: Male | E189: 28 | F189: Married | G189: Master's | H189: D05 | I189: Operations | J189: Process Analyst | K189: L2 | L189: Mumbai | M189: Hybrid | N189: Full-time | O189: 44814 | P189: 1290000 | Q189: 37 | R189: No | S189: LinkedIn | T189: E11072 | U189: Active | V189: =IF(O189="","",YEAR(O189)) -> 2022 | W189: =IF(E189<25,"21-24",IF(E189<30,"25-29",IF(E189<35,"30-34",IF(E189<40,"35-39",IF(E189<45,"40-44","45+"))))) -> 25-29
... A658: E10657 | B658: Divya | C658: Reddy | D658: Male | E658: 38 | F658: Married | G658: Master's | H658: D01 | I658: Engineering | J658: QA Engineer | K658: L2 | L658: Coimbatore | M658: Onsite | N658: Full-time | O658: 43682 | P658: 977000 | Q658: 15 | R658: Yes | S658: Job Portal | T658: E10211 | U658: Exited | V658: =IF(O658="","",YEAR(O658)) -> 2019 | W658: =IF(E658<25,"21-24",IF(E658<30,"25-29",IF(E658<35,"30-34",IF(E658<40,"35-39",IF(E658<45,"40-44","45+"))))) -> 35-39
A659: E10658 | B659: Meena | C659: Krishnan | D659: Male | E659: 39 | F659: Married | G659: MBA | H659: D08 | I659: Marketing | J659: Digital Marketing Manager | K659: L4 | L659: Coimbatore | M659: Hybrid | N659: Full-time | O659: 44396 | P659: 4764000 | Q659: 13 | R659: No | S659: Referral | U659: Active | V659: =IF(O659="","",YEAR(O659)) -> 2021 | W659: =IF(E659<25,"21-24",IF(E659<30,"25-29",IF(E659<35,"30-34",IF(E659<40,"35-39",IF(E659<45,"40-44","45+"))))) -> 35-39
A660: E10659 | B660: Ravi | C660: Das | D660: Male | E660: 27 | F660: Married | G660: Diploma | H660: D05 | I660: Operations | J660: Operations Executive | K660: L1 | L660: Chennai | M660: Remote | N660: Contract | O660: 44923 | P660: 450000 | Q660: 1 | R660: Yes | S660: Job Portal | T660: E10483 | U660: Active | V660: =IF(O660="","",YEAR(O660)) -> 2022 | W660: =IF(E660<25,"21-24",IF(E660<30,"25-29",IF(E660<35,"30-34",IF(E660<40,"35-39",IF(E660<45,"40-44","45+"))))) -> 25-29
A661: E10660 | B661: Manoj | C661: Pillai | D661: Male | E661: 33 | F661: Single | G661: MBA | H661: D01 | I661: Engineering | J661: DevOps Engineer | K661: L2 | L661: Bengaluru | M661: Onsite | N661: Full-time | O661: 43827 | P661: 924000 | Q661: 7 | R661: No | S661: Campus | T661: E10730 | U661: Active | V661: =IF(O661="","",YEAR(O661)) -> 2019 | W661: =IF(E661<25,"21-24",IF(E661<30,"25-29",IF(E661<35,"30-34",IF(E661<40,"35-39",IF(E661<45,"40-44","45+"))))) -> 30-34
A662: E10661 | B662: Harish | C662: Iyer | D662: Female | E662: 26 | F662: Single | G662: Bachelor's | H662: D01 | I662: Engineering | J662: QA Engineer | K662: L2 | L662: Mumbai | M662: Remote | N662: Full-time | O662: 45604 | P662: 796000 | Q662: 8 | R662: No | S662: Job Portal | T662: E11273 | U662: Active | V662: =IF(O662="","",YEAR(O662)) -> 2024 | W662: =IF(E662<25,"21-24",IF(E662<30,"25-29",IF(E662<35,"30-34",IF(E662<40,"35-39",IF(E662<45,"40-44","45+"))))) -> 25-29
A663: E10662 | B663: Ajay | C663: Fernandes | D663: Male | E663: 35 | F663: Married | G663: Bachelor's | H663: D04 | I663: Customer Support | J663: Team Lead - Support | K663: L3 | L663: Bengaluru | M663: Onsite | N663: Full-time | O663: 42171 | P663: 2464000 | Q663: 14 | R663: No | S663: Job Portal | T663: E10732 | U663: Active | V663: =IF(O663="","",YEAR(O663)) -> 2015 | W663: =IF(E663<25,"21-24",IF(E663<30,"25-29",IF(E663<35,"30-34",IF(E663<40,"35-39",IF(E663<45,"40-44","45+"))))) -> 35-39
A664: E10663 | B664: Suresh | C664: Krishnan | D664: Male | E664: 30 | F664: Single | G664: Master's | H664: D01 | I664: Engineering | J664: Tech Lead | K664: L3 | L664: Bengaluru | M664: Hybrid | N664: Full-time | O664: 44309 | P664: 2149000 | Q664: 14 | R664: No | S664: Referral | T664: E11082 | U664: Active | V664: =IF(O664="","",YEAR(O664)) -> 2021 | W664: =IF(E664<25,"21-24",IF(E664<30,"25-29",IF(E664<35,"30-34",IF(E664<40,"35-39",IF(E664<45,"40-44","45+"))))) -> 30-34
A665: E10664 | B665: Siddharth | C665: Iyer | D665: Female | E665: 31 | F665: Single | G665: Master's | H665: D01 | I665: Engineering | J665: QA Engineer | K665: L2 | L665: Bengaluru | M665: Onsite | N665: Full-time | O665: 45541 | P665: 1104000 | Q665: 9 | R665: No | S665: Campus | T665: E10672 | U665: Active | V665: =IF(O665="","",YEAR(O665)) -> 2024 | W665: =IF(E665<25,"21-24",IF(E665<30,"25-29",IF(E665<35,"30-34",IF(E665<40,"35-39",IF(E665<45,"40-44","45+"))))) -> 30-34
A666: E10665 | B666: Ravi | C666: Subramanian | D666: Male | E666: 32 | F666: Single | G666: Bachelor's | H666: D02 | I666: Data & AI | J666: Analytics Manager | K666: L4 | L666: Bengaluru | M666: Hybrid | N666: Full-time | O666: 43680 | P666: 3854000 | Q666: 8 | R666: No | S666: LinkedIn | U666: Active | V666: =IF(O666="","",YEAR(O666)) -> 2019 | W666: =IF(E666<25,"21-24",IF(E666<30,"25-29",IF(E666<35,"30-34",IF(E666<40,"35-39",IF(E666<45,"40-44","45+"))))) -> 30-34
A667: E10666 | B667: Meena | C667: Patel | D667: Female | E667: 40 | F667: Married | G667: Bachelor's | H667: D05 | I667: Operations | J667: Operations Manager | K667: L4 | L667: Pune | M667: Onsite | N667: Full-time | O667: 45899 | P667: 4073000 | Q667: 14 | R667: No | S667: Job Portal | T667: E11210 | U667: Active | V667: =IF(O667="","",YEAR(O667)) -> 2025 | W667: =IF(E667<25,"21-24",IF(E667<30,"25-29",IF(E667<35,"30-34",IF(E667<40,"35-39",IF(E667<45,"40-44","45+"))))) -> 40-44
A668: E10667 | B668: Bhavya | C668: Verma | D668: Female | E668: 35 | F668: Single | G668: Diploma | H668: D08 | I668: Marketing | J668: Digital Marketing Manager | K668: L4 | L668: Bengaluru | M668: Hybrid | N668: Full-time | O668: 44027 | P668: 4528000 | Q668: 20 | R668: No | S668: Campus | T668: E10582 | U668: Active | V668: =IF(O668="","",YEAR(O668)) -> 2020 | W668: =IF(E668<25,"21-24",IF(E668<30,"25-29",IF(E668<35,"30-34",IF(E668<40,"35-39",IF(E668<45,"40-44","45+"))))) -> 35-39
A669: E10668 | B669: Pranav | C669: Sharma | D669: Female | E669: 25 | F669: Married | G669: Bachelor's | H669: D07 | I669: Human Resources | J669: Talent Acquisition Specialist | K669: L2 | L669: Bengaluru | M669: Hybrid | N669: Full-time | O669: 45310 | P669: 1132000 | Q669: 10 | R669: No | S669: Job Portal | T669: E10616 | U669: Exited | V669: =IF(O669="","",YEAR(O669)) -> 2024 | W669: =IF(E669<25,"21-24",IF(E669<30,"25-29",IF(E669<35,"30-34",IF(E669<40,"35-39",IF(E669<45,"40-44","45+"))))) -> 25-29
A670: E10669 | B670: Sneha | C670: Sharma | D670: Female | E670: 37 | F670: Single | G670: Master's | H670: D02 | I670: Data & AI | J670: Data Analyst | K670: L2 | L670: Chennai | M670: Remote | N670: Full-time | O670: 42081 | P670: 1288000 | Q670: 7 | R670: Yes | S670: Campus | T670: E10966 | U670: Active | V670: =IF(O670="","",YEAR(O670)) -> 2015 | W670: =IF(E670<25,"21-24",IF(E670<30,"25-29",IF(E670<35,"30-34",IF(E670<40,"35-39",IF(E670<45,"40-44","45+"))))) -> 35-39
A671: E10670 | B671: Pranav | C671: Rao | D671: Female | E671: 39 | F671: Married | G671: Bachelor's | H671: D06 | I671: Finance | J671: Finance Manager | K671: L4 | L671: Bengaluru | M671: Hybrid | N671: Full-time | O671: 44349 | P671: 4053000 | Q671: 6 | R671: No | S671: Job Portal | T671: E10622 | U671: Active | V671: =IF(O671="","",YEAR(O671)) -> 2021 | W671: =IF(E671<25,"21-24",IF(E671<30,"25-29",IF(E671<35,"30-34",IF(E671<40,"35-39",IF(E671<45,"40-44","45+"))))) -> 35-39
A672: E10671 | B672: Lakshmi | C672: Subramanian | D672: Male | E672: 28 | F672: Married | G672: Bachelor's | H672: D01 | I672: Engineering | J672: DevOps Engineer | K672: L2 | L672: Chennai | M672: Hybrid | N672: Full-time | O672: 43871 | P672: 1164000 | Q672: 10 | R672: No | S672: Job Portal | T672: E10470 | U672: Active | V672: =IF(O672="","",YEAR(O672)) -> 2020 | W672: =IF(E672<25,"21-24",IF(E672<30,"25-29",IF(E672<35,"30-34",IF(E672<40,"35-39",IF(E672<45,"40-44","45+"))))) -> 25-29
A673: E10672 | B673: Bhavya | C673: Kumar | D673: Female | E673: 37 | F673: Married | G673: Diploma | H673: D01 | I673: Engineering | J673: Engineering Manager | K673: L4 | L673: Coimbatore | M673: Onsite | N673: Intern | O673: 45487 | P673: 3808000 | Q673: 61 | R673: No | S673: Campus | T673: E10014 | U673: Active | V673: =IF(O673="","",YEAR(O673)) -> 2024 | W673: =IF(E673<25,"21-24",IF(E673<30,"25-29",IF(E673<35,"30-34",IF(E673<40,"35-39",IF(E673<45,"40-44","45+"))))) -> 35-39
A674: E10673 | B674: Siddharth | C674: Krishnan | D674: Male | E674: 36 | F674: Single | G674: MBA | H674: D01 | I674: Engineering | J674: Engineering Manager | K674: L4 | L674: Chennai | M674: Hybrid | N674: Full-time | O674: 45844 | P674: 2446000 | Q674: 2 | R674: No | S674: Consultant | T674: E10014 | U674: Exited | V674: =IF(O674="","",YEAR(O674)) -> 2025 | W674: =IF(E674<25,"21-24",IF(E674<30,"25-29",IF(E674<35,"30-34",IF(E674<40,"35-39",IF(E674<45,"40-44","45+"))))) -> 35-39
A675: E10674 | B675: Naveen | C675: Singh | D675: Male | E675: 29 | F675: Divorced | G675: MBA | H675: D04 | I675: Customer Support | J675: Team Lead - Support | K675: L3 | L675: Chennai | M675: Remote | N675: Contract | O675: 45537 | P675: 2172000 | Q675: 4 | R675: Yes | S675: Referral | T675: E11265 | U675: Active | V675: =IF(O675="","",YEAR(O675)) -> 2024 | W675: =IF(E675<25,"21-24",IF(E675<30,"25-29",IF(E675<35,"30-34",IF(E675<40,"35-39",IF(E675<45,"40-44","45+"))))) -> 25-29
A676: E10675 | B676: Fathima | C676: Krishnan | D676: Female | E676: 31 | F676: Married | G676: Bachelor's | H676: D01 | I676: Engineering | J676: DevOps Engineer | K676: L2 | L676: Bengaluru | M676: Hybrid | N676: Full-time | O676: 45497 | P676: 1153000 | Q676: 11 | R676: Yes | S676: Campus | T676: E11404 | U676: Active | V676: =IF(O676="","",YEAR(O676)) -> 2024 | W676: =IF(E676<25,"21-24",IF(E676<30,"25-29",IF(E676<35,"30-34",IF(E676<40,"35-39",IF(E676<45,"40-44","45+"))))) -> 30-34
A677: E10676 | B677: Rahul | C677: Sharma | D677: Female | E677: 39 | F677: Married | G677: Bachelor's | H677: D03 | I677: Sales | J677: Regional Sales Manager | K677: L4 | L677: Chennai | M677: Onsite | N677: Contract | O677: 42753 | P677: 2822000 | Q677: 10 | R677: No | S677: Referral | T677: E10486 | U677: Active | V677: =IF(O677="","",YEAR(O677)) -> 2017 | W677: =IF(E677<25,"21-24",IF(E677<30,"25-29",IF(E677<35,"30-34",IF(E677<40,"35-39",IF(E677<45,"40-44","45+"))))) -> 35-39
A678: E10677 | B678: Aditya | C678: Shetty | D678: Male | E678: 34 | F678: Married | G678: Master's | H678: D04 | I678: Customer Support | J678: Senior Support Associate | K678: L3 | L678: Pune | M678: Hybrid | N678: Contract | O678: 45905 | P678: 2379000 | Q678: 1 | R678: Yes | S678: Consultant | T678: E10538 | U678: Active | V678: =IF(O678="","",YEAR(O678)) -> 2025 | W678: =IF(E678<25,"21-24",IF(E678<30,"25-29",IF(E678<35,"30-34",IF(E678<40,"35-39",IF(E678<45,"40-44","45+"))))) -> 30-34
... A884: E10883 | B884: Divya | C884: Verma | D884: Male | E884: 28 | F884: Single | G884: Bachelor's | H884: D01 | I884: Engineering | J884: Tech Lead | K884: L3 | L884: Chennai | M884: Hybrid | N884: Full-time | O884: 44461 | P884: 2005000 | Q884: 6 | R884: No | S884: Referral | T884: E10211 | U884: Exited | V884: =IF(O884="","",YEAR(O884)) -> 2021 | W884: =IF(E884<25,"21-24",IF(E884<30,"25-29",IF(E884<35,"30-34",IF(E884<40,"35-39",IF(E884<45,"40-44","45+"))))) -> 25-29
A885: E10884 | B885: Keerthana | C885: Kumar | D885: Male | E885: 35 | F885: Married | G885: Master's | H885: D04 | I885: Customer Support | J885: Support Manager | K885: L4 | L885: Bengaluru | M885: Hybrid | N885: Full-time | O885: 42742 | P885: 3479000 | Q885: 11 | R885: Yes | S885: LinkedIn | U885: Active | V885: =IF(O885="","",YEAR(O885)) -> 2017 | W885: =IF(E885<25,"21-24",IF(E885<30,"25-29",IF(E885<35,"30-34",IF(E885<40,"35-39",IF(E885<45,"40-44","45+"))))) -> 35-39
A886: E10885 | B886: Siddharth | C886: Fernandes | D886: Female | E886: 28 | F886: Single | G886: Bachelor's | H886: D02 | I886: Data & AI | J886: Data Analyst | K886: L2 | L886: Coimbatore | M886: Onsite | N886: Full-time | O886: 46066 | P886: 1274000 | Q886: 2 | R886: Yes | S886: Campus | T886: E10458 | U886: Active | V886: =IF(O886="","",YEAR(O886)) -> 2026 | W886: =IF(E886<25,"21-24",IF(E886<30,"25-29",IF(E886<35,"30-34",IF(E886<40,"35-39",IF(E886<45,"40-44","45+"))))) -> 25-29
A887: E10886 | B887: Arun | C887: Kumar | D887: Male | E887: 30 | F887: Married | G887: Master's | H887: D05 | I887: Operations | J887: Process Analyst | K887: L2 | L887: Coimbatore | M887: Hybrid | N887: Full-time | O887: 44415 | P887: 1373000 | Q887: 8 | R887: No | S887: LinkedIn | T887: E10116 | U887: Active | V887: =IF(O887="","",YEAR(O887)) -> 2021 | W887: =IF(E887<25,"21-24",IF(E887<30,"25-29",IF(E887<35,"30-34",IF(E887<40,"35-39",IF(E887<45,"40-44","45+"))))) -> 30-34
A888: E10887 | B888: Pooja | C888: Fernandes | D888: Female | E888: 28 | F888: Married | G888: MBA | H888: D01 | I888: Engineering | J888: QA Engineer | K888: L2 | L888: Chennai | M888: Onsite | N888: Full-time | O888: 45615 | P888: 990000 | Q888: 4 | R888: Yes | S888: Referral | T888: E10153 | U888: Exited | V888: =IF(O888="","",YEAR(O888)) -> 2024 | W888: =IF(E888<25,"21-24",IF(E888<30,"25-29",IF(E888<35,"30-34",IF(E888<40,"35-39",IF(E888<45,"40-44","45+"))))) -> 25-29
A889: E10888 | B889: Priya | C889: Khan | D889: Male | E889: 25 | F889: Married | G889: Master's | H889: D07 | I889: Human Resources | J889: Talent Acquisition Specialist | K889: L2 | L889: Coimbatore | M889: Onsite | N889: Full-time | O889: 46199 | P889: 1163000 | Q889: 5 | R889: No | S889: Job Portal | T889: E10408 | U889: Active | V889: =IF(O889="","",YEAR(O889)) -> 2026 | W889: =IF(E889<25,"21-24",IF(E889<30,"25-29",IF(E889<35,"30-34",IF(E889<40,"35-39",IF(E889<45,"40-44","45+"))))) -> 25-29
A890: E10889 | B890: Kavya | C890: Reddy | D890: Male | E890: 30 | F890: Married | G890: Bachelor's | H890: D02 | I890: Data & AI | J890: Senior Data Scientist | K890: L3 | L890: Bengaluru | M890: Onsite | N890: Full-time | O890: 45606 | P890: 1881000 | Q890: 11 | R890: Yes | S890: Referral | T890: E10915 | U890: Active | V890: =IF(O890="","",YEAR(O890)) -> 2024 | W890: =IF(E890<25,"21-24",IF(E890<30,"25-29",IF(E890<35,"30-34",IF(E890<40,"35-39",IF(E890<45,"40-44","45+"))))) -> 30-34
A891: E10890 | B891: Anitha | C891: Nair | D891: Female | E891: 24 | F891: Single | G891: Bachelor's | H891: D04 | I891: Customer Support | J891: Support Associate | K891: L1 | L891: Hyderabad | M891: Hybrid | N891: Full-time | O891: 45764 | P891: 377000 | Q891: 4 | R891: No | S891: Job Portal | T891: E10704 | U891: Active | V891: =IF(O891="","",YEAR(O891)) -> 2025 | W891: =IF(E891<25,"21-24",IF(E891<30,"25-29",IF(E891<35,"30-34",IF(E891<40,"35-39",IF(E891<45,"40-44","45+"))))) -> 21-24
A892: E10891 | B892: Ajay | C892: Verma | D892: Male | E892: 22 | F892: Married | G892: Bachelor's | H892: D05 | I892: Operations | J892: Operations Executive | K892: L1 | L892: Bengaluru | M892: Hybrid | N892: Contract | O892: 46199 | P892: 320000 | Q892: 12 | R892: No | S892: Campus | T892: E11299 | U892: Active | V892: =IF(O892="","",YEAR(O892)) -> 2026 | W892: =IF(E892<25,"21-24",IF(E892<30,"25-29",IF(E892<35,"30-34",IF(E892<40,"35-39",IF(E892<45,"40-44","45+"))))) -> 21-24
A893: E10892 | B893: Sanjay | C893: Pillai | D893: Female | E893: 28 | F893: Single | G893: Bachelor's | H893: D01 | I893: Engineering | J893: QA Engineer | K893: L2 | L893: Chennai | M893: Onsite | N893: Intern | O893: 45408 | P893: 1197000 | Q893: 32 | R893: No | S893: Campus | T893: E10974 | U893: Active | V893: =IF(O893="","",YEAR(O893)) -> 2024 | W893: =IF(E893<25,"21-24",IF(E893<30,"25-29",IF(E893<35,"30-34",IF(E893<40,"35-39",IF(E893<45,"40-44","45+"))))) -> 25-29
A894: E10893 | B894: Fathima | C894: Iyer | D894: Female | E894: 25 | F894: Single | G894: Bachelor's | H894: D01 | I894: Engineering | J894: Tech Lead | K894: L3 | L894: Coimbatore | M894: Onsite | N894: Full-time | O894: 45691 | P894: 1907000 | Q894: 9 | R894: No | S894: Referral | T894: E11053 | U894: Active | V894: =IF(O894="","",YEAR(O894)) -> 2025 | W894: =IF(E894<25,"21-24",IF(E894<30,"25-29",IF(E894<35,"30-34",IF(E894<40,"35-39",IF(E894<45,"40-44","45+"))))) -> 25-29
A895: E10894 | B895: Fathima | C895: Gupta | D895: Female | E895: 40 | F895: Married | G895: Bachelor's | H895: D03 | I895: Sales | J895: Senior Account Manager | K895: L4 | L895: Bengaluru | M895: Hybrid | N895: Contract | O895: 42913 | P895: 3937000 | Q895: 11 | R895: No | S895: LinkedIn | T895: E11489 | U895: Active | V895: =IF(O895="","",YEAR(O895)) -> 2017 | W895: =IF(E895<25,"21-24",IF(E895<30,"25-29",IF(E895<35,"30-34",IF(E895<40,"35-39",IF(E895<45,"40-44","45+"))))) -> 40-44
A896: E10895 | B896: Deepa | C896: Singh | D896: Female | E896: 44 | F896: Married | G896: MBA | H896: D08 | I896: Marketing | J896: Digital Marketing Manager | K896: L4 | L896: Chennai | M896: Hybrid | N896: Full-time | O896: 45582 | P896: 2890000 | Q896: 25 | R896: No | S896: Referral | T896: E10998 | U896: Active | V896: =IF(O896="","",YEAR(O896)) -> 2024 | W896: =IF(E896<25,"21-24",IF(E896<30,"25-29",IF(E896<35,"30-34",IF(E896<40,"35-39",IF(E896<45,"40-44","45+"))))) -> 40-44
A897: E10896 | B897: Sneha | C897: Sharma | D897: Female | E897: 30 | F897: Married | G897: Master's | H897: D06 | I897: Finance | J897: Financial Analyst | K897: L2 | L897: Mumbai | M897: Hybrid | N897: Contract | O897: 44713 | P897: 820000 | Q897: 2 | R897: Yes | S897: Job Portal | T897: E11033 | U897: Active | V897: =IF(O897="","",YEAR(O897)) -> 2022 | W897: =IF(E897<25,"21-24",IF(E897<30,"25-29",IF(E897<35,"30-34",IF(E897<40,"35-39",IF(E897<45,"40-44","45+"))))) -> 30-34
... A1097: E11096 | B1097: Suresh | C1097: Joshi | D1097: Male | E1097: 38 | F1097: Single | G1097: Bachelor's | H1097: D04 | I1097: Customer Support | J1097: Team Lead - Support | K1097: L3 | L1097: Pune | M1097: Hybrid | N1097: Full-time | O1097: 42771 | P1097: 1663000 | Q1097: 21 | R1097: Yes | S1097: Consultant | T1097: E11493 | U1097: Active | V1097: =IF(O1097="","",YEAR(O1097)) -> 2017 | W1097: =IF(E1097<25,"21-24",IF(E1097<30,"25-29",IF(E1097<35,"30-34",IF(E1097<40,"35-39",IF(E1097<45,"40-44","45+"))))) -> 35-39
A1098: E11097 | B1098: John | C1098: Pillai | D1098: Male | E1098: 39 | F1098: Single | G1098: Master's | H1098: D02 | I1098: Data & AI | J1098: Analytics Manager | K1098: L4 | L1098: Hyderabad | M1098: Onsite | N1098: Full-time | O1098: 44181 | P1098: 4617000 | Q1098: 2 | R1098: No | S1098: Job Portal | U1098: Active | V1098: =IF(O1098="","",YEAR(O1098)) -> 2020 | W1098: =IF(E1098<25,"21-24",IF(E1098<30,"25-29",IF(E1098<35,"30-34",IF(E1098<40,"35-39",IF(E1098<45,"40-44","45+"))))) -> 35-39
A1099: E11098 | B1099: Naveen | C1099: Iyer | D1099: Male | E1099: 37 | F1099: Married | G1099: Diploma | H1099: D03 | I1099: Sales | J1099: Account Manager | K1099: L4 | L1099: Hyderabad | M1099: Onsite | N1099: Full-time | O1099: 43825 | P1099: 4263000 | Q1099: 5 | R1099: No | S1099: Campus | T1099: E10233 | U1099: Active | V1099: =IF(O1099="","",YEAR(O1099)) -> 2019 | W1099: =IF(E1099<25,"21-24",IF(E1099<30,"25-29",IF(E1099<35,"30-34",IF(E1099<40,"35-39",IF(E1099<45,"40-44","45+"))))) -> 35-39
A1100: E11099 | B1100: Ishita | C1100: Iyer | D1100: Female | E1100: 24 | F1100: Single | G1100: Bachelor's | H1100: D08 | I1100: Marketing | J1100: Marketing Executive | K1100: L1 | L1100: Coimbatore | M1100: Onsite | N1100: Full-time | O1100: 45698 | P1100: 380000 | Q1100: 9 | R1100: No | S1100: Referral | T1100: E10895 | U1100: Exited | V1100: =IF(O1100="","",YEAR(O1100)) -> 2025 | W1100: =IF(E1100<25,"21-24",IF(E1100<30,"25-29",IF(E1100<35,"30-34",IF(E1100<40,"35-39",IF(E1100<45,"40-44","45+"))))) -> 21-24
A1101: E11100 | B1101: Sanjay | C1101: Menon | D1101: Male | E1101: 30 | F1101: Married | G1101: Bachelor's | H1101: D04 | I1101: Customer Support | J1101: Support Associate | K1101: L1 | L1101: Coimbatore | M1101: Hybrid | N1101: Full-time | O1101: 43348 | P1101: 477000 | Q1101: 8 | R1101: Yes | S1101: Campus | T1101: E10190 | U1101: Active | V1101: =IF(O1101="","",YEAR(O1101)) -> 2018 | W1101: =IF(E1101<25,"21-24",IF(E1101<30,"25-29",IF(E1101<35,"30-34",IF(E1101<40,"35-39",IF(E1101<45,"40-44","45+"))))) -> 30-34
A1102: E11101 | B1102: Divya | C1102: Joshi | D1102: Female | E1102: 26 | F1102: Married | G1102: Master's | H1102: D09 | I1102: Legal & Compliance | J1102: Compliance Officer | K1102: L2 | L1102: Coimbatore | M1102: Onsite | N1102: Full-time | O1102: 44477 | P1102: 741000 | Q1102: 27 | R1102: No | S1102: Campus | T1102: E10371 | U1102: Exited | V1102: =IF(O1102="","",YEAR(O1102)) -> 2021 | W1102: =IF(E1102<25,"21-24",IF(E1102<30,"25-29",IF(E1102<35,"30-34",IF(E1102<40,"35-39",IF(E1102<45,"40-44","45+"))))) -> 25-29
A1103: E11102 | B1103: Harish | C1103: Khan | D1103: Male | E1103: 29 | F1103: Single | G1103: Master's | H1103: D01 | I1103: Engineering | J1103: QA Engineer | K1103: L2 | L1103: Bengaluru | M1103: Onsite | N1103: Full-time | O1103: 46011 | P1103: 1098000 | Q1103: 11 | R1103: No | S1103: Consultant | T1103: E10745 | U1103: Active | V1103: =IF(O1103="","",YEAR(O1103)) -> 2025 | W1103: =IF(E1103<25,"21-24",IF(E1103<30,"25-29",IF(E1103<35,"30-34",IF(E1103<40,"35-39",IF(E1103<45,"40-44","45+"))))) -> 25-29
A1104: E11103 | B1104: Mary | C1104: Joshi | D1104: Male | E1104: 43 | F1104: Single | G1104: Bachelor's | H1104: D01 | I1104: Engineering | J1104: Engineering Manager | K1104: L4 | L1104: Hyderabad | M1104: Onsite | N1104: Full-time | O1104: 42892 | P1104: 2656000 | Q1104: 6 | R1104: No | S1104: Referral | T1104: E10859 | U1104: Active | V1104: =IF(O1104="","",YEAR(O1104)) -> 2017 | W1104: =IF(E1104<25,"21-24",IF(E1104<30,"25-29",IF(E1104<35,"30-34",IF(E1104<40,"35-39",IF(E1104<45,"40-44","45+"))))) -> 40-44
A1105: E11104 | B1105: Siddharth | C1105: Fernandes | D1105: Female | E1105: 32 | F1105: Single | G1105: Bachelor's | H1105: D04 | I1105: Customer Support | J1105: Support Associate | K1105: L1 | L1105: Bengaluru | M1105: Hybrid | N1105: Full-time | O1105: 43285 | P1105: 476000 | Q1105: 0 | R1105: Yes | S1105: Consultant | T1105: E10209 | U1105: Exited | V1105: =IF(O1105="","",YEAR(O1105)) -> 2018 | W1105: =IF(E1105<25,"21-24",IF(E1105<30,"25-29",IF(E1105<35,"30-34",IF(E1105<40,"35-39",IF(E1105<45,"40-44","45+"))))) -> 30-34
A1106: E11105 | B1106: Meena | C1106: Rao | D1106: Female | E1106: 30 | F1106: Married | G1106: Master's | H1106: D01 | I1106: Engineering | J1106: QA Engineer | K1106: L2 | L1106: Chennai | M1106: Onsite | N1106: Full-time | O1106: 44273 | P1106: 1335000 | Q1106: 10 | R1106: Yes | S1106: LinkedIn | T1106: E10300 | U1106: Active | V1106: =IF(O1106="","",YEAR(O1106)) -> 2021 | W1106: =IF(E1106<25,"21-24",IF(E1106<30,"25-29",IF(E1106<35,"30-34",IF(E1106<40,"35-39",IF(E1106<45,"40-44","45+"))))) -> 30-34
A1107: E11106 | B1107: Nisha | C1107: Iyer | D1107: Female | E1107: 26 | F1107: Married | G1107: Diploma | H1107: D03 | I1107: Sales | J1107: Sales Executive | K1107: L1 | L1107: Coimbatore | M1107: Hybrid | N1107: Full-time | O1107: 44486 | P1107: 312000 | Q1107: 19 | R1107: Yes | S1107: Job Portal | T1107: E10452 | U1107: Active | V1107: =IF(O1107="","",YEAR(O1107)) -> 2021 | W1107: =IF(E1107<25,"21-24",IF(E1107<30,"25-29",IF(E1107<35,"30-34",IF(E1107<40,"35-39",IF(E1107<45,"40-44","45+"))))) -> 25-29
A1108: E11107 | B1108: Lakshmi | C1108: Nair | D1108: Male | E1108: 28 | F1108: Married | G1108: Master's | H1108: D01 | I1108: Engineering | J1108: QA Engineer | K1108: L2 | L1108: Coimbatore | M1108: Onsite | N1108: Full-time | O1108: 44920 | P1108: 602000 | Q1108: 1 | R1108: Yes | S1108: Referral | T1108: E11200 | U1108: Active | V1108: =IF(O1108="","",YEAR(O1108)) -> 2022 | W1108: =IF(E1108<25,"21-24",IF(E1108<30,"25-29",IF(E1108<35,"30-34",IF(E1108<40,"35-39",IF(E1108<45,"40-44","45+"))))) -> 25-29
A1109: E11108 | B1109: Vikram | C1109: Joshi | D1109: Male | E1109: 41 | F1109: Married | G1109: Bachelor's | H1109: D05 | I1109: Operations | J1109: Operations Manager | K1109: L4 | L1109: Bengaluru | M1109: Onsite | N1109: Full-time | O1109: 43843 | P1109: 3418000 | Q1109: 11 | R1109: No | S1109: LinkedIn | T1109: E10924 | U1109: Exited | V1109: =IF(O1109="","",YEAR(O1109)) -> 2020 | W1109: =IF(E1109<25,"21-24",IF(E1109<30,"25-29",IF(E1109<35,"30-34",IF(E1109<40,"35-39",IF(E1109<45,"40-44","45+"))))) -> 40-44
A1110: E11109 | B1110: Rahul | C1110: Krishnan | D1110: Female | E1110: 44 | F1110: Single | G1110: Bachelor's | H1110: D09 | I1110: Legal & Compliance | J1110: Compliance Manager | K1110: L4 | L1110: Bengaluru | M1110: Onsite | N1110: Full-time | O1110: 45358 | P1110: 3132000 | Q1110: 25 | R1110: No | S1110: Job Portal | T1110: E11309 | U1110: Active | V1110: =IF(O1110="","",YEAR(O1110)) -> 2024 | W1110: =IF(E1110<25,"21-24",IF(E1110<30,"25-29",IF(E1110<35,"30-34",IF(E1110<40,"35-39",IF(E1110<45,"40-44","45+"))))) -> 40-44
... A1152: E11151 | B1152: Anitha | C1152: Singh | D1152: Female | E1152: 23 | F1152: Married | G1152: Bachelor's | H1152: D09 | I1152: Legal & Compliance | J1152: Compliance Officer | K1152: L2 | L1152: Coimbatore | M1152: Hybrid | N1152: Full-time | O1152: 45821 | P1152: 600000 | Q1152: 11 | R1152: No | S1152: Campus | T1152: E11039 | U1152: Active | V1152: =IF(O1152="","",YEAR(O1152)) -> 2025 | W1152: =IF(E1152<25,"21-24",IF(E1152<30,"25-29",IF(E1152<35,"30-34",IF(E1152<40,"35-39",IF(E1152<45,"40-44","45+"))))) -> 21-24
A1153: E11152 | B1153: Keerthana | C1153: Sharma | D1153: Male | E1153: 39 | F1153: Single | G1153: PhD | H1153: D01 | I1153: Engineering | J1153: Engineering Manager | K1153: L4 | L1153: Hyderabad | M1153: Onsite | N1153: Contract | O1153: 44027 | P1153: 4377000 | Q1153: 8 | R1153: Yes | S1153: Job Portal | U1153: Exited | V1153: =IF(O1153="","",YEAR(O1153)) -> 2020 | W1153: =IF(E1153<25,"21-24",IF(E1153<30,"25-29",IF(E1153<35,"30-34",IF(E1153<40,"35-39",IF(E1153<45,"40-44","45+"))))) -> 35-39
A1154: E11153 | B1154: Pooja | C1154: Iyer | D1154: Male | E1154: 37 | F1154: Divorced | G1154: Bachelor's | H1154: D09 | I1154: Legal & Compliance | J1154: Compliance Officer | K1154: L2 | L1154: Hyderabad | M1154: Remote | N1154: Full-time | O1154: 42612 | P1154: 996000 | Q1154: 11 | R1154: No | S1154: Referral | T1154: E11424 | U1154: Active | V1154: =IF(O1154="","",YEAR(O1154)) -> 2016 | W1154: =IF(E1154<25,"21-24",IF(E1154<30,"25-29",IF(E1154<35,"30-34",IF(E1154<40,"35-39",IF(E1154<45,"40-44","45+"))))) -> 35-39
A1155: E11154 | B1155: Manoj | C1155: Khan | D1155: Male | E1155: 33 | F1155: Single | G1155: Bachelor's | H1155: D02 | I1155: Data & AI | J1155: Data Analyst | K1155: L2 | L1155: Coimbatore | M1155: Hybrid | N1155: Full-time | O1155: 45512 | P1155: 1161000 | Q1155: 23 | R1155: Yes | S1155: LinkedIn | T1155: E10050 | U1155: Exited | V1155: =IF(O1155="","",YEAR(O1155)) -> 2024 | W1155: =IF(E1155<25,"21-24",IF(E1155<30,"25-29",IF(E1155<35,"30-34",IF(E1155<40,"35-39",IF(E1155<45,"40-44","45+"))))) -> 30-34
A1156: E11155 | B1156: Revathi | C1156: Gupta | D1156: Female | E1156: 27 | F1156: Single | G1156: Master's | H1156: D09 | I1156: Legal & Compliance | J1156: Legal Associate | K1156: L2 | L1156: Mumbai | M1156: Remote | N1156: Intern | O1156: 44213 | P1156: 824000 | Q1156: 11 | R1156: Yes | S1156: Referral | T1156: E11109 | U1156: Active | V1156: =IF(O1156="","",YEAR(O1156)) -> 2021 | W1156: =IF(E1156<25,"21-24",IF(E1156<30,"25-29",IF(E1156<35,"30-34",IF(E1156<40,"35-39",IF(E1156<45,"40-44","45+"))))) -> 25-29
A1157: E11156 | B1157: Sneha | C1157: Subramanian | D1157: Female | E1157: 24 | F1157: Married | G1157: Bachelor's | H1157: D01 | I1157: Engineering | J1157: DevOps Engineer | K1157: L2 | L1157: Chennai | M1157: Hybrid | N1157: Full-time | O1157: 45537 | P1157: 640000 | Q1157: 3 | R1157: Yes | S1157: Job Portal | T1157: E10103 | U1157: Active | V1157: =IF(O1157="","",YEAR(O1157)) -> 2024 | W1157: =IF(E1157<25,"21-24",IF(E1157<30,"25-29",IF(E1157<35,"30-34",IF(E1157<40,"35-39",IF(E1157<45,"40-44","45+"))))) -> 21-24
A1158: E11157 | B1158: Rohit | C1158: Nair | D1158: Male | E1158: 31 | F1158: Single | G1158: Bachelor's | H1158: D02 | I1158: Data & AI | J1158: Data Analyst | K1158: L2 | L1158: Pune | M1158: Onsite | N1158: Full-time | O1158: 45289 | P1158: 1119000 | Q1158: 21 | R1158: No | S1158: Job Portal | T1158: E10050 | U1158: Active | V1158: =IF(O1158="","",YEAR(O1158)) -> 2023 | W1158: =IF(E1158<25,"21-24",IF(E1158<30,"25-29",IF(E1158<35,"30-34",IF(E1158<40,"35-39",IF(E1158<45,"40-44","45+"))))) -> 30-34
A1159: E11158 | B1159: Rahul | C1159: Subramanian | D1159: Female | E1159: 39 | F1159: Divorced | G1159: Master's | H1159: D07 | I1159: Human Resources | J1159: HR Manager | K1159: L4 | L1159: Mumbai | M1159: Remote | N1159: Contract | O1159: 44004 | P1159: 3525000 | Q1159: 8 | R1159: No | S1159: LinkedIn | T1159: E10245 | U1159: Active | V1159: =IF(O1159="","",YEAR(O1159)) -> 2020 | W1159: =IF(E1159<25,"21-24",IF(E1159<30,"25-29",IF(E1159<35,"30-34",IF(E1159<40,"35-39",IF(E1159<45,"40-44","45+"))))) -> 35-39
A1160: E11159 | B1160: Mary | C1160: Nair | D1160: Male | E1160: 21 | F1160: Married | G1160: Master's | H1160: D04 | I1160: Customer Support | J1160: Support Associate | K1160: L1 | L1160: Coimbatore | M1160: Onsite | N1160: Full-time | O1160: 46247 | P1160: 335000 | Q1160: 32 | R1160: No | S1160: LinkedIn | T1160: E10580 | U1160: Active | V1160: =IF(O1160="","",YEAR(O1160)) -> 2026 | W1160: =IF(E1160<25,"21-24",IF(E1160<30,"25-29",IF(E1160<35,"30-34",IF(E1160<40,"35-39",IF(E1160<45,"40-44","45+"))))) -> 21-24
A1161: E11160 | B1161: Harish | C1161: Rao | D1161: Male | E1161: 34 | F1161: Married | G1161: Master's | H1161: D02 | I1161: Data & AI | J1161: Data Scientist | K1161: L2 | L1161: Chennai | M1161: Onsite | N1161: Full-time | O1161: 42386 | P1161: 1001000 | Q1161: 7 | R1161: No | S1161: Consultant | T1161: E10583 | U1161: Active | V1161: =IF(O1161="","",YEAR(O1161)) -> 2016 | W1161: =IF(E1161<25,"21-24",IF(E1161<30,"25-29",IF(E1161<35,"30-34",IF(E1161<40,"35-39",IF(E1161<45,"40-44","45+"))))) -> 30-34
A1162: E11161 | B1162: Fathima | C1162: Das | D1162: Female | E1162: 30 | F1162: Married | G1162: Bachelor's | H1162: D02 | I1162: Data & AI | J1162: ML Engineer | K1162: L2 | L1162: Mumbai | M1162: Onsite | N1162: Full-time | O1162: 44661 | P1162: 821000 | Q1162: 8 | R1162: No | S1162: LinkedIn | T1162: E10964 | U1162: Active | V1162: =IF(O1162="","",YEAR(O1162)) -> 2022 | W1162: =IF(E1162<25,"21-24",IF(E1162<30,"25-29",IF(E1162<35,"30-34",IF(E1162<40,"35-39",IF(E1162<45,"40-44","45+"))))) -> 30-34
A1163: E11162 | B1163: Aditya | C1163: Rao | D1163: Male | E1163: 37 | F1163: Single | G1163: Bachelor's | H1163: D03 | I1163: Sales | J1163: Senior Account Manager | K1163: L4 | L1163: Chennai | M1163: Hybrid | N1163: Contract | O1163: 46103 | P1163: 3405000 | Q1163: 13 | R1163: No | S1163: Referral | T1163: E10071 | U1163: Active | V1163: =IF(O1163="","",YEAR(O1163)) -> 2026 | W1163: =IF(E1163<25,"21-24",IF(E1163<30,"25-29",IF(E1163<35,"30-34",IF(E1163<40,"35-39",IF(E1163<45,"40-44","45+"))))) -> 35-39
A1164: E11163 | B1164: Rahul | C1164: Menon | D1164: Male | E1164: 27 | F1164: Married | G1164: Bachelor's | H1164: D02 | I1164: Data & AI | J1164: Data Scientist | K1164: L2 | L1164: Chennai | M1164: Onsite | N1164: Full-time | O1164: 45510 | P1164: 1399000 | Q1164: 0 | R1164: No | S1164: LinkedIn | T1164: E10316 | U1164: Exited | V1164: =IF(O1164="","",YEAR(O1164)) -> 2024 | W1164: =IF(E1164<25,"21-24",IF(E1164<30,"25-29",IF(E1164<35,"30-34",IF(E1164<40,"35-39",IF(E1164<45,"40-44","45+"))))) -> 25-29
A1165: E11164 | B1165: Ishita | C1165: Reddy | D1165: Male | E1165: 21 | F1165: Single | G1165: Bachelor's | H1165: D08 | I1165: Marketing | J1165: Marketing Executive | K1165: L1 | L1165: Chennai | M1165: Hybrid | N1165: Contract | O1165: 46236 | P1165: 318000 | Q1165: 7 | R1165: No | S1165: Job Portal | T1165: E11143 | U1165: Exited | V1165: =IF(O1165="","",YEAR(O1165)) -> 2026 | W1165: =IF(E1165<25,"21-24",IF(E1165<30,"25-29",IF(E1165<35,"30-34",IF(E1165<40,"35-39",IF(E1165<45,"40-44","45+"))))) -> 21-24
... A1501: E11500 | B1501: Rohit | C1501: Fernandes | D1501: Male | E1501: 29 | F1501: Married | G1501: Bachelor's | H1501: D07 | I1501: Human Resources | J1501: HR Business Partner | K1501: L2 | L1501: Chennai | M1501: Hybrid | N1501: Full-time | O1501: 44780 | P1501: 943000 | Q1501: 7 | R1501: No | S1501: Referral | T1501: E10598 | U1501: Active | V1501: =IF(O1501="","",YEAR(O1501)) -> 2022 | W1501: =IF(E1501<25,"21-24",IF(E1501<30,"25-29",IF(E1501<35,"30-34",IF(E1501<40,"35-39",IF(E1501<45,"40-44","45+"))))) -> 25-29

Sheet Attrition
A1: employee_id | B1: resignation_date | C1: exit_date | D1: exit_type | E1: primary_reason | F1: notice_period_days | G1: notice_served_days | H1: tenure_months | I1: regrettable_loss | J1: rehire_eligible | K1: counter_offer_made | L1: exit_interview_done | M1: fnf_settlement_days | N1: new_employer_type | O1: exit_year | P1: department | Q1: tenure_band
A2: E10007 | C2: 46044 | D2: Involuntary | E2: Misconduct / Policy Violation | F2: 60 | G2: 0 | H2: 37.5 | I2: No | J2: No | K2: No | L2: No | M2: 21 | O2: =IF(C2="","",YEAR(C2)) -> 2026 | P2: =IFERROR(VLOOKUP(A2,Employees!$A$2:$I$1501,9,FALSE()),"Unknown") -> Data & AI | Q2: =IF(H2<12,"<1 yr",IF(H2<36,"1-3 yrs",IF(H2<60,"3-5 yrs","5+ yrs"))) -> 3-5 yrs
A3: E10008 | C3: 45646 | D3: Involuntary | E3: Restructuring / Layoff | F3: 60 | G3: 0 | H3: 22.1 | I3: No | J3: Yes | K3: No | L3: No | M3: 3 | O3: =IF(C3="","",YEAR(C3)) -> 2024 | P3: =IFERROR(VLOOKUP(A3,Employees!$A$2:$I$1501,9,FALSE()),"Unknown") -> Engineering | Q3: =IF(H3<12,"<1 yr",IF(H3<36,"1-3 yrs",IF(H3<60,"3-5 yrs","5+ yrs"))) -> 1-3 yrs
A4: E10011 | B4: 45476 | C4: 45536 | D4: Voluntary | E4: Work-Life Balance | F4: 60 | G4: 18 | H4: 104.2 | I4: No | J4: Yes | K4: Yes | L4: Yes | M4: 28 | N4: MNC | O4: =IF(C4="","",YEAR(C4)) -> 2024 | P4: =IFERROR(VLOOKUP(A4,Employees!$A$2:$I$1501,9,FALSE()),"Unknown") -> Engineering | Q4: =IF(H4<12,"<1 yr",IF(H4<36,"1-3 yrs",IF(H4<60,"3-5 yrs","5+ yrs"))) -> 5+ yrs
A5: E10017 | B5: 46253 | C5: 46283 | D5: Voluntary | E5: Higher Studies | F5: 30 | G5: 0 | H5: 1.4 | I5: Yes | J5: No | K5: No | L5: Yes | M5: 36 | N5: MNC | O5: =IF(C5="","",YEAR(C5)) -> 2026 | P5: =IFERROR(VLOOKUP(A5,Employees!$A$2:$I$1501,9,FALSE()),"Unknown") -> Customer Support | Q5: =IF(H5<12,"<1 yr",IF(H5<36,"1-3 yrs",IF(H5<60,"3-5 yrs","5+ yrs"))) -> <1 yr
A6: E10018 | B6: 44298 | C6: 44388 | D6: Voluntary | E6: Better Compensation | F6: 90 | G6: 90 | H6: 31.5 | I6: Yes | J6: Yes | K6: No | L6: Yes | M6: 61 | N6: Not Disclosed | O6: =IF(C6="","",YEAR(C6)) -> 2021 | P6: =IFERROR(VLOOKUP(A6,Employees!$A$2:$I$1501,9,FALSE()),"Unknown") -> Sales | Q6: =IF(H6<12,"<1 yr",IF(H6<36,"1-3 yrs",IF(H6<60,"3-5 yrs","5+ yrs"))) -> 1-3 yrs
A7: E10025 | B7: 46197 | C7: 46257 | D7: Voluntary | E7: Manager Issues | F7: 60 | G7: 30 | H7: 3.1 | I7: No | J7: No | K7: No | L7: No | M7: 22 | N7: Competitor | O7: =IF(C7="","",YEAR(C7)) -> 2026 | P7: =IFERROR(VLOOKUP(A7,Employees!$A$2:$I$1501,9,FALSE()),"Unknown") -> Engineering | Q7: =IF(H7<12,"<1 yr",IF(H7<36,"1-3 yrs",IF(H7<60,"3-5 yrs","5+ yrs"))) -> <1 yr
A8: E10036 | B8: 45698 | C8: 45758 | D8: Voluntary | E8: Work-Life Balance | F8: 60 | G8: 60 | H8: 43.3 | I8: No | J8: Yes | K8: No | L8: Yes | M8: 50 | N8: Competitor | O8: =IF(C8="","",YEAR(C8)) -> 2025 | P8: =IFERROR(VLOOKUP(A8,Employees!$A$2:$I$1501,9,FALSE()),"Unknown") -> Human Resources | Q8: =IF(H8<12,"<1 yr",IF(H8<36,"1-3 yrs",IF(H8<60,"3-5 yrs","5+ yrs"))) -> 3-5 yrs
A9: E10038 | B9: 45277 | C9: 45337 | D9: Voluntary | E9: Better Compensation | F9: 60 | G9: 60 | H9: 15 | I9: No | J9: No | K9: No | L9: Yes | M9: 92 | N9: Not Disclosed | O9: =IF(C9="","",YEAR(C9)) -> 2024 | P9: =IFERROR(VLOOKUP(A9,Employees!$A$2:$I$1501,9,FALSE()),"Unknown") -> Operations | Q9: =IF(H9<12,"<1 yr",IF(H9<36,"1-3 yrs",IF(H9<60,"3-5 yrs","5+ yrs"))) -> 1-3 yrs
A10: E10040 | C10: 45885 | D10: Involuntary | E10: Performance | F10: 90 | G10: 0 | H10: 22.3 | I10: No | J10: Yes | K10: No | L10: No | M10: 51 | O10: =IF(C10="","",YEAR(C10)) -> 2025 | P10: =IFERROR(VLOOKUP(A10,Employees!$A$2:$I$1501,9,FALSE()),"Unknown") -> Sales | Q10: =IF(H10<12,"<1 yr",IF(H10<36,"1-3 yrs",IF(H10<60,"3-5 yrs","5+ yrs"))) -> 1-3 yrs
A11: E10043 | B11: 45107 | C11: 45197 | D11: Voluntary | E11: Career Growth | F11: 90 | G11: 0 | H11: 68 | I11: Yes | J11: Yes | K11: Yes | L11: Yes | M11: 7 | N11: MNC | O11: =IF(C11="","",YEAR(C11)) -> 2023 | P11: =IFERROR(VLOOKUP(A11,Employees!$A$2:$I$1501,9,FALSE()),"Unknown") -> Operations | Q11: =IF(H11<12,"<1 yr",IF(H11<36,"1-3 yrs",IF(H11<60,"3-5 yrs","5+ yrs"))) -> 5+ yrs
A12: E10045 | C12: 45047 | D12: Involuntary | E12: Performance | F12: 90 | G12: 0 | H12: 13.3 | I12: No | J12: Yes | K12: No | L12: No | M12: 6 | O12: =IF(C12="","",YEAR(C12)) -> 2023 | P12: =IFERROR(VLOOKUP(A12,Employees!$A$2:$I$1501,9,FALSE()),"Unknown") -> Finance | Q12: =IF(H12<12,"<1 yr",IF(H12<36,"1-3 yrs",IF(H12<60,"3-5 yrs","5+ yrs"))) -> 1-3 yrs
A13: E10056 | B13: 45849 | C13: 45909 | D13: Voluntary | E13: Job Role Mismatch | F13: 60 | G13: 0 | H13: 3.3 | I13: Yes | J13: Yes | K13: Yes | L13: Yes | M13: 25 | N13: MNC | O13: =IF(C13="","",YEAR(C13)) -> 2025 | P13: =IFERROR(VLOOKUP(A13,Employees!$A$2:$I$1501,9,FALSE()),"Unknown") -> Data & AI | Q13: =IF(H13<12,"<1 yr",IF(H13<36,"1-3 yrs",IF(H13<60,"3-5 yrs","5+ yrs"))) -> <1 yr
A14: E10058 | B14: 46163 | C14: 46193 | D14: Voluntary | E14: Health / Personal | F14: 30 | G14: 15 | H14: 39.8 | I14: Yes | J14: Yes | K14: No | L14: Yes | M14: 16 | N14: MNC | O14: =IF(C14="","",YEAR(C14)) -> 2026 | P14: =IFERROR(VLOOKUP(A14,Employees!$A$2:$I$1501,9,FALSE()),"Unknown") -> Customer Support | Q14: =IF(H14<12,"<1 yr",IF(H14<36,"1-3 yrs",IF(H14<60,"3-5 yrs","5+ yrs"))) -> 3-5 yrs
A15: E10062 | B15: 46157 | C15: 46217 | D15: Voluntary | E15: Better Compensation | F15: 60 | G15: 60 | H15: 1.7 | I15: Yes | J15: No | K15: No | L15: Yes | M15: 53 | N15: MNC | O15: =IF(C15="","",YEAR(C15)) -> 2026 | P15: =IFERROR(VLOOKUP(A15,Employees!$A$2:$I$1501,9,FALSE()),"Unknown") -> Engineering | Q15: =IF(H15<12,"<1 yr",IF(H15<36,"1-3 yrs",IF(H15<60,"3-5 yrs","5+ yrs"))) -> <1 yr
A16: E10063 | B16: 45139 | C16: 45229 | D16: Voluntary | E16: Higher Studies | F16: 90 | G16: 90 | H16: 19.9 | I16: No | J16: Yes | K16: No | L16: Yes | M16: 32 | N16: Not Working | O16: =IF(C16="","",YEAR(C16)) -> 2023 | P16: =IFERROR(VLOOKUP(A16,Employees!$A$2:$I$1501,9,FALSE()),"Unknown") -> Sales | Q16: =IF(H16<12,"<1 yr",IF(H16<36,"1-3 yrs",IF(H16<60,"3-5 yrs","5+ yrs"))) -> 1-3 yrs
A17: E10071 | B17: 46192 | C17: 46282 | D17: Voluntary | E17: Work-Life Balance | F17: 90 | G17: 90 | H17: 0.9 | I17: Yes | J17: Yes | K17: Yes | L17: Yes | M17: 6 | N17: Not Disclosed | O17: =IF(C17="","",YEAR(C17)) -> 2026 | P17: =IFERROR(VLOOKUP(A17,Employees!$A$2:$I$1501,9,FALSE()),"Unknown") -> Sales | Q17: =IF(H17<12,"<1 yr",IF(H17<36,"1-3 yrs",IF(H17<60,"3-5 yrs","5+ yrs"))) -> <1 yr
A18: E10074 | B18: 45835 | C18: 45925 | D18: Voluntary | E18: Career Growth | F18: 90 | G18: 45 | H18: 6.8 | I18: No | J18: Yes | K18: No | L18: No | M18: 75 | N18: Startup | O18: =IF(C18="","",YEAR(C18)) -> 2025 | P18: =IFERROR(VLOOKUP(A18,Employees!$A$2:$I$1501,9,FALSE()),"Unknown") -> Sales | Q18: =IF(H18<12,"<1 yr",IF(H18<36,"1-3 yrs",IF(H18<60,"3-5 yrs","5+ yrs"))) -> <1 yr
A19: E10075 | B19: 45734 | C19: 45824 | D19: Voluntary | E19: Job Role Mismatch | F19: 90 | G19: 90 | H19: 5.3 | I19: Yes | J19: Yes | K19: No | L19: Yes | M19: 67 | N19: Not Disclosed | O19: =IF(C19="","",YEAR(C19)) -> 2025 | P19: =IFERROR(VLOOKUP(A19,Employees!$A$2:$I$1501,9,FALSE()),"Unknown") -> Engineering | Q19: =IF(H19<12,"<1 yr",IF(H19<36,"1-3 yrs",IF(H19<60,"3-5 yrs","5+ yrs"))) -> <1 yr
A20: E10082 | B20: 45257 | C20: 45287 | D20: Voluntary | E20: Health / Personal | F20: 30 | G20: 30 | H20: 9.2 | I20: Yes | J20: Yes | K20: No | L20: Yes | M20: 25 | N20: Not Working | O20: =IF(C20="","",YEAR(C20)) -> 2023 | P20: =IFERROR(VLOOKUP(A20,Employees!$A$2:$I$1501,9,FALSE()),"Unknown") -> Marketing | Q20: =IF(H20<12,"<1 yr",IF(H20<36,"1-3 yrs",IF(H20<60,"3-5 yrs","5+ yrs"))) -> <1 yr
A21: E10087 | B21: 46160 | C21: 46220 | D21: Voluntary | E21: Better Compensation | F21: 60 | G21: 0 | H21: 28.9 | I21: No | J21: Yes | K21: No | L21: Yes | M21: 21 | N21: MNC | O21: =IF(C21="","",YEAR(C21)) -> 2026 | P21: =IFERROR(VLOOKUP(A21,Employees!$A$2:$I$1501,9,FALSE()),"Unknown") -> Engineering | Q21: =IF(H21<12,"<1 yr",IF(H21<36,"1-3 yrs",IF(H21<60,"3-5 yrs","5+ yrs"))) -> 1-3 yrs
A22: E10090 | B22: 44927 | C22: 44957 | D22: Voluntary | E22: Work-Life Balance | F22: 30 | G22: 30 | H22: 24.4 | I22: No | J22: Yes | K22: No | L22: Yes | M22: 33 | N22: Competitor | O22: =IF(C22="","",YEAR(C22)) -> 2023 | P22: =IFERROR(VLOOKUP(A22,Employees!$A$2:$I$1501,9,FALSE()),"Unknown") -> Sales | Q22: =IF(H22<12,"<1 yr",IF(H22<36,"1-3 yrs",IF(H22<60,"3-5 yrs","5+ yrs"))) -> 1-3 yrs
A23: E10092 | C23: 44234 | D23: Involuntary | E23: Performance | F23: 90 | G23: 0 | H23: 27.4 | I23: No | J23: Yes | K23: No | L23: No | M23: 38 | O23: =IF(C23="","",YEAR(C23)) -> 2021 | P23: =IFERROR(VLOOKUP(A23,Employees!$A$2:$I$1501,9,FALSE()),"Unknown") -> Customer Support | Q23: =IF(H23<12,"<1 yr",IF(H23<36,"1-3 yrs",IF(H23<60,"3-5 yrs","5+ yrs"))) -> 1-3 yrs
A24: E10102 | B24: 46238 | C24: 46268 | D24: Voluntary | E24: Relocation | F24: 30 | G24: 30 | H24: 6.8 | I24: No | J24: Yes | K24: No | L24: Yes | M24: 25 | N24: Not Disclosed | O24: =IF(C24="","",YEAR(C24)) -> 2026 | P24: =IFERROR(VLOOKUP(A24,Employees!$A$2:$I$1501,9,FALSE()),"Unknown") -> Sales | Q24: =IF(H24<12,"<1 yr",IF(H24<36,"1-3 yrs",IF(H24<60,"3-5 yrs","5+ yrs"))) -> <1 yr
A25: E10104 | B25: 45319 | C25: 45409 | D25: Voluntary | E25: Career Growth | F25: 90 | G25: 27 | H25: 26 | I25: Yes | J25: Yes | K25: No | L25: Yes | M25: 18 | N25: MNC | O25: =IF(C25="","",YEAR(C25)) -> 2024 | P25: =IFERROR(VLOOKUP(A25,Employees!$A$2:$I$1501,9,FALSE()),"Unknown") -> Sales | Q25: =IF(H25<12,"<1 yr",IF(H25<36,"1-3 yrs",IF(H25<60,"3-5 yrs","5+ yrs"))) -> 1-3 yrs
A26: E10117 | C26: 46272 | D26: Involuntary | E26: Performance | F26: 90 | G26: 0 | H26: 14.2 | I26: No | J26: Yes | K26: No | L26: No | M26: 19 | O26: =IF(C26="","",YEAR(C26)) -> 2026 | P26: =IFERROR(VLOOKUP(A26,Employees!$A$2:$I$1501,9,FALSE()),"Unknown") -> Operations | Q26: =IF(H26<12,"<1 yr",IF(H26<36,"1-3 yrs",IF(H26<60,"3-5 yrs","5+ yrs"))) -> 1-3 yrs
A27: E10118 | B27: 45698 | C27: 45758 | D27: Voluntary | E27: Higher Studies | F27: 60 | G27: 60 | H27: 31.2 | I27: No | J27: No | K27: No | L27: Yes | M27: 55 | N27: Not Working | O27: =IF(C27="","",YEAR(C27)) -> 2025 | P27: =IFERROR(VLOOKUP(A27,Employees!$A$2:$I$1501,9,FALSE()),"Unknown") -> Engineering | Q27: =IF(H27<12,"<1 yr",IF(H27<36,"1-3 yrs",IF(H27<60,"3-5 yrs","5+ yrs"))) -> 1-3 yrs
A28: E10120 | C28: 46279 | D28: Involuntary | E28: Misconduct / Policy Violation | F28: 60 | G28: 0 | H28: 0.6 | I28: No | J28: No | K28: No | L28: No | M28: 64 | O28: =IF(C28="","",YEAR(C28)) -> 2026 | P28: =IFERROR(VLOOKUP(A28,Employees!$A$2:$I$1501,9,FALSE()),"Unknown") -> Finance | Q28: =IF(H28<12,"<1 yr",IF(H28<36,"1-3 yrs",IF(H28<60,"3-5 yrs","5+ yrs"))) -> <1 yr
A29: E10124 | B29: 46146 | C29: 46176 | D29: Voluntary | E29: Better Compensation | F29: 30 | G29: 9 | H29: 2.7 | I29: Yes | J29: Yes | K29: No | L29: Yes | M29: 76 | N29: MNC | O29: =IF(C29="","",YEAR(C29)) -> 2026 | P29: =IFERROR(VLOOKUP(A29,Employees!$A$2:$I$1501,9,FALSE()),"Unknown") -> Sales | Q29: =IF(H29<12,"<1 yr",IF(H29<36,"1-3 yrs",IF(H29<60,"3-5 yrs","5+ yrs"))) -> <1 yr
A30: E10125 | B30: 46199 | C30: 46229 | D30: Voluntary | E30: Manager Issues | F30: 30 | G30: 15 | H30: 2.7 | I30: Yes | J30: Yes | K30: Yes | L30: Yes | M30: 29 | N30: Startup | O30: =IF(C30="","",YEAR(C30)) -> 2026 | P30: =IFERROR(VLOOKUP(A30,Employees!$A$2:$I$1501,9,FALSE()),"Unknown") -> Human Resources | Q30: =IF(H30<12,"<1 yr",IF(H30<36,"1-3 yrs",IF(H30<60,"3-5 yrs","5+ yrs"))) -> <1 yr
A31: E10138 | B31: 44496 | C31: 44556 | D31: Voluntary | E31: Manager Issues | F31: 60 | G31: 60 | H31: 11.7 | I31: No | J31: Yes | K31: No | L31: Yes | M31: 26 | N31: MNC | O31: =IF(C31="","",YEAR(C31)) -> 2021 | P31: =IFERROR(VLOOKUP(A31,Employees!$A$2:$I$1501,9,FALSE()),"Unknown") -> Operations | Q31: =IF(H31<12,"<1 yr",IF(H31<36,"1-3 yrs",IF(H31<60,"3-5 yrs","5+ yrs"))) -> <1 yr
A32: E10145 | C32: 45540 | D32: Involuntary | E32: Restructuring / Layoff | F32: 30 | G32: 0 | H32: 4.4 | I32: No | J32: Yes | K32: No | L32: No | M32: 41 | O32: =IF(C32="","",YEAR(C32)) -> 2024 | P32: =IFERROR(VLOOKUP(A32,Employees!$A$2:$I$1501,9,FALSE()),"Unknown") -> Marketing | Q32: =IF(H32<12,"<1 yr",IF(H32<36,"1-3 yrs",IF(H32<60,"3-5 yrs","5+ yrs"))) -> <1 yr
A33: E10147 | B33: 44220 | C33: 44310 | D33: Voluntary | E33: Health / Personal | F33: 90 | G33: 90 | H33: 7.6 | I33: No | J33: Yes | K33: No | L33: Yes | M33: 19 | N33: Startup | O33: =IF(C33="","",YEAR(C33)) -> 2021 | P33: =IFERROR(VLOOKUP(A33,Employees!$A$2:$I$1501,9,FALSE()),"Unknown") -> Sales | Q33: =IF(H33<12,"<1 yr",IF(H33<36,"1-3 yrs",IF(H33<60,"3-5 yrs","5+ yrs"))) -> <1 yr
A34: E10150 | B34: 46249 | C34: 46279 | D34: Voluntary | E34: Better Compensation | F34: 30 | G34: 0 | H34: 0.8 | I34: No | J34: Yes | K34: No | L34: Yes | M34: 48 | N34: Not Disclosed | O34: =IF(C34="","",YEAR(C34)) -> 2026 | P34: =IFERROR(VLOOKUP(A34,Employees!$A$2:$I$1501,9,FALSE()),"Unknown") -> Operations | Q34: =IF(H34<12,"<1 yr",IF(H34<36,"1-3 yrs",IF(H34<60,"3-5 yrs","5+ yrs"))) -> <1 yr
A35: E10154 | B35: 46139 | C35: 46169 | D35: Voluntary | E35: Better Compensation | F35: 30 | G35: 30 | H35: 9.5 | I35: Yes | J35: Yes | K35: No | L35: Yes | M35: 25 | N35: Competitor | O35: =IF(C35="","",YEAR(C35)) -> 2026 | P35: =IFERROR(VLOOKUP(A35,Employees!$A$2:$I$1501,9,FALSE()),"Unknown") -> Sales | Q35: =IF(H35<12,"<1 yr",IF(H35<36,"1-3 yrs",IF(H35<60,"3-5 yrs","5+ yrs"))) -> <1 yr
A36: E10155 | C36: 45159 | D36: Involuntary | E36: Contract End | F36: 60 | G36: 0 | H36: 55.8 | I36: No | J36: No | K36: No | L36: No | M36: 71 | O36: =IF(C36="","",YEAR(C36)) -> 2023 | P36: =IFERROR(VLOOKUP(A36,Employees!$A$2:$I$1501,9,FALSE()),"Unknown") -> Finance | Q36: =IF(H36<12,"<1 yr",IF(H36<36,"1-3 yrs",IF(H36<60,"3-5 yrs","5+ yrs"))) -> 3-5 yrs
A37: E10159 | B37: 46098 | C37: 46158 | D37: Voluntary | E37: Relocation | F37: 60 | G37: 60 | H37: 6.1 | I37: Yes | J37: No | K37: No | L37: Yes | M37: 43 | N37: Competitor | O37: =IF(C37="","",YEAR(C37)) -> 2026 | P37: =IFERROR(VLOOKUP(A37,Employees!$A$2:$I$1501,9,FALSE()),"Unknown") -> Marketing | Q37: =IF(H37<12,"<1 yr",IF(H37<36,"1-3 yrs",IF(H37<60,"3-5 yrs","5+ yrs"))) -> <1 yr
A38: E10162 | B38: 45620 | C38: 45680 | D38: Voluntary | E38: Manager Issues | F38: 60 | G38: 60 | H38: 11.7 | I38: Yes | J38: Yes | K38: Yes | L38: Yes | M38: 38 | N38: MNC | O38: =IF(C38="","",YEAR(C38)) -> 2025 | P38: =IFERROR(VLOOKUP(A38,Employees!$A$2:$I$1501,9,FALSE()),"Unknown") -> Engineering | Q38: =IF(H38<12,"<1 yr",IF(H38<36,"1-3 yrs",IF(H38<60,"3-5 yrs","5+ yrs"))) -> <1 yr
A39: E10175 | B39: 46012 | C39: 46102 | D39: Voluntary | E39: Better Compensation | F39: 90 | G39: 0 | H39: 70.1 | I39: Yes | J39: Yes | K39: No | L39: Yes | M39: 36 | N39: Startup | O39: =IF(C39="","",YEAR(C39)) -> 2026 | P39: =IFERROR(VLOOKUP(A39,Employees!$A$2:$I$1501,9,FALSE()),"Unknown") -> Engineering | Q39: =IF(H39<12,"<1 yr",IF(H39<36,"1-3 yrs",IF(H39<60,"3-5 yrs","5+ yrs"))) -> 5+ yrs
A40: E10193 | C40: 46268 | D40: Involuntary | E40: Performance | F40: 60 | G40: 0 | H40: 8.8 | I40: No | J40: Yes | K40: No | L40: No | M40: 26 | O40: =IF(C40="","",YEAR(C40)) -> 2026 | P40: =IFERROR(VLOOKUP(A40,Employees!$A$2:$I$1501,9,FALSE()),"Unknown") -> Legal & Compliance | Q40: =IF(H40<12,"<1 yr",IF(H40<36,"1-3 yrs",IF(H40<60,"3-5 yrs","5+ yrs"))) -> <1 yr
A41: E10212 | B41: 45492 | C41: 45552 | D41: Voluntary | E41: Higher Studies | F41: 60 | G41: 18 | H41: 27.5 | I41: No | J41: Yes | K41: Yes | L41: Yes | M41: 12 | N41: Competitor | O41: =IF(C41="","",YEAR(C41)) -> 2024 | P41: =IFERROR(VLOOKUP(A41,Employees!$A$2:$I$1501,9,FALSE()),"Unknown") -> Operations | Q41: =IF(H41<12,"<1 yr",IF(H41<36,"1-3 yrs",IF(H41<60,"3-5 yrs","5+ yrs"))) -> 1-3 yrs
A42: E10216 | B42: 46135 | C42: 46195 | D42: Voluntary | E42: Career Growth | F42: 60 | G42: 60 | H42: 24 | I42: Yes | J42: No | K42: No | L42: Yes | M42: 17 | N42: Competitor | O42: =IF(C42="","",YEAR(C42)) -> 2026 | P42: =IFERROR(VLOOKUP(A42,Employees!$A$2:$I$1501,9,FALSE()),"Unknown") -> Customer Support | Q42: =IF(H42<12,"<1 yr",IF(H42<36,"1-3 yrs",IF(H42<60,"3-5 yrs","5+ yrs"))) -> 1-3 yrs
A43: E10217 | B43: 44424 | C43: 44454 | D43: Voluntary | E43: Toxic Culture | F43: 30 | G43: 30 | H43: 17.6 | I43: Yes | J43: Yes | K43: Yes | L43: Yes | M43: 24 | N43: Not Disclosed | O43: =IF(C43="","",YEAR(C43)) -> 2021 | P43: =IFERROR(VLOOKUP(A43,Employees!$A$2:$I$1501,9,FALSE()),"Unknown") -> Human Resources | Q43: =IF(H43<12,"<1 yr",IF(H43<36,"1-3 yrs",IF(H43<60,"3-5 yrs","5+ yrs"))) -> 1-3 yrs
A44: E10221 | B44: 46098 | C44: 46158 | D44: Voluntary | E44: Relocation | F44: 60 | G44: 18 | H44: 16.4 | I44: No | J44: Yes | K44: No | L44: Yes | M44: 35 | N44: Not Disclosed | O44: =IF(C44="","",YEAR(C44)) -> 2026 | P44: =IFERROR(VLOOKUP(A44,Employees!$A$2:$I$1501,9,FALSE()),"Unknown") -> Data & AI | Q44: =IF(H44<12,"<1 yr",IF(H44<36,"1-3 yrs",IF(H44<60,"3-5 yrs","5+ yrs"))) -> 1-3 yrs
A45: E10222 | B45: 46187 | C45: 46247 | D45: Voluntary | E45: Better Compensation | F45: 60 | G45: 0 | H45: 46.8 | I45: No | J45: Yes | K45: No | L45: Yes | M45: 71 | N45: Competitor | O45: =IF(C45="","",YEAR(C45)) -> 2026 | P45: =IFERROR(VLOOKUP(A45,Employees!$A$2:$I$1501,9,FALSE()),"Unknown") -> Engineering | Q45: =IF(H45<12,"<1 yr",IF(H45<36,"1-3 yrs",IF(H45<60,"3-5 yrs","5+ yrs"))) -> 3-5 yrs
A46: E10244 | B46: 42861 | C46: 42951 | D46: Voluntary | E46: Career Growth | F46: 90 | G46: 27 | H46: 31.9 | I46: No | J46: No | K46: Yes | L46: Yes | M46: 15 | N46: Not Working | O46: =IF(C46="","",YEAR(C46)) -> 2017 | P46: =IFERROR(VLOOKUP(A46,Employees!$A$2:$I$1501,9,FALSE()),"Unknown") -> Customer Support | Q46: =IF(H46<12,"<1 yr",IF(H46<36,"1-3 yrs",IF(H46<60,"3-5 yrs","5+ yrs"))) -> 1-3 yrs
A47: E10258 | C47: 44986 | D47: Involuntary | E47: Contract End | F47: 60 | G47: 0 | H47: 26.7 | I47: No | J47: No | K47: No | L47: No | M47: 38 | O47: =IF(C47="","",YEAR(C47)) -> 2023 | P47: =IFERROR(VLOOKUP(A47,Employees!$A$2:$I$1501,9,FALSE()),"Unknown") -> Human Resources | Q47: =IF(H47<12,"<1 yr",IF(H47<36,"1-3 yrs",IF(H47<60,"3-5 yrs","5+ yrs"))) -> 1-3 yrs
A48: E10261 | B48: 45583 | C48: 45643 | D48: Voluntary | E48: Better Compensation | F48: 60 | G48: 30 | H48: 18.1 | I48: Yes | J48: Yes | K48: No | L48: Yes | M48: 10 | N48: Not Working | O48: =IF(C48="","",YEAR(C48)) -> 2024 | P48: =IFERROR(VLOOKUP(A48,Employees!$A$2:$I$1501,9,FALSE()),"Unknown") -> Data & AI | Q48: =IF(H48<12,"<1 yr",IF(H48<36,"1-3 yrs",IF(H48<60,"3-5 yrs","5+ yrs"))) -> 1-3 yrs
A49: E10266 | B49: 45803 | C49: 45863 | D49: Voluntary | E49: Better Compensation | F49: 60 | G49: 60 | H49: 14.4 | I49: No | J49: No | K49: No | L49: Yes | M49: 43 | N49: Not Disclosed | O49: =IF(C49="","",YEAR(C49)) -> 2025 | P49: =IFERROR(VLOOKUP(A49,Employees!$A$2:$I$1501,9,FALSE()),"Unknown") -> Finance | Q49: =IF(H49<12,"<1 yr",IF(H49<36,"1-3 yrs",IF(H49<60,"3-5 yrs","5+ yrs"))) -> 1-3 yrs
A50: E10267 | C50: 45988 | D50: Involuntary | E50: Restructuring / Layoff | F50: 90 | G50: 0 | H50: 57.4 | I50: No | J50: Yes | K50: No | L50: No | M50: 55 | O50: =IF(C50="","",YEAR(C50)) -> 2025 | P50: =IFERROR(VLOOKUP(A50,Employees!$A$2:$I$1501,9,FALSE()),"Unknown") -> Sales | Q50: =IF(H50<12,"<1 yr",IF(H50<36,"1-3 yrs",IF(H50<60,"3-5 yrs","5+ yrs"))) -> 3-5 yrs
A51: E10288 | B51: 44159 | C51: 44249 | D51: Voluntary | E51: Better Compensation | F51: 90 | G51: 0 | H51: 36.3 | I51: No | J51: Yes | K51: No | L51: Yes | M51: 24 | N51: Startup | O51: =IF(C51="","",YEAR(C51)) -> 2021 | P51: =IFERROR(VLOOKUP(A51,Employees!$A$2:$I$1501,9,FALSE()),"Unknown") -> Engineering | Q51: =IF(H51<12,"<1 yr",IF(H51<36,"1-3 yrs",IF(H51<60,"3-5 yrs","5+ yrs"))) -> 3-5 yrs
A52: E10291 | B52: 43092 | C52: 43152 | D52: Voluntary | E52: Better Compensation | F52: 60 | G52: 0 | H52: 7 | I52: No | J52: Yes | K52: No | L52: Yes | M52: 38 | N52: Not Working | O52: =IF(C52="","",YEAR(C52)) -> 2018 | P52: =IFERROR(VLOOKUP(A52,Employees!$A$2:$I$1501,9,FALSE()),"Unknown") -> Engineering | Q52: =IF(H52<12,"<1 yr",IF(H52<36,"1-3 yrs",IF(H52<60,"3-5 yrs","5+ yrs"))) -> <1 yr
A53: E10294 | B53: 45788 | C53: 45848 | D53: Voluntary | E53: Better Compensation | F53: 60 | G53: 30 | H53: 47 | I53: Yes | J53: Yes | K53: Yes | L53: Yes | M53: 24 | N53: MNC | O53: =IF(C53="","",YEAR(C53)) -> 2025 | P53: =IFERROR(VLOOKUP(A53,Employees!$A$2:$I$1501,9,FALSE()),"Unknown") -> Customer Support | Q53: =IF(H53<12,"<1 yr",IF(H53<36,"1-3 yrs",IF(H53<60,"3-5 yrs","5+ yrs"))) -> 3-5 yrs
A54: E10299 | B54: 46225 | C54: 46285 | D54: Voluntary | E54: Better Compensation | F54: 60 | G54: 60 | H54: 1.2 | I54: No | J54: Yes | K54: No | L54: Yes | M54: 65 | N54: Not Working | O54: =IF(C54="","",YEAR(C54)) -> 2026 | P54: =IFERROR(VLOOKUP(A54,Employees!$A$2:$I$1501,9,FALSE()),"Unknown") -> Finance | Q54: =IF(H54<12,"<1 yr",IF(H54<36,"1-3 yrs",IF(H54<60,"3-5 yrs","5+ yrs"))) -> <1 yr
A55: E10302 | B55: 45158 | C55: 45248 | D55: Voluntary | E55: Relocation | F55: 90 | G55: 45 | H55: 4.2 | I55: Yes | J55: Yes | K55: No | L55: Yes | M55: 65 | N55: Startup | O55: =IF(C55="","",YEAR(C55)) -> 2023 | P55: =IFERROR(VLOOKUP(A55,Employees!$A$2:$I$1501,9,FALSE()),"Unknown") -> Sales | Q55: =IF(H55<12,"<1 yr",IF(H55<36,"1-3 yrs",IF(H55<60,"3-5 yrs","5+ yrs"))) -> <1 yr
A56: E10304 | B56: 46171 | C56: 46201 | D56: Voluntary | E56: Manager Issues | F56: 30 | G56: 30 | H56: 7.4 | I56: No | J56: Yes | K56: Yes | L56: Yes | M56: 48 | N56: Startup | O56: =IF(C56="","",YEAR(C56)) -> 2026 | P56: =IFERROR(VLOOKUP(A56,Employees!$A$2:$I$1501,9,FALSE()),"Unknown") -> Sales | Q56: =IF(H56<12,"<1 yr",IF(H56<36,"1-3 yrs",IF(H56<60,"3-5 yrs","5+ yrs"))) -> <1 yr
A57: E10312 | B57: 45746 | C57: 45836 | D57: Voluntary | E57: Career Growth | F57: 90 | G57: 90 | H57: 72.9 | I57: No | J57: Yes | K57: No | L57: No | M57: 36 | N57: Not Disclosed | O57: =IF(C57="","",YEAR(C57)) -> 2025 | P57: =IFERROR(VLOOKUP(A57,Employees!$A$2:$I$1501,9,FALSE()),"Unknown") -> Sales | Q57: =IF(H57<12,"<1 yr",IF(H57<36,"1-3 yrs",IF(H57<60,"3-5 yrs","5+ yrs"))) -> 5+ yrs
A58: E10313 | C58: 45539 | D58: Involuntary | E58: Performance | F58: 90 | G58: 0 | H58: 87.5 | I58: No | J58: Yes | K58: No | L58: No | M58: 34 | O58: =IF(C58="","",YEAR(C58)) -> 2024 | P58: =IFERROR(VLOOKUP(A58,Employees!$A$2:$I$1501,9,FALSE()),"Unknown") -> Operations | Q58: =IF(H58<12,"<1 yr",IF(H58<36,"1-3 yrs",IF(H58<60,"3-5 yrs","5+ yrs"))) -> 5+ yrs
A59: E10321 | B59: 45548 | C59: 45608 | D59: Voluntary | E59: Career Growth | F59: 60 | G59: 60 | H59: 8.8 | I59: Yes | J59: Yes | K59: No | L59: Yes | M59: 32 | N59: Not Disclosed | O59: =IF(C59="","",YEAR(C59)) -> 2024 | P59: =IFERROR(VLOOKUP(A59,Employees!$A$2:$I$1501,9,FALSE()),"Unknown") -> Data & AI | Q59: =IF(H59<12,"<1 yr",IF(H59<36,"1-3 yrs",IF(H59<60,"3-5 yrs","5+ yrs"))) -> <1 yr
A60: E10322 | B60: 44591 | C60: 44681 | D60: Voluntary | E60: Higher Studies | F60: 90 | G60: 45 | H60: 27.7 | I60: No | J60: No | K60: Yes | L60: Yes | M60: 24 | N60: MNC | O60: =IF(C60="","",YEAR(C60)) -> 2022 | P60: =IFERROR(VLOOKUP(A60,Employees!$A$2:$I$1501,9,FALSE()),"Unknown") -> Human Resources | Q60: =IF(H60<12,"<1 yr",IF(H60<36,"1-3 yrs",IF(H60<60,"3-5 yrs","5+ yrs"))) -> 1-3 yrs
A61: E10331 | B61: 44861 | C61: 44951 | D61: Voluntary | E61: Career Growth | F61: 90 | G61: 90 | H61: 71.6 | I61: No | J61: Yes | K61: Yes | L61: Yes | M61: 26 | N61: Not Working | O61: =IF(C61="","",YEAR(C61)) -> 2023 | P61: =IFERROR(VLOOKUP(A61,Employees!$A$2:$I$1501,9,FALSE()),"Unknown") -> Sales | Q61: =IF(H61<12,"<1 yr",IF(H61<36,"1-3 yrs",IF(H61<60,"3-5 yrs","5+ yrs"))) -> 5+ yrs
A62: E10337 | B62: 45661 | C62: 45721 | D62: Voluntary | E62: Career Growth | F62: 60 | G62: 60 | H62: 8.2 | I62: Yes | J62: Yes | K62: No | L62: Yes | M62: 11 | N62: Competitor | O62: =IF(C62="","",YEAR(C62)) -> 2025 | P62: =IFERROR(VLOOKUP(A62,Employees!$A$2:$I$1501,9,FALSE()),"Unknown") -> Engineering | Q62: =IF(H62<12,"<1 yr",IF(H62<36,"1-3 yrs",IF(H62<60,"3-5 yrs","5+ yrs"))) -> <1 yr
A63: E10339 | B63: 44315 | C63: 44405 | D63: Voluntary | E63: Toxic Culture | F63: 90 | G63: 90 | H63: 11.4 | I63: No | J63: No | K63: No | L63: Yes | M63: 23 | N63: MNC | O63: =IF(C63="","",YEAR(C63)) -> 2021 | P63: =IFERROR(VLOOKUP(A63,Employees!$A$2:$I$1501,9,FALSE()),"Unknown") -> Sales | Q63: =IF(H63<12,"<1 yr",IF(H63<36,"1-3 yrs",IF(H63<60,"3-5 yrs","5+ yrs"))) -> <1 yr
A64: E10341 | B64: 46199 | C64: 46259 | D64: Voluntary | E64: Manager Issues | F64: 60 | G64: 60 | H64: 1.8 | I64: Yes | J64: No | K64: No | L64: Yes | M64: 23 | N64: Not Working | O64: =IF(C64="","",YEAR(C64)) -> 2026 | P64: =IFERROR(VLOOKUP(A64,Employees!$A$2:$I$1501,9,FALSE()),"Unknown") -> Operations | Q64: =IF(H64<12,"<1 yr",IF(H64<36,"1-3 yrs",IF(H64<60,"3-5 yrs","5+ yrs"))) -> <1 yr
A65: E10352 | B65: 43702 | C65: 43792 | D65: Voluntary | E65: Career Growth | F65: 90 | G65: 0 | H65: 3.8 | I65: No | J65: Yes | K65: Yes | L65: Yes | M65: 21 | N65: Startup | O65: =IF(C65="","",YEAR(C65)) -> 2019 | P65: =IFERROR(VLOOKUP(A65,Employees!$A$2:$I$1501,9,FALSE()),"Unknown") -> Sales | Q65: =IF(H65<12,"<1 yr",IF(H65<36,"1-3 yrs",IF(H65<60,"3-5 yrs","5+ yrs"))) -> <1 yr
A66: E10356 | B66: 45601 | C66: 45661 | D66: Voluntary | E66: Toxic Culture | F66: 60 | G66: 60 | H66: 71.4 | I66: No | J66: Yes | K66: No | L66: Yes | M66: 8 | N66: Not Disclosed | O66: =IF(C66="","",YEAR(C66)) -> 2025 | P66: =IFERROR(VLOOKUP(A66,Employees!$A$2:$I$1501,9,FALSE()),"Unknown") -> Engineering | Q66: =IF(H66<12,"<1 yr",IF(H66<36,"1-3 yrs",IF(H66<60,"3-5 yrs","5+ yrs"))) -> 5+ yrs
A67: E10367 | C67: 45443 | D67: Involuntary | E67: Contract End | F67: 60 | G67: 0 | H67: 10.8 | I67: No | J67: No | K67: No | L67: No | M67: 4 | O67: =IF(C67="","",YEAR(C67)) -> 2024 | P67: =IFERROR(VLOOKUP(A67,Employees!$A$2:$I$1501,9,FALSE()),"Unknown") -> Data & AI | Q67: =IF(H67<12,"<1 yr",IF(H67<36,"1-3 yrs",IF(H67<60,"3-5 yrs","5+ yrs"))) -> <1 yr
A68: E10400 | C68: 45590 | D68: Involuntary | E68: Performance | F68: 60 | G68: 0 | H68: 11.2 | I68: No | J68: Yes | K68: No | L68: No | M68: 18 | O68: =IF(C68="","",YEAR(C68)) -> 2024 | P68: =IFERROR(VLOOKUP(A68,Employees!$A$2:$I$1501,9,FALSE()),"Unknown") -> Engineering | Q68: =IF(H68<12,"<1 yr",IF(H68<36,"1-3 yrs",IF(H68<60,"3-5 yrs","5+ yrs"))) -> <1 yr
A69: E10401 | C69: 45832 | D69: Involuntary | E69: Contract End | F69: 60 | G69: 0 | H69: 9.2 | I69: No | J69: Yes | K69: No | L69: No | M69: 40 | O69: =IF(C69="","",YEAR(C69)) -> 2025 | P69: =IFERROR(VLOOKUP(A69,Employees!$A$2:$I$1501,9,FALSE()),"Unknown") -> Engineering | Q69: =IF(H69<12,"<1 yr",IF(H69<36,"1-3 yrs",IF(H69<60,"3-5 yrs","5+ yrs"))) -> <1 yr
A70: E10404 | B70: 45540 | C70: 45570 | D70: Voluntary | E70: Better Compensation | F70: 30 | G70: 0 | H70: 18.2 | I70: No | J70: Yes | K70: No | L70: No | M70: 33 | N70: Competitor | O70: =IF(C70="","",YEAR(C70)) -> 2024 | P70: =IFERROR(VLOOKUP(A70,Employees!$A$2:$I$1501,9,FALSE()),"Unknown") -> Marketing | Q70: =IF(H70<12,"<1 yr",IF(H70<36,"1-3 yrs",IF(H70<60,"3-5 yrs","5+ yrs"))) -> 1-3 yrs
A71: E10405 | B71: 46232 | C71: 46262 | D71: Voluntary | E71: Manager Issues | F71: 30 | G71: 30 | H71: 4.8 | I71: No | J71: Yes | K71: No | L71: Yes | M71: 20 | N71: Competitor | O71: =IF(C71="","",YEAR(C71)) -> 2026 | P71: =IFERROR(VLOOKUP(A71,Employees!$A$2:$I$1501,9,FALSE()),"Unknown") -> Marketing | Q71: =IF(H71<12,"<1 yr",IF(H71<36,"1-3 yrs",IF(H71<60,"3-5 yrs","5+ yrs"))) -> <1 yr
A72: E10406 | B72: 45549 | C72: 45639 | D72: Voluntary | E72: Better Compensation | F72: 90 | G72: 90 | H72: 38.7 | I72: Yes | J72: Yes | K72: No | L72: Yes | M72: 12 | N72: Competitor | O72: =IF(C72="","",YEAR(C72)) -> 2024 | P72: =IFERROR(VLOOKUP(A72,Employees!$A$2:$I$1501,9,FALSE()),"Unknown") -> Operations | Q72: =IF(H72<12,"<1 yr",IF(H72<36,"1-3 yrs",IF(H72<60,"3-5 yrs","5+ yrs"))) -> 3-5 yrs
A73: E10407 | B73: 46209 | C73: 46269 | D73: Voluntary | E73: Better Compensation | F73: 60 | G73: 60 | H73: 3.6 | I73: Yes | J73: Yes | K73: No | L73: No | M73: 76 | N73: Not Disclosed | O73: =IF(C73="","",YEAR(C73)) -> 2026 | P73: =IFERROR(VLOOKUP(A73,Employees!$A$2:$I$1501,9,FALSE()),"Unknown") -> Legal & Compliance | Q73: =IF(H73<12,"<1 yr",IF(H73<36,"1-3 yrs",IF(H73<60,"3-5 yrs","5+ yrs"))) -> <1 yr
A74: E10412 | B74: 43950 | C74: 44040 | D74: Voluntary | E74: Better Compensation | F74: 90 | G74: 0 | H74: 25.6 | I74: No | J74: Yes | K74: No | L74: Yes | M74: 47 | N74: Not Disclosed | O74: =IF(C74="","",YEAR(C74)) -> 2020 | P74: =IFERROR(VLOOKUP(A74,Employees!$A$2:$I$1501,9,FALSE()),"Unknown") -> Sales | Q74: =IF(H74<12,"<1 yr",IF(H74<36,"1-3 yrs",IF(H74<60,"3-5 yrs","5+ yrs"))) -> 1-3 yrs
A75: E10416 | B75: 46248 | C75: 46278 | D75: Voluntary | E75: Toxic Culture | F75: 30 | G75: 15 | H75: 0.6 | I75: Yes | J75: Yes | K75: Yes | L75: Yes | M75: 33 | N75: MNC | O75: =IF(C75="","",YEAR(C75)) -> 2026 | P75: =IFERROR(VLOOKUP(A75,Employees!$A$2:$I$1501,9,FALSE()),"Unknown") -> Human Resources | Q75: =IF(H75<12,"<1 yr",IF(H75<36,"1-3 yrs",IF(H75<60,"3-5 yrs","5+ yrs"))) -> <1 yr
A76: E10418 | B76: 44559 | C76: 44619 | D76: Voluntary | E76: Career Growth | F76: 60 | G76: 18 | H76: 2.7 | I76: No | J76: Yes | K76: Yes | L76: No | M76: 32 | N76: Startup | O76: =IF(C76="","",YEAR(C76)) -> 2022 | P76: =IFERROR(VLOOKUP(A76,Employees!$A$2:$I$1501,9,FALSE()),"Unknown") -> Engineering | Q76: =IF(H76<12,"<1 yr",IF(H76<36,"1-3 yrs",IF(H76<60,"3-5 yrs","5+ yrs"))) -> <1 yr
A77: E10419 | B77: 46109 | C77: 46169 | D77: Voluntary | E77: Career Growth | F77: 60 | G77: 60 | H77: 9 | I77: No | J77: Yes | K77: No | L77: Yes | M77: 61 | N77: Startup | O77: =IF(C77="","",YEAR(C77)) -> 2026 | P77: =IFERROR(VLOOKUP(A77,Employees!$A$2:$I$1501,9,FALSE()),"Unknown") -> Engineering | Q77: =IF(H77<12,"<1 yr",IF(H77<36,"1-3 yrs",IF(H77<60,"3-5 yrs","5+ yrs"))) -> <1 yr
A78: E10424 | B78: 45914 | C78: 45974 | D78: Voluntary | E78: Better Compensation | F78: 60 | G78: 18 | H78: 30.9 | I78: Yes | J78: No | K78: Yes | L78: Yes | M78: 16 | N78: Not Working | O78: =IF(C78="","",YEAR(C78)) -> 2025 | P78: =IFERROR(VLOOKUP(A78,Employees!$A$2:$I$1501,9,FALSE()),"Unknown") -> Engineering | Q78: =IF(H78<12,"<1 yr",IF(H78<36,"1-3 yrs",IF(H78<60,"3-5 yrs","5+ yrs"))) -> 1-3 yrs
A79: E10435 | B79: 44821 | C79: 44911 | D79: Voluntary | E79: Toxic Culture | F79: 90 | G79: 90 | H79: 10.8 | I79: No | J79: Yes | K79: No | L79: Yes | M79: 46 | N79: Competitor | O79: =IF(C79="","",YEAR(C79)) -> 2022 | P79: =IFERROR(VLOOKUP(A79,Employees!$A$2:$I$1501,9,FALSE()),"Unknown") -> Sales | Q79: =IF(H79<12,"<1 yr",IF(H79<36,"1-3 yrs",IF(H79<60,"3-5 yrs","5+ yrs"))) -> <1 yr
A80: E10441 | C80: 45819 | D80: Involuntary | E80: Restructuring / Layoff | F80: 90 | G80: 0 | H80: 57.7 | I80: No | J80: No | K80: No | L80: No | M80: 83 | O80: =IF(C80="","",YEAR(C80)) -> 2025 | P80: =IFERROR(VLOOKUP(A80,Employees!$A$2:$I$1501,9,FALSE()),"Unknown") -> Sales | Q80: =IF(H80<12,"<1 yr",IF(H80<36,"1-3 yrs",IF(H80<60,"3-5 yrs","5+ yrs"))) -> 3-5 yrs
A81: E10446 | B81: 46016 | C81: 46106 | D81: Voluntary | E81: Better Compensation | F81: 90 | G81: 90 | H81: 60.8 | I81: No | J81: Yes | K81: No | L81: Yes | M81: 8 | N81: MNC | O81: =IF(C81="","",YEAR(C81)) -> 2026 | P81: =IFERROR(VLOOKUP(A81,Employees!$A$2:$I$1501,9,FALSE()),"Unknown") -> Engineering | Q81: =IF(H81<12,"<1 yr",IF(H81<36,"1-3 yrs",IF(H81<60,"3-5 yrs","5+ yrs"))) -> 5+ yrs
A82: E10449 | B82: 45809 | C82: 45869 | D82: Voluntary | E82: Work-Life Balance | F82: 60 | G82: 60 | H82: 7 | I82: Yes | J82: Yes | K82: No | L82: Yes | M82: 43 | N82: Not Working | O82: =IF(C82="","",YEAR(C82)) -> 2025 | P82: =IFERROR(VLOOKUP(A82,Employees!$A$2:$I$1501,9,FALSE()),"Unknown") -> Human Resources | Q82: =IF(H82<12,"<1 yr",IF(H82<36,"1-3 yrs",IF(H82<60,"3-5 yrs","5+ yrs"))) -> <1 yr
A83: E10454 | C83: 45349 | D83: Involuntary | E83: Misconduct / Policy Violation | F83: 60 | G83: 0 | H83: 23.4 | I83: No | J83: No | K83: No | L83: No | M83: 35 | O83: =IF(C83="","",YEAR(C83)) -> 2024 | P83: =IFERROR(VLOOKUP(A83,Employees!$A$2:$I$1501,9,FALSE()),"Unknown") -> Human Resources | Q83: =IF(H83<12,"<1 yr",IF(H83<36,"1-3 yrs",IF(H83<60,"3-5 yrs","5+ yrs"))) -> 1-3 yrs
A84: E10472 | B84: 42837 | C84: 42897 | D84: Voluntary | E84: Manager Issues | F84: 60 | G84: 30 | H84: 2.8 | I84: No | J84: Yes | K84: No | L84: Yes | M84: 25 | N84: MNC | O84: =IF(C84="","",YEAR(C84)) -> 2017 | P84: =IFERROR(VLOOKUP(A84,Employees!$A$2:$I$1501,9,FALSE()),"Unknown") -> Engineering | Q84: =IF(H84<12,"<1 yr",IF(H84<36,"1-3 yrs",IF(H84<60,"3-5 yrs","5+ yrs"))) -> <1 yr
A85: E10473 | B85: 46117 | C85: 46147 | D85: Voluntary | E85: Career Growth | F85: 30 | G85: 9 | H85: 75.8 | I85: Yes | J85: Yes | K85: No | L85: Yes | M85: 28 | N85: Not Disclosed | O85: =IF(C85="","",YEAR(C85)) -> 2026 | P85: =IFERROR(VLOOKUP(A85,Employees!$A$2:$I$1501,9,FALSE()),"Unknown") -> Customer Support | Q85: =IF(H85<12,"<1 yr",IF(H85<36,"1-3 yrs",IF(H85<60,"3-5 yrs","5+ yrs"))) -> 5+ yrs
A86: E10478 | B86: 45075 | C86: 45165 | D86: Voluntary | E86: Better Compensation | F86: 90 | G86: 0 | H86: 24.5 | I86: No | J86: Yes | K86: No | L86: Yes | M86: 35 | N86: Competitor | O86: =IF(C86="","",YEAR(C86)) -> 2023 | P86: =IFERROR(VLOOKUP(A86,Employees!$A$2:$I$1501,9,FALSE()),"Unknown") -> Sales | Q86: =IF(H86<12,"<1 yr",IF(H86<36,"1-3 yrs",IF(H86<60,"3-5 yrs","5+ yrs"))) -> 1-3 yrs
A87: E10484 | C87: 45366 | D87: Involuntary | E87: Performance | F87: 90 | G87: 0 | H87: 31.1 | I87: No | J87: Yes | K87: No | L87: No | M87: 37 | O87: =IF(C87="","",YEAR(C87)) -> 2024 | P87: =IFERROR(VLOOKUP(A87,Employees!$A$2:$I$1501,9,FALSE()),"Unknown") -> Sales | Q87: =IF(H87<12,"<1 yr",IF(H87<36,"1-3 yrs",IF(H87<60,"3-5 yrs","5+ yrs"))) -> 1-3 yrs
A88: E10491 | B88: 44804 | C88: 44834 | D88: Voluntary | E88: Better Compensation | F88: 30 | G88: 15 | H88: 5.9 | I88: No | J88: Yes | K88: Yes | L88: Yes | M88: 18 | N88: Not Working | O88: =IF(C88="","",YEAR(C88)) -> 2022 | P88: =IFERROR(VLOOKUP(A88,Employees!$A$2:$I$1501,9,FALSE()),"Unknown") -> Sales | Q88: =IF(H88<12,"<1 yr",IF(H88<36,"1-3 yrs",IF(H88<60,"3-5 yrs","5+ yrs"))) -> <1 yr
A89: E10492 | B89: 45843 | C89: 45903 | D89: Voluntary | E89: Career Growth | F89: 60 | G89: 60 | H89: 17.9 | I89: Yes | J89: Yes | K89: No | L89: Yes | M89: 44 | N89: Not Working | O89: =IF(C89="","",YEAR(C89)) -> 2025 | P89: =IFERROR(VLOOKUP(A89,Employees!$A$2:$I$1501,9,FALSE()),"Unknown") -> Operations | Q89: =IF(H89<12,"<1 yr",IF(H89<36,"1-3 yrs",IF(H89<60,"3-5 yrs","5+ yrs"))) -> 1-3 yrs
A90: E10493 | B90: 44635 | C90: 44725 | D90: Voluntary | E90: Better Compensation | F90: 90 | G90: 27 | H90: 78.9 | I90: No | J90: Yes | K90: No | L90: Yes | M90: 21 | N90: Competitor | O90: =IF(C90="","",YEAR(C90)) -> 2022 | P90: =IFERROR(VLOOKUP(A90,Employees!$A$2:$I$1501,9,FALSE()),"Unknown") -> Customer Support | Q90: =IF(H90<12,"<1 yr",IF(H90<36,"1-3 yrs",IF(H90<60,"3-5 yrs","5+ yrs"))) -> 5+ yrs
A91: E10498 | B91: 46233 | C91: 46293 | D91: Voluntary | E91: Job Role Mismatch | F91: 60 | G91: 0 | H91: 1.1 | I91: No | J91: Yes | K91: No | L91: Yes | M91: 75 | N91: Startup | O91: =IF(C91="","",YEAR(C91)) -> 2026 | P91: =IFERROR(VLOOKUP(A91,Employees!$A$2:$I$1501,9,FALSE()),"Unknown") -> Finance | Q91: =IF(H91<12,"<1 yr",IF(H91<36,"1-3 yrs",IF(H91<60,"3-5 yrs","5+ yrs"))) -> <1 yr
A92: E10506 | B92: 46253 | C92: 46283 | D92: Voluntary | E92: Career Growth | F92: 30 | G92: 9 | H92: 1 | I92: No | J92: Yes | K92: No | L92: Yes | M92: 55 | N92: Not Working | O92: =IF(C92="","",YEAR(C92)) -> 2026 | P92: =IFERROR(VLOOKUP(A92,Employees!$A$2:$I$1501,9,FALSE()),"Unknown") -> Customer Support | Q92: =IF(H92<12,"<1 yr",IF(H92<36,"1-3 yrs",IF(H92<60,"3-5 yrs","5+ yrs"))) -> <1 yr
A93: E10509 | B93: 45638 | C93: 45728 | D93: Voluntary | E93: Toxic Culture | F93: 90 | G93: 90 | H93: 96.5 | I93: Yes | J93: Yes | K93: No | L93: Yes | M93: 7 | N93: Not Working | O93: =IF(C93="","",YEAR(C93)) -> 2025 | P93: =IFERROR(VLOOKUP(A93,Employees!$A$2:$I$1501,9,FALSE()),"Unknown") -> Sales | Q93: =IF(H93<12,"<1 yr",IF(H93<36,"1-3 yrs",IF(H93<60,"3-5 yrs","5+ yrs"))) -> 5+ yrs
A94: E10526 | C94: 45793 | D94: Involuntary | E94: Performance | F94: 30 | G94: 0 | H94: 2.6 | I94: No | J94: Yes | K94: No | L94: No | M94: 12 | O94: =IF(C94="","",YEAR(C94)) -> 2025 | P94: =IFERROR(VLOOKUP(A94,Employees!$A$2:$I$1501,9,FALSE()),"Unknown") -> Operations | Q94: =IF(H94<12,"<1 yr",IF(H94<36,"1-3 yrs",IF(H94<60,"3-5 yrs","5+ yrs"))) -> <1 yr
A95: E10527 | B95: 42803 | C95: 42863 | D95: Voluntary | E95: Career Growth | F95: 60 | G95: 60 | H95: 7.6 | I95: No | J95: Yes | K95: No | L95: Yes | M95: 30 | N95: MNC | O95: =IF(C95="","",YEAR(C95)) -> 2017 | P95: =IFERROR(VLOOKUP(A95,Employees!$A$2:$I$1501,9,FALSE()),"Unknown") -> Customer Support | Q95: =IF(H95<12,"<1 yr",IF(H95<36,"1-3 yrs",IF(H95<60,"3-5 yrs","5+ yrs"))) -> <1 yr
A96: E10539 | B96: 45224 | C96: 45314 | D96: Voluntary | E96: Career Growth | F96: 90 | G96: 90 | H96: 111.4 | I96: No | J96: No | K96: No | L96: Yes | M96: 47 | N96: MNC | O96: =IF(C96="","",YEAR(C96)) -> 2024 | P96: =IFERROR(VLOOKUP(A96,Employees!$A$2:$I$1501,9,FALSE()),"Unknown") -> Data & AI | Q96: =IF(H96<12,"<1 yr",IF(H96<36,"1-3 yrs",IF(H96<60,"3-5 yrs","5+ yrs"))) -> 5+ yrs
A97: E10540 | B97: 44453 | C97: 44513 | D97: Voluntary | E97: Better Compensation | F97: 60 | G97: 60 | H97: 0.5 | I97: No | J97: Yes | K97: No | L97: Yes | M97: 27 | N97: MNC | O97: =IF(C97="","",YEAR(C97)) -> 2021 | P97: =IFERROR(VLOOKUP(A97,Employees!$A$2:$I$1501,9,FALSE()),"Unknown") -> Customer Support | Q97: =IF(H97<12,"<1 yr",IF(H97<36,"1-3 yrs",IF(H97<60,"3-5 yrs","5+ yrs"))) -> <1 yr
A98: E10546 | C98: 46275 | D98: Involuntary | E98: Misconduct / Policy Violation | F98: 60 | G98: 0 | H98: 1 | I98: No | J98: No | K98: No | L98: No | M98: 114 | O98: =IF(C98="","",YEAR(C98)) -> 2026 | P98: =IFERROR(VLOOKUP(A98,Employees!$A$2:$I$1501,9,FALSE()),"Unknown") -> Finance | Q98: =IF(H98<12,"<1 yr",IF(H98<36,"1-3 yrs",IF(H98<60,"3-5 yrs","5+ yrs"))) -> <1 yr
A99: E10552 | C99: 46165 | D99: Involuntary | E99: Misconduct / Policy Violation | F99: 90 | G99: 0 | H99: 9.9 | I99: No | J99: No | K99: No | L99: No | M99: 30 | O99: =IF(C99="","",YEAR(C99)) -> 2026 | P99: =IFERROR(VLOOKUP(A99,Employees!$A$2:$I$1501,9,FALSE()),"Unknown") -> Operations | Q99: =IF(H99<12,"<1 yr",IF(H99<36,"1-3 yrs",IF(H99<60,"3-5 yrs","5+ yrs"))) -> <1 yr
A100: E10558 | B100: 45476 | C100: 45566 | D100: Voluntary | E100: Better Compensation | F100: 90 | G100: 0 | H100: 90.3 | I100: No | J100: No | K100: No | L100: Yes | M100: 21 | N100: Not Working | O100: =IF(C100="","",YEAR(C100)) -> 2024 | P100: =IFERROR(VLOOKUP(A100,Employees!$A$2:$I$1501,9,FALSE()),"Unknown") -> Sales | Q100: =IF(H100<12,"<1 yr",IF(H100<36,"1-3 yrs",IF(H100<60,"3-5 yrs","5+ yrs"))) -> 5+ yrs
...

Sheet Exit_Reviews
A1: review_id | B1: employee_id | C1: exit_date | D1: department | E1: interview_mode | F1: stated_reason | G1: review_text | H1: rating_manager | I1: rating_culture | J1: rating_compensation | K1: rating_growth | L1: rating_worklife | M1: would_recommend | N1: would_return
A2: R00001 | B2: E10011 | C2: 45536 | D2: Engineering | E2: Online form | F2: Work-Life Balance | G2: Hybrid policy was withdrawn suddenly. Commute of 11 km daily is too much. Leadership communication is clear. | H2: 2 | I2: 5 | J2: 3 | K2: 3 | L2: 4 | M2: Yes | N2: Maybe
A3: R00002 | B3: E10017 | C3: 46283 | D3: Customer Support | E3: Online form | F3: Higher Studies | G3: Leaving to pursue a Master's degree abroad. The company supported me throughout. Leadership communication is clear. | H3: 1 | I3: 3 | J3: 3 | K3: 2 | L3: 4 | M3: Yes | N3: No
A4: R00003 | B4: E10018 | C4: 44388 | D4: Sales | E4: In-person | F4: Better Compensation | G4: Leaving mainly for money. Nothing against the company, I'd happily come back if the package matched. | H4: 4 | I4: 4 | J4: 2 | K4: 1 | L4: 3 | M4: Maybe | N4: Maybe
A5: R00004 | B5: E10036 | C5: 45758 | D5: Human Resources | E5: In-person | F5: Work-Life Balance | G5: Late-night calls with clients every day. The work is interesting but unsustainable. Leadership communication is clear. | H5: 2 | I5: 3 | J5: 2 | K5: 4 | L5: 3 | M5: No | N5: Yes
A6: R00005 | B6: E10038 | C6: 45337 | D6: Operations | E6: In-person | F6: Better Compensation | G6: I got an offer with a 30% hike. The work here was good but pay has not kept up with the market. Food and facilities were good. | H6: 4 | I6: 3 | J6: 1 | K6: 1 | L6: 4 | M6: Maybe | N6: No
A7: R00006 | B7: E10043 | C7: 45197 | D7: Operations | E7: Online form | F7: Career Growth | G7: I learned a lot here and am grateful, but I need bigger challenges now. Leadership communication is clear. | H7: 4 | I7: 4 | J7: 4 | K7: 2 | L7: 3 | M7: Maybe | N7: Yes
A8: R00007 | B8: E10056 | C8: 45909 | D8: Data & AI | E8: In-person | F8: Job Role Mismatch | G8: The role described in the interview was very different from actual work. Mostly doing manual tasks. | H8: 4 | I8: 5 | J8: 3 | K8: 3 | L8: 1 | M8: No | N8: Yes
A9: R00008 | B9: E10058 | C9: 46193 | D9: Customer Support | E9: In-person | F9: Health / Personal | G9: Family situation requires my full attention. HR was kind and flexible about the exit. | H9: 1 | I9: 3 | J9: 2 | K9: 2 | L9: 2 | M9: No | N9: Maybe
A10: R00009 | B10: E10062 | C10: 46217 | D10: Engineering | E10: Online form | F10: Better Compensation | G10: Salary revisions were very low this year. I liked my team but I have financial responsibilities. HR processes are slow. | H10: 3 | I10: 5 | J10: 3 | K10: 5 | L10: 5 | M10: No | N10: Maybe
A11: R00010 | B11: E10063 | C11: 45229 | D11: Sales | E11: Online form | F11: Higher Studies | G11: Going for MBA. Grateful for the experience, would recommend this company to freshers. Colleagues were very helpful. | H11: 3 | I11: 5 | J11: 4 | K11: 2 | L11: 2 | M11: Maybe | N11: No
A12: R00011 | B12: E10071 | C12: 46282 | D12: Sales | E12: In-person | F12: Work-Life Balance | G12: Weekend work became normal. I was burning out and missing family time. | H12: 4 | I12: 4 | J12: 1 | K12: 2 | L12: 5 | M12: Yes | N12: Maybe
A13: R00012 | B13: E10075 | C13: 45824 | D13: Engineering | E13: In-person | F13: Job Role Mismatch | G13: I joined for data science but ended up doing reporting. Mismatched expectations. HR processes are slow. | H13: 2 | I13: 5 | J13: 3 | K13: 1 | L13: 2 | M13: Maybe | N13: Yes
... A186: R00185 | B186: E11497 | C186: 46253 | D186: Human Resources | E186: Video call | F186: Career Growth | G186: No clear promotion path. I've been in the same role for 4 years despite good ratings. | H186: 5 | I186: 4 | J186: 3 | K186: 4 | L186: 4 | M186: Maybe | N186: Yes

Sheet Performance
A1: employee_id | B1: review_year | C1: performance_rating | D1: goals_achieved_pct | E1: promoted | F1: hike_pct | G1: training_hours | H1: department | I1: employment_status
A2: E10001 | B2: 2021 | C2: 3 | D2: 81 | E2: No | F2: 7.2 | G2: 55 | H2: =IFERROR(VLOOKUP(A2,Employees!$A$2:$I$1501,9,FALSE()),"Unknown") -> Sales | I2: =IFERROR(VLOOKUP(A2,Employees!$A$2:$U$1501,21,FALSE()),"Unknown") -> Active
A3: E10001 | B3: 2022 | C3: 3 | D3: 103 | E3: No | F3: 8.6 | G3: 40 | H3: =IFERROR(VLOOKUP(A3,Employees!$A$2:$I$1501,9,FALSE()),"Unknown") -> Sales | I3: =IFERROR(VLOOKUP(A3,Employees!$A$2:$U$1501,21,FALSE()),"Unknown") -> Active
A4: E10001 | B4: 2023 | C4: 2 | D4: 57 | E4: No | F4: 5.8 | G4: 22 | H4: =IFERROR(VLOOKUP(A4,Employees!$A$2:$I$1501,9,FALSE()),"Unknown") -> Sales | I4: =IFERROR(VLOOKUP(A4,Employees!$A$2:$U$1501,21,FALSE()),"Unknown") -> Active
A5: E10001 | B5: 2024 | C5: 4 | D5: 88 | E5: No | F5: 6.5 | G5: 28 | H5: =IFERROR(VLOOKUP(A5,Employees!$A$2:$I$1501,9,FALSE()),"Unknown") -> Sales | I5: =IFERROR(VLOOKUP(A5,Employees!$A$2:$U$1501,21,FALSE()),"Unknown") -> Active
A6: E10001 | B6: 2025 | C6: 3 | D6: 79 | E6: No | F6: 10.5 | G6: 9 | H6: =IFERROR(VLOOKUP(A6,Employees!$A$2:$I$1501,9,FALSE()),"Unknown") -> Sales | I6: =IFERROR(VLOOKUP(A6,Employees!$A$2:$U$1501,21,FALSE()),"Unknown") -> Active
A7: E10004 | B7: 2021 | C7: 3 | D7: 73 | E7: No | F7: 5 | G7: 39 | H7: =IFERROR(VLOOKUP(A7,Employees!$A$2:$I$1501,9,FALSE()),"Unknown") -> Engineering | I7: =IFERROR(VLOOKUP(A7,Employees!$A$2:$U$1501,21,FALSE()),"Unknown") -> Active
A8: E10004 | B8: 2022 | C8: 3 | D8: 85 | E8: No | F8: 5.6 | G8: 18 | H8: =IFERROR(VLOOKUP(A8,Employees!$A$2:$I$1501,9,FALSE()),"Unknown") -> Engineering | I8: =IFERROR(VLOOKUP(A8,Employees!$A$2:$U$1501,21,FALSE()),"Unknown") -> Active
A9: E10004 | B9: 2023 | C9: 4 | D9: 96 | E9: No | F9: 10 | G9: 6 | H9: =IFERROR(VLOOKUP(A9,Employees!$A$2:$I$1501,9,FALSE()),"Unknown") -> Engineering | I9: =IFERROR(VLOOKUP(A9,Employees!$A$2:$U$1501,21,FALSE()),"Unknown") -> Active
A10: E10004 | B10: 2024 | C10: 2 | D10: 67 | E10: No | F10: 7.3 | G10: 7 | H10: =IFERROR(VLOOKUP(A10,Employees!$A$2:$I$1501,9,FALSE()),"Unknown") -> Engineering | I10: =IFERROR(VLOOKUP(A10,Employees!$A$2:$U$1501,21,FALSE()),"Unknown") -> Active
A11: E10004 | B11: 2025 | C11: 3 | D11: 79 | E11: No | F11: 6.8 | G11: 45 | H11: =IFERROR(VLOOKUP(A11,Employees!$A$2:$I$1501,9,FALSE()),"Unknown") -> Engineering | I11: =IFERROR(VLOOKUP(A11,Employees!$A$2:$U$1501,21,FALSE()),"Unknown") -> Active
A12: E10005 | B12: 2025 | C12: 2 | D12: 74 | E12: No | F12: 5.2 | G12: 30 | H12: =IFERROR(VLOOKUP(A12,Employees!$A$2:$I$1501,9,FALSE()),"Unknown") -> Customer Support | I12: =IFERROR(VLOOKUP(A12,Employees!$A$2:$U$1501,21,FALSE()),"Unknown") -> Active
A13: E10006 | B13: 2023 | C13: 3 | D13: 87 | E13: No | F13: 6.5 | G13: 14 | H13: =IFERROR(VLOOKUP(A13,Employees!$A$2:$I$1501,9,FALSE()),"Unknown") -> Finance | I13: =IFERROR(VLOOKUP(A13,Employees!$A$2:$U$1501,21,FALSE()),"Unknown") -> Active
... A3701: E11500 | B3701: 2025 | C3701: 3 | D3701: 75 | E3701: No | F3701: 8.4 | G3701: 36 | H3701: =IFERROR(VLOOKUP(A3701,Employees!$A$2:$I$1501,9,FALSE()),"Unknown") -> Human Resources | I3701: =IFERROR(VLOOKUP(A3701,Employees!$A$2:$U$1501,21,FALSE()),"Unknown") -> Active

Sheet Engagement
A1: employee_id | B1: survey_year | C1: job_satisfaction | D1: environment_satisfaction | E1: relationship_with_manager | F1: work_life_balance | G1: recognition | H1: enps_score | I1: department
A2: E10818 | B2: 2024 | C2: 3 | D2: 3 | E2: 4 | F2: 3 | G2: 4 | H2: 10 | I2: =IFERROR(VLOOKUP(A2,Employees!$A$2:$I$1501,9,FALSE()),"Unknown") -> Engineering
A3: E10920 | B3: 2024 | C3: 5 | D3: 4 | E3: 4 | F3: 3 | G3: 4 | H3: 8 | I3: =IFERROR(VLOOKUP(A3,Employees!$A$2:$I$1501,9,FALSE()),"Unknown") -> Engineering
A4: E10563 | B4: 2024 | C4: 3 | D4: 5 | E4: 2 | F4: 3 | G4: 3 | H4: 9 | I4: =IFERROR(VLOOKUP(A4,Employees!$A$2:$I$1501,9,FALSE()),"Unknown") -> Engineering
A5: E10121 | B5: 2024 | C5: 3 | D5: 3 | E5: 3 | F5: 2 | G5: 5 | H5: 4 | I5: =IFERROR(VLOOKUP(A5,Employees!$A$2:$I$1501,9,FALSE()),"Unknown") -> Engineering
A6: E10226 | B6: 2024 | C6: 2 | D6: 4 | E6: 3 | F6: 3 | G6: 3 | H6: 9 | I6: =IFERROR(VLOOKUP(A6,Employees!$A$2:$I$1501,9,FALSE()),"Unknown") -> Engineering
A7: E11062 | B7: 2024 | C7: 3 | D7: 4 | E7: 3 | F7: 4 | G7: 4 | H7: 10 | I7: =IFERROR(VLOOKUP(A7,Employees!$A$2:$I$1501,9,FALSE()),"Unknown") -> Engineering
A8: E10994 | B8: 2024 | C8: 2 | D8: 3 | E8: 5 | F8: 4 | G8: 3 | H8: 7 | I8: =IFERROR(VLOOKUP(A8,Employees!$A$2:$I$1501,9,FALSE()),"Unknown") -> Engineering
A9: E11362 | B9: 2024 | C9: 4 | D9: 3 | E9: 4 | F9: 4 | G9: 2 | H9: 6 | I9: =IFERROR(VLOOKUP(A9,Employees!$A$2:$I$1501,9,FALSE()),"Unknown") -> Human Resources
A10: E11277 | B10: 2024 | C10: 3 | D10: 3 | E10: 4 | F10: 4 | G10: 3 | H10: 10 | I10: =IFERROR(VLOOKUP(A10,Employees!$A$2:$I$1501,9,FALSE()),"Unknown") -> Engineering
A11: E11208 | B11: 2024 | C11: 3 | D11: 5 | E11: 5 | F11: 2 | G11: 3 | H11: 6 | I11: =IFERROR(VLOOKUP(A11,Employees!$A$2:$I$1501,9,FALSE()),"Unknown") -> Finance
A12: E10378 | B12: 2024 | C12: 4 | D12: 4 | E12: 3 | F12: 3 | G12: 5 | H12: 6 | I12: =IFERROR(VLOOKUP(A12,Employees!$A$2:$I$1501,9,FALSE()),"Unknown") -> Engineering
A13: E10529 | B13: 2024 | C13: 4 | D13: 4 | E13: 4 | F13: 4 | G13: 5 | H13: 8 | I13: =IFERROR(VLOOKUP(A13,Employees!$A$2:$I$1501,9,FALSE()),"Unknown") -> Engineering
... A2375: E11151 | B2375: 2026 | C2375: 4 | D2375: 4 | E2375: 2 | F2375: 4 | G2375: 4 | H2375: 7 | I2375: =IFERROR(VLOOKUP(A2375,Employees!$A$2:$I$1501,9,FALSE()),"Unknown") -> Legal & Compliance

Sheet Compliance_Trainings
A1: employee_id | B1: training_name | C1: frequency_days | D1: due_date | E1: status | F1: completion_date | G1: score_pct
A2: E10001 | B2: POSH Awareness | C2: 365 | D2: 46331 | E2: Completed | F2: 46328 | G2: 98
A3: E10001 | B3: Code of Conduct | C3: 365 | D3: 46347 | E3: Completed | F3: 46328 | G3: 60
A4: E10001 | B4: Data Privacy & DPDP Act | C4: 365 | D4: 46117 | E4: Completed | F4: 46081 | G4: 61
A5: E10001 | B5: Information Security | C5: 180 | D5: 46267 | E5: Overdue
A6: E10001 | B6: Anti-Bribery | C6: 730 | D6: 46377 | E6: Overdue
A7: E10001 | B7: Fire & Safety | C7: 365 | D7: 46249 | E7: Completed | F7: 46241 | G7: 69
A8: E10002 | B8: POSH Awareness | C8: 365 | D8: 46154 | E8: Completed | F8: 46141 | G8: 72
A9: E10002 | B9: Code of Conduct | C9: 365 | D9: 46306 | E9: Completed | F9: 46301 | G9: 66
A10: E10002 | B10: Data Privacy & DPDP Act | C10: 365 | D10: 46224 | E10: Completed | F10: 46187 | G10: 81
A11: E10002 | B11: Information Security | C11: 180 | D11: 46259 | E11: Completed | F11: 46230 | G11: 77
A12: E10002 | B12: Anti-Bribery | C12: 730 | D12: 46165 | E12: Completed | F12: 46141 | G12: 88
A13: E10002 | B13: Fire & Safety | C13: 365 | D13: 46281 | E13: Completed | F13: 46278 | G13: 70
A14: E10003 | B14: POSH Awareness | C14: 365 | D14: 46337 | E14: Completed | F14: 46333 | G14: 93
A15: E10003 | B15: Code of Conduct | C15: 365 | D15: 46173 | E15: In Progress
A16: E10003 | B16: Data Privacy & DPDP Act | C16: 365 | D16: 46111 | E16: Completed | F16: 46081 | G16: 79
A17: E10003 | B17: Information Security | C17: 180 | D17: 46158 | E17: Completed | F17: 46129 | G17: 71
A18: E10003 | B18: Anti-Bribery | C18: 730 | D18: 46186 | E18: Completed | F18: 46176 | G18: 87
A19: E10003 | B19: Fire & Safety | C19: 365 | D19: 46278 | E19: Completed | F19: 46252 | G19: 86
A20: E10004 | B20: POSH Awareness | C20: 365 | D20: 46187 | E20: Completed | F20: 46162 | G20: 96
A21: E10004 | B21: Code of Conduct | C21: 365 | D21: 46365 | E21: Overdue
A22: E10004 | B22: Data Privacy & DPDP Act | C22: 365 | D22: 46347 | E22: Completed | F22: 46340 | G22: 91
A23: E10004 | B23: Information Security | C23: 180 | D23: 46374 | E23: Completed | F23: 46358 | G23: 70
A24: E10004 | B24: Anti-Bribery | C24: 730 | D24: 46107 | E24: Completed | F24: 46098 | G24: 77
A25: E10004 | B25: Fire & Safety | C25: 365 | D25: 46297 | E25: Completed | F25: 46295 | G25: 87
A26: E10005 | B26: POSH Awareness | C26: 365 | D26: 46263 | E26: Overdue
A27: E10005 | B27: Code of Conduct | C27: 365 | D27: 46289 | E27: Completed | F27: 46259 | G27: 65
A28: E10005 | B28: Data Privacy & DPDP Act | C28: 365 | D28: 46247 | E28: Overdue
A29: E10005 | B29: Information Security | C29: 180 | D29: 46117 | E29: Completed | F29: 46084 | G29: 91
A30: E10005 | B30: Anti-Bribery | C30: 730 | D30: 46118 | E30: Overdue
A31: E10005 | B31: Fire & Safety | C31: 365 | D31: 46359 | E31: Not Started
A32: E10006 | B32: POSH Awareness | C32: 365 | D32: 46377 | E32: Completed | F32: 46361 | G32: 79
A33: E10006 | B33: Code of Conduct | C33: 365 | D33: 46316 | E33: Completed | F33: 46283 | G33: 85
A34: E10006 | B34: Data Privacy & DPDP Act | C34: 365 | D34: 46248 | E34: Overdue
A35: E10006 | B35: Information Security | C35: 180 | D35: 46120 | E35: Completed | F35: 46107 | G35: 97
A36: E10006 | B36: Anti-Bribery | C36: 730 | D36: 46228 | E36: Completed | F36: 46221 | G36: 99
A37: E10006 | B37: Fire & Safety | C37: 365 | D37: 46230 | E37: In Progress
A38: E10009 | B38: POSH Awareness | C38: 365 | D38: 46201 | E38: Completed | F38: 46167 | G38: 74
A39: E10009 | B39: Code of Conduct | C39: 365 | D39: 46163 | E39: Completed | F39: 46128 | G39: 80
A40: E10009 | B40: Data Privacy & DPDP Act | C40: 365 | D40: 46291 | E40: Completed | F40: 46257 | G40: 94
A41: E10009 | B41: Information Security | C41: 180 | D41: 46247 | E41: Completed | F41: 46241 | G41: 61
A42: E10009 | B42: Anti-Bribery | C42: 730 | D42: 46115 | E42: Completed | F42: 46092 | G42: 83
A43: E10009 | B43: Fire & Safety | C43: 365 | D43: 46378 | E43: Completed | F43: 46342 | G43: 78
A44: E10010 | B44: POSH Awareness | C44: 365 | D44: 46217 | E44: Completed | F44: 46212 | G44: 72
A45: E10010 | B45: Code of Conduct | C45: 365 | D45: 46360 | E45: Completed | F45: 46321 | G45: 74
A46: E10010 | B46: Data Privacy & DPDP Act | C46: 365 | D46: 46137 | E46: Completed | F46: 46117 | G46: 86
A47: E10010 | B47: Information Security | C47: 180 | D47: 46293 | E47: Completed | F47: 46284 | G47: 62
A48: E10010 | B48: Anti-Bribery | C48: 730 | D48: 46128 | E48: Completed | F48: 46125 | G48: 91
A49: E10010 | B49: Fire & Safety | C49: 365 | D49: 46298 | E49: Completed | F49: 46286 | G49: 95
A50: E10012 | B50: POSH Awareness | C50: 365 | D50: 46116 | E50: In Progress
A51: E10012 | B51: Code of Conduct | C51: 365 | D51: 46295 | E51: Completed | F51: 46262 | G51: 93
A52: E10012 | B52: Data Privacy & DPDP Act | C52: 365 | D52: 46283 | E52: Completed | F52: 46267 | G52: 60
A53: E10012 | B53: Information Security | C53: 180 | D53: 46266 | E53: In Progress
A54: E10012 | B54: Anti-Bribery | C54: 730 | D54: 46137 | E54: Completed | F54: 46125 | G54: 62
A55: E10012 | B55: Fire & Safety | C55: 365 | D55: 46298 | E55: Completed | F55: 46295 | G55: 95
A56: E10013 | B56: POSH Awareness | C56: 365 | D56: 46142 | E56: In Progress
A57: E10013 | B57: Code of Conduct | C57: 365 | D57: 46170 | E57: Overdue
A58: E10013 | B58: Data Privacy & DPDP Act | C58: 365 | D58: 46157 | E58: Completed | F58: 46150 | G58: 67
A59: E10013 | B59: Information Security | C59: 180 | D59: 46240 | E59: Completed | F59: 46238 | G59: 81
A60: E10013 | B60: Anti-Bribery | C60: 730 | D60: 46128 | E60: Completed | F60: 46115 | G60: 99
A61: E10013 | B61: Fire & Safety | C61: 365 | D61: 46290 | E61: Completed | F61: 46263 | G61: 99
A62: E10014 | B62: POSH Awareness | C62: 365 | D62: 46318 | E62: Completed | F62: 46301 | G62: 81
A63: E10014 | B63: Code of Conduct | C63: 365 | D63: 46149 | E63: Not Started
A64: E10014 | B64: Data Privacy & DPDP Act | C64: 365 | D64: 46150 | E64: Completed | F64: 46119 | G64: 85
A65: E10014 | B65: Information Security | C65: 180 | D65: 46243 | E65: Completed | F65: 46225 | G65: 85
A66: E10014 | B66: Anti-Bribery | C66: 730 | D66: 46172 | E66: Completed | F66: 46147 | G66: 66
A67: E10014 | B67: Fire & Safety | C67: 365 | D67: 46288 | E67: Completed | F67: 46250 | G67: 73
A68: E10015 | B68: POSH Awareness | C68: 365 | D68: 46148 | E68: Completed | F68: 46139 | G68: 77
A69: E10015 | B69: Code of Conduct | C69: 365 | D69: 46358 | E69: Overdue
A70: E10015 | B70: Data Privacy & DPDP Act | C70: 365 | D70: 46241 | E70: Completed | F70: 46209 | G70: 76
A71: E10015 | B71: Information Security | C71: 180 | D71: 46255 | E71: Completed | F71: 46227 | G71: 93
A72: E10015 | B72: Anti-Bribery | C72: 730 | D72: 46219 | E72: Completed | F72: 46191 | G72: 86
A73: E10015 | B73: Fire & Safety | C73: 365 | D73: 46286 | E73: Completed | F73: 46266 | G73: 91
A74: E10016 | B74: POSH Awareness | C74: 365 | D74: 46188 | E74: Completed | F74: 46156 | G74: 94
A75: E10016 | B75: Code of Conduct | C75: 365 | D75: 46369 | E75: Completed | F75: 46350 | G75: 91
A76: E10016 | B76: Data Privacy & DPDP Act | C76: 365 | D76: 46353 | E76: In Progress
A77: E10016 | B77: Information Security | C77: 180 | D77: 46345 | E77: Completed | F77: 46313 | G77: 61
A78: E10016 | B78: Anti-Bribery | C78: 730 | D78: 46139 | E78: Overdue
A79: E10016 | B79: Fire & Safety | C79: 365 | D79: 46342 | E79: Completed | F79: 46308 | G79: 98
A80: E10019 | B80: POSH Awareness | C80: 365 | D80: 46245 | E80: Completed | F80: 46234 | G80: 73
A81: E10019 | B81: Code of Conduct | C81: 365 | D81: 46202 | E81: Completed | F81: 46178 | G81: 95
A82: E10019 | B82: Data Privacy & DPDP Act | C82: 365 | D82: 46381 | E82: Completed | F82: 46369 | G82: 90
A83: E10019 | B83: Information Security | C83: 180 | D83: 46188 | E83: In Progress
A84: E10019 | B84: Anti-Bribery | C84: 730 | D84: 46295 | E84: In Progress
A85: E10019 | B85: Fire & Safety | C85: 365 | D85: 46229 | E85: Completed | F85: 46196 | G85: 69
A86: E10020 | B86: POSH Awareness | C86: 365 | D86: 46165 | E86: Completed | F86: 46144 | G86: 81
A87: E10020 | B87: Code of Conduct | C87: 365 | D87: 46103 | E87: Completed | F87: 46101 | G87: 98
A88: E10020 | B88: Data Privacy & DPDP Act | C88: 365 | D88: 46303 | E88: Completed | F88: 46270 | G88: 63
A89: E10020 | B89: Information Security | C89: 180 | D89: 46317 | E89: In Progress
A90: E10020 | B90: Anti-Bribery | C90: 730 | D90: 46351 | E90: Completed | F90: 46343 | G90: 74
A91: E10020 | B91: Fire & Safety | C91: 365 | D91: 46156 | E91: Not Started
A92: E10021 | B92: POSH Awareness | C92: 365 | D92: 46219 | E92: Completed | F92: 46215 | G92: 76
A93: E10021 | B93: Code of Conduct | C93: 365 | D93: 46149 | E93: Overdue
A94: E10021 | B94: Data Privacy & DPDP Act | C94: 365 | D94: 46282 | E94: Completed | F94: 46260 | G94: 93
A95: E10021 | B95: Information Security | C95: 180 | D95: 46222 | E95: Completed | F95: 46194 | G95: 65
A96: E10021 | B96: Anti-Bribery | C96: 730 | D96: 46206 | E96: Completed | F96: 46199 | G96: 62
A97: E10021 | B97: Fire & Safety | C97: 365 | D97: 46207 | E97: Not Started
A98: E10022 | B98: POSH Awareness | C98: 365 | D98: 46341 | E98: Completed | F98: 46306 | G98: 94
A99: E10022 | B99: Code of Conduct | C99: 365 | D99: 46263 | E99: Completed | F99: 46261 | G99: 90
A100: E10022 | B100: Data Privacy & DPDP Act | C100: 365 | D100: 46175 | E100: Completed | F100: 46170 | G100: 71
...

Sheet Compliance_Records
A1: employee_id | B1: background_verification | C1: pf_uan_linked | D1: esi_applicable | E1: nda_signed | F1: policy_acknowledged | G1: grievances_raised | H1: posh_complaints | I1: disciplinary_actions
A2: E10001 | B2: Cleared | C2: Yes | D2: No | E2: Yes | F2: Yes | G2: 0 | H2: 0 | I2: 1
A3: E10002 | B3: Cleared | C3: Yes | D3: No | E3: Yes | F3: Yes | G3: 0 | H3: 0 | I3: 0
A4: E10003 | B4: Cleared | C4: Yes | D4: No | E4: Yes | F4: Yes | G4: 0 | H4: 0 | I4: 0
A5: E10004 | B5: Cleared | C5: Yes | D5: No | E5: Yes | F5: Yes | G5: 0 | H5: 0 | I5: 0
A6: E10005 | B6: Cleared | C6: Yes | D6: No | E6: Yes | F6: No | G6: 1 | H6: 0 | I6: 0
A7: E10006 | B7: Cleared | C7: Yes | D7: No | E7: Yes | F7: Yes | G7: 0 | H7: 0 | I7: 0
A8: E10007 | B8: Cleared | C8: Yes | D8: No | E8: Yes | F8: Yes | G8: 0 | H8: 0 | I8: 0
A9: E10008 | B9: Cleared | C9: Yes | D9: No | E9: Yes | F9: No | G9: 0 | H9: 0 | I9: 0
A10: E10009 | B10: Cleared | C10: Yes | D10: No | E10: Yes | F10: Yes | G10: 0 | H10: 0 | I10: 0
A11: E10010 | B11: Cleared | C11: Yes | D11: No | E11: Yes | F11: Yes | G11: 1 | H11: 0 | I11: 0
A12: E10011 | B12: Cleared | C12: Yes | D12: No | E12: Yes | F12: Yes | G12: 0 | H12: 0 | I12: 0
A13: E10012 | B13: Cleared | C13: Yes | D13: No | E13: Yes | F13: Yes | G13: 0 | H13: 0 | I13: 0
... A1501: E11500 | B1501: Cleared | C1501: Yes | D1501: No | E1501: Yes | F1501: Yes | G1501: 0 | H1501: 0 | I1501: 0

Sheet Attendance
A1: employee_id | B1: month | C1: working_days | D1: days_present | E1: sick_leave | F1: casual_leave | G1: unplanned_absence | H1: late_logins | I1: overtime_hours | J1: attendance_rate
A2: E10001 | B2: 2025-10 | C2: 22 | D2: 21 | E2: 1 | F2: 2 | G2: 1 | H2: 1 | I2: 1 | J2: =IF(C2=0,"",D2/C2) -> 0.95454545
A3: E10001 | B3: 2025-11 | C3: 22 | D3: 19 | E3: 0 | F3: 2 | G3: 0 | H3: 3 | I3: 1 | J3: =IF(C3=0,"",D3/C3) -> 0.86363636
A4: E10001 | B4: 2025-12 | C4: 22 | D4: 18 | E4: 1 | F4: 0 | G4: 0 | H4: 0 | I4: 1 | J4: =IF(C4=0,"",D4/C4) -> 0.81818182
A5: E10001 | B5: 2026-01 | C5: 22 | D5: 19 | E5: 0 | F5: 0 | G5: 0 | H5: 2 | I5: 3 | J5: =IF(C5=0,"",D5/C5) -> 0.86363636
A6: E10001 | B6: 2026-02 | C6: 22 | D6: 19 | E6: 2 | F6: 0 | G6: 0 | H6: 1 | I6: 1 | J6: =IF(C6=0,"",D6/C6) -> 0.86363636
A7: E10001 | B7: 2026-03 | C7: 22 | D7: 20 | E7: 0 | F7: 0 | G7: 0 | H7: 0 | I7: 0 | J7: =IF(C7=0,"",D7/C7) -> 0.90909091
A8: E10001 | B8: 2026-04 | C8: 22 | D8: 19 | E8: 4 | F8: 0 | G8: 0 | H8: 1 | I8: 1 | J8: =IF(C8=0,"",D8/C8) -> 0.86363636
A9: E10001 | B9: 2026-05 | C9: 22 | D9: 19 | E9: 2 | F9: 0 | G9: 0 | H9: 0 | I9: 2 | J9: =IF(C9=0,"",D9/C9) -> 0.86363636
A10: E10001 | B10: 2026-06 | C10: 22 | D10: 20 | E10: 0 | F10: 0 | G10: 0 | H10: 3 | I10: 0 | J10: =IF(C10=0,"",D10/C10) -> 0.90909091
A11: E10001 | B11: 2026-07 | C11: 22 | D11: 22 | E11: 1 | F11: 1 | G11: 0 | H11: 1 | I11: 0 | J11: =IF(C11=0,"",D11/C11) -> 1
A12: E10001 | B12: 2026-08 | C12: 22 | D12: 22 | E12: 0 | F12: 0 | G12: 0 | H12: 1 | I12: 0 | J12: =IF(C12=0,"",D12/C12) -> 1
A13: E10001 | B13: 2026-09 | C13: 22 | D13: 18 | E13: 0 | F13: 0 | G13: 0 | H13: 3 | I13: 0 | J13: =IF(C13=0,"",D13/C13) -> 0.81818182
... A13892: E11500 | B13892: 2026-09 | C13892: 22 | D13892: 21 | E13892: 0 | F13892: 0 | G13892: 1 | H13892: 0 | I13892: 1 | J13892: =IF(C13892=0,"",D13892/C13892) -> 0.95454545

Sheet Recruitment
A1: requisition_id | B1: hired_employee_id | C1: department | D1: job_role | E1: req_open_date | F1: offer_date | G1: join_date | H1: applicants | I1: interviews | J1: offers_made | K1: cost_per_hire_inr | L1: source | M1: time_to_offer_days | N1: time_to_hire_days
A2: REQ00001 | B2: E10001 | C2: Sales | D2: Sales Executive | E2: 43895 | F2: 43899 | G2: 43925 | H2: 20 | I2: 12 | J2: 1 | K2: 62004 | L2: Consultant | M2: =IF(OR(E2="",F2=""),"",F2-E2) -> 4 | N2: =IF(OR(E2="",G2=""),"",G2-E2) -> 30
A3: REQ00002 | B3: E10002 | C3: Marketing | D3: Marketing Executive | E3: 46063 | F3: 46089 | G3: 46129 | H3: 120 | I3: 11 | J3: 1 | K3: 30228 | L3: Referral | M3: =IF(OR(E3="",F3=""),"",F3-E3) -> 26 | N3: =IF(OR(E3="",G3=""),"",G3-E3) -> 66
A4: REQ00003 | B4: E10003 | C4: Sales | D4: Sales Executive | E4: 46170 | F4: 46225 | G4: 46245 | H4: 109 | I4: 14 | J4: 2 | K4: 38388 | L4: Referral | M4: =IF(OR(E4="",F4=""),"",F4-E4) -> 55 | N4: =IF(OR(E4="",G4=""),"",G4-E4) -> 75
A5: REQ00004 | B5: E10004 | C5: Engineering | D5: QA Engineer | E5: 44071 | F5: 44043 | G5: 44101 | H5: 133 | I5: 10 | J5: 3 | K5: 23976 | L5: Campus | M5: =IF(OR(E5="",F5=""),"",F5-E5) -> -28 | N5: =IF(OR(E5="",G5=""),"",G5-E5) -> 30
A6: REQ00005 | B6: E10005 | C6: Customer Support | D6: Support Associate | E6: 45574 | F6: 45556 | G6: 45609 | H6: 118 | I6: 7 | J6: 2 | K6: 24136 | L6: Campus | M6: =IF(OR(E6="",F6=""),"",F6-E6) -> -18 | N6: =IF(OR(E6="",G6=""),"",G6-E6) -> 35
A7: REQ00006 | B7: E10006 | C7: Finance | D7: Accountant | E7: 44754 | F7: 44760 | G7: 44794 | H7: 97 | I7: 6 | J7: 3 | K7: 14172 | L7: Job Portal | M7: =IF(OR(E7="",F7=""),"",F7-E7) -> 6 | N7: =IF(OR(E7="",G7=""),"",G7-E7) -> 40
A8: REQ00007 | B8: E10007 | C8: Data & AI | D8: Data Analyst | E8: 44828 | F8: 44879 | G8: 44904 | H8: 37 | I8: 5 | J8: 1 | K8: 40184 | L8: Job Portal | M8: =IF(OR(E8="",F8=""),"",F8-E8) -> 51 | N8: =IF(OR(E8="",G8=""),"",G8-E8) -> 76
A9: REQ00008 | B9: E10008 | C9: Engineering | D9: DevOps Engineer | E9: 44929 | F9: 44953 | G9: 44975 | H9: 87 | I9: 11 | J9: 1 | K9: 13136 | L9: Campus | M9: =IF(OR(E9="",F9=""),"",F9-E9) -> 24 | N9: =IF(OR(E9="",G9=""),"",G9-E9) -> 46
A10: REQ00009 | B10: E10009 | C10: Customer Support | D10: Senior Support Associate | E10: 45030 | F10: 45049 | G10: 45064 | H10: 67 | I10: 10 | J10: 1 | K10: 30844 | L10: Campus | M10: =IF(OR(E10="",F10=""),"",F10-E10) -> 19 | N10: =IF(OR(E10="",G10=""),"",G10-E10) -> 34
A11: REQ00010 | B11: E10010 | C11: Engineering | D11: Tech Lead | E11: 44975 | F11: 45025 | G11: 45048 | H11: 52 | I11: 4 | J11: 1 | K11: 28895 | L11: Job Portal | M11: =IF(OR(E11="",F11=""),"",F11-E11) -> 50 | N11: =IF(OR(E11="",G11=""),"",G11-E11) -> 73
A12: REQ00011 | B12: E10011 | C12: Engineering | D12: DevOps Engineer | E12: 42288 | F12: 42315 | G12: 42367 | H12: 49 | I12: 10 | J12: 3 | K12: 32430 | L12: Referral | M12: =IF(OR(E12="",F12=""),"",F12-E12) -> 27 | N12: =IF(OR(E12="",G12=""),"",G12-E12) -> 79
A13: REQ00012 | B13: E10012 | C13: Engineering | D13: Tech Lead | E13: 44882 | F13: 44883 | G13: 44923 | H13: 96 | I13: 4 | J13: 3 | K13: 24340 | L13: Job Portal | M13: =IF(OR(E13="",F13=""),"",F13-E13) -> 1 | N13: =IF(OR(E13="",G13=""),"",G13-E13) -> 41
... A1501: REQ01500 | B1501: E11500 | C1501: Human Resources | D1501: HR Business Partner | E1501: 44736 | F1501: 44723 | G1501: 44780 | H1501: 48 | I1501: 9 | J1501: 1 | K1501: 33988 | L1501: Referral | M1501: =IF(OR(E1501="",F1501=""),"",F1501-E1501) -> -13 | N1501: =IF(OR(E1501="",G1501=""),"",G1501-E1501) -> 44
